Workbook
Name SegmentaçãodeDados_Mês: #N/A
Name SegmentaçãodeDados_Mês1: #N/A
Name SegmentaçãodeDados_Mês2: #N/A
Name SegmentaçãodeDados_Quinzena: #N/A
Name SegmentaçãodeDados_Quinzena1: #N/A
Name SegmentaçãodeDados_Selecione_o_Usuário: #N/A
Name SegmentaçãodeDados_Selecione_o_Usuário1: #N/A

Sheet Consolidado a Pagar
B1: NOTA: após confirmação de pagamento copiar a tabela abaixo como valores na aba histórico | K1: TODOS POSSUEM UM ADIANTAMENTO INICIAL DE 500,00 QUE SÓ SERÁ FINALIZADO QUANDO TIVER DESLIGAMENTO
B3: ='Por Supervisor'!$B$2&" "&'Por Supervisor'!$B$1 -> 1ª Quinzena SETEMBRO | K3: *Não precisa reembolso
B4: Matricula | C4: Nome | D4: FUNÇÃO | E4: C.Custo | F4: Valor KM | G4: Pedagio | H4: Estacionamento | I4: Diversas | J4: TT Reembolsavel | K4: Hotel* | L4: Adiantamento / Saldo | M4: Valor a depositar | N4: Obs
B5: MZ-322052 | C5: CAMILA CRISTINE ALTHOFF | D5: Supervisor | E5: 2907 | F5: =SUMIFS('Por Supervisor'!F:F,'Por Supervisor'!$A:$A,Tabela2[[#This Row],[Nome]]) -> 999.99 | G5: =SUMIFS('Por Supervisor'!G:G,'Por Supervisor'!$A:$A,Tabela2[[#This Row],[Nome]]) -> 28.5 | H5: =SUMIFS('Por Supervisor'!H:H,'Por Supervisor'!$A:$A,Tabela2[[#This Row],[Nome]]) -> 0 | I5: =SUMIFS('Por Supervisor'!I:I,'Por Supervisor'!$A:$A,Tabela2[[#This Row],[Nome]]) -> 43 | J5: =SUM(Tabela2[[#This Row],[Valor KM]:[Diversas]]) -> 1071.49 | K5: =SUMIFS('Por Supervisor'!K:K,'Por Supervisor'!$A:$A,Tabela2[[#This Row],[Nome]]) -> 0 | M5: =IF(AND(J5=0,Tabela2[[#This Row],[Adiantamento / Saldo]]=""),"-",(Tabela2[[#This Row],[TT Reembolsavel]]+Tabela2[[#This Row],[Adiantamento / Saldo]])) -> 1071.49
B6: MZ-331203 | C6: THAYS APARECIDA CARVALHO | D6: Supervisor | E6: 2907 | F6: =SUMIFS('Por Supervisor'!F:F,'Por Supervisor'!$A:$A,Tabela2[[#This Row],[Nome]]) -> 755.22 | G6: =SUMIFS('Por Supervisor'!G:G,'Por Supervisor'!$A:$A,Tabela2[[#This Row],[Nome]]) -> 0 | H6: =SUMIFS('Por Supervisor'!H:H,'Por Supervisor'!$A:$A,Tabela2[[#This Row],[Nome]]) -> 0 | I6: =SUMIFS('Por Supervisor'!I:I,'Por Supervisor'!$A:$A,Tabela2[[#This Row],[Nome]]) -> 0 | J6: =SUM(Tabela2[[#This Row],[Valor KM]:[Diversas]]) -> 755.22 | K6: =SUMIFS('Por Supervisor'!K:K,'Por Supervisor'!$A:$A,Tabela2[[#This Row],[Nome]]) -> 0 | M6: =IF(AND(J6=0,Tabela2[[#This Row],[Adiantamento / Saldo]]=""),"-",(Tabela2[[#This Row],[TT Reembolsavel]]+Tabela2[[#This Row],[Adiantamento / Saldo]])) -> 755.22
B7: MZ-335327 | C7: GEOVANA DUARTE FARIAS | D7: Supervisor | E7: 2907 | F7: =SUMIFS('Por Supervisor'!F:F,'Por Supervisor'!$A:$A,Tabela2[[#This Row],[Nome]]) -> 763.83 | G7: =SUMIFS('Por Supervisor'!G:G,'Por Supervisor'!$A:$A,Tabela2[[#This Row],[Nome]]) -> 5.7 | H7: =SUMIFS('Por Supervisor'!H:H,'Por Supervisor'!$A:$A,Tabela2[[#This Row],[Nome]]) -> 0 | I7: =SUMIFS('Por Supervisor'!I:I,'Por Supervisor'!$A:$A,Tabela2[[#This Row],[Nome]]) -> 0 | J7: =SUM(Tabela2[[#This Row],[Valor KM]:[Diversas]]) -> 769.53 | K7: =SUMIFS('Por Supervisor'!K:K,'Por Supervisor'!$A:$A,Tabela2[[#This Row],[Nome]]) -> 0 | M7: =IF(AND(J7=0,Tabela2[[#This Row],[Adiantamento / Saldo]]=""),"-",(Tabela2[[#This Row],[TT Reembolsavel]]+Tabela2[[#This Row],[Adiantamento / Saldo]])) -> 769.53
B8: MZ-332404 | C8: GUSTAVO MATHEUS DE OLIVEIRA | D8: Supervisor | E8: 2907 | F8: =SUMIFS('Por Supervisor'!F:F,'Por Supervisor'!$A:$A,Tabela2[[#This Row],[Nome]]) -> 313.65 | G8: =SUMIFS('Por Supervisor'!G:G,'Por Supervisor'!$A:$A,Tabela2[[#This Row],[Nome]]) -> 0 | H8: =SUMIFS('Por Supervisor'!H:H,'Por Supervisor'!$A:$A,Tabela2[[#This Row],[Nome]]) -> 0 | I8: =SUMIFS('Por Supervisor'!I:I,'Por Supervisor'!$A:$A,Tabela2[[#This Row],[Nome]]) -> 0 | J8: =SUM(Tabela2[[#This Row],[Valor KM]:[Diversas]]) -> 313.65 | K8: =SUMIFS('Por Supervisor'!K:K,'Por Supervisor'!$A:$A,Tabela2[[#This Row],[Nome]]) -> 0 | M8: =IF(AND(J8=0,Tabela2[[#This Row],[Adiantamento / Saldo]]=""),"-",(Tabela2[[#This Row],[TT Reembolsavel]]+Tabela2[[#This Row],[Adiantamento / Saldo]])) -> 313.65
B9: MZ-333609 | C9: MATHEUS DA SILVA MORAES | D9: Supervisor | E9: 2907 | F9: =SUMIFS('Por Supervisor'!F:F,'Por Supervisor'!$A:$A,Tabela2[[#This Row],[Nome]]) -> 687.57 | G9: =SUMIFS('Por Supervisor'!G:G,'Por Supervisor'!$A:$A,Tabela2[[#This Row],[Nome]]) -> 0 | H9: =SUMIFS('Por Supervisor'!H:H,'Por Supervisor'!$A:$A,Tabela2[[#This Row],[Nome]]) -> 0 | I9: =SUMIFS('Por Supervisor'!I:I,'Por Supervisor'!$A:$A,Tabela2[[#This Row],[Nome]]) -> 0 | J9: =SUM(Tabela2[[#This Row],[Valor KM]:[Diversas]]) -> 687.57 | K9: =SUMIFS('Por Supervisor'!K:K,'Por Supervisor'!$A:$A,Tabela2[[#This Row],[Nome]]) -> 0 | M9: =IF(AND(J9=0,Tabela2[[#This Row],[Adiantamento / Saldo]]=""),"-",(Tabela2[[#This Row],[TT Reembolsavel]]+Tabela2[[#This Row],[Adiantamento / Saldo]])) -> 687.57
B10: MZ-332790 | C10: RICARDO ALEXANDRE LOMBARDI | D10: Supervisor | E10: 2907 | F10: =SUMIFS('Por Supervisor'!F:F,'Por Supervisor'!$A:$A,Tabela2[[#This Row],[Nome]]) -> 321.03 | G10: =SUMIFS('Por Supervisor'!G:G,'Por Supervisor'!$A:$A,Tabela2[[#This Row],[Nome]]) -> 0 | H10: =SUMIFS('Por Supervisor'!H:H,'Por Supervisor'!$A:$A,Tabela2[[#This Row],[Nome]]) -> 0 | I10: =SUMIFS('Por Supervisor'!I:I,'Por Supervisor'!$A:$A,Tabela2[[#This Row],[Nome]]) -> 0 | J10: =SUM(Tabela2[[#This Row],[Valor KM]:[Diversas]]) -> 321.03 | K10: =SUMIFS('Por Supervisor'!K:K,'Por Supervisor'!$A:$A,Tabela2[[#This Row],[Nome]]) -> 0 | M10: =IF(AND(J10=0,Tabela2[[#This Row],[Adiantamento / Saldo]]=""),"-",(Tabela2[[#This Row],[TT Reembolsavel]]+Tabela2[[#This Row],[Adiantamento / Saldo]])) -> 321.03
B11: MZ-333502 | C11: SAIDDA KAULE ABDALA | D11: Coordenador | E11: 2907 | F11: =SUMIFS('Por Supervisor'!F:F,'Por Supervisor'!$A:$A,Tabela2[[#This Row],[Nome]]) -> 0 | G11: =SUMIFS('Por Supervisor'!G:G,'Por Supervisor'!$A:$A,Tabela2[[#This Row],[Nome]]) -> 0 | H11: =SUMIFS('Por Supervisor'!H:H,'Por Supervisor'!$A:$A,Tabela2[[#This Row],[Nome]]) -> 0 | I11: =SUMIFS('Por Supervisor'!I:I,'Por Supervisor'!$A:$A,Tabela2[[#This Row],[Nome]]) -> 0 | J11: =SUM(Tabela2[[#This Row],[Valor KM]:[Diversas]]) -> 0 | K11: =SUMIFS('Por Supervisor'!K:K,'Por Supervisor'!$A:$A,Tabela2[[#This Row],[Nome]]) -> 0 | M11: =IF(AND(J11=0,Tabela2[[#This Row],[Adiantamento / Saldo]]=""),"-",(Tabela2[[#This Row],[TT Reembolsavel]]+Tabela2[[#This Row],[Adiantamento / Saldo]])) -> -
B12: MZ-333871 | C12: CARLOS PROENÇA | D12: Supervisor | E12: 2907 | F12: =SUMIFS('Por Supervisor'!F:F,'Por Supervisor'!$A:$A,Tabela2[[#This Row],[Nome]]) -> 977.85 | G12: =SUMIFS('Por Supervisor'!G:G,'Por Supervisor'!$A:$A,Tabela2[[#This Row],[Nome]]) -> 33.8 | H12: =SUMIFS('Por Supervisor'!H:H,'Por Supervisor'!$A:$A,Tabela2[[#This Row],[Nome]]) -> 0 | I12: =SUMIFS('Por Supervisor'!I:I,'Por Supervisor'!$A:$A,Tabela2[[#This Row],[Nome]]) -> 0 | J12: =SUM(Tabela2[[#This Row],[Valor KM]:[Diversas]]) -> 1011.65 | M12: =IF(AND(J12=0,Tabela2[[#This Row],[Adiantamento / Saldo]]=""),"-",(Tabela2[[#This Row],[TT Reembolsavel]]+Tabela2[[#This Row],[Adiantamento / Saldo]])) -> 1011.65
B13: MZ-333812 | C13: JOÃO MARTINS NETO | D13: Supervisor | E13: 2907 | F13: =SUMIFS('Por Supervisor'!F:F,'Por Supervisor'!$A:$A,Tabela2[[#This Row],[Nome]]) -> 626.07 | G13: =SUMIFS('Por Supervisor'!G:G,'Por Supervisor'!$A:$A,Tabela2[[#This Row],[Nome]]) -> 11.4 | H13: =SUMIFS('Por Supervisor'!H:H,'Por Supervisor'!$A:$A,Tabela2[[#This Row],[Nome]]) -> 0 | I13: =SUMIFS('Por Supervisor'!I:I,'Por Supervisor'!$A:$A,Tabela2[[#This Row],[Nome]]) -> 0 | J13: =SUM(Tabela2[[#This Row],[Valor KM]:[Diversas]]) -> 637.47 | K13: =SUMIFS('Por Supervisor'!K:K,'Por Supervisor'!$A:$A,Tabela2[[#This Row],[Nome]]) -> 0 | M13: =IF(AND(J13=0,Tabela2[[#This Row],[Adiantamento / Saldo]]=""),"-",(Tabela2[[#This Row],[TT Reembolsavel]]+Tabela2[[#This Row],[Adiantamento / Saldo]])) -> 637.47
B14: MZ-327723 | C14: ANDERSON MICHALSKI FERREIRA | D14: Coordenador | E14: 2907 | F14: =SUMIFS('Por Supervisor'!F:F,'Por Supervisor'!$A:$A,Tabela2[[#This Row],[Nome]]) -> 0 | G14: =SUMIFS('Por Supervisor'!G:G,'Por Supervisor'!$A:$A,Tabela2[[#This Row],[Nome]]) -> 0 | H14: =SUMIFS('Por Supervisor'!H:H,'Por Supervisor'!$A:$A,Tabela2[[#This Row],[Nome]]) -> 0 | I14: =SUMIFS('Por Supervisor'!I:I,'Por Supervisor'!$A:$A,Tabela2[[#This Row],[Nome]]) -> 0 | J14: =SUM(Tabela2[[#This Row],[Valor KM]:[Diversas]]) -> 0 | K14: =SUMIFS('Por Supervisor'!K:K,'Por Supervisor'!$A:$A,Tabela2[[#This Row],[Nome]]) -> 0 | M14: =IF(AND(J14=0,Tabela2[[#This Row],[Adiantamento / Saldo]]=""),"-",(Tabela2[[#This Row],[TT Reembolsavel]]+Tabela2[[#This Row],[Adiantamento / Saldo]])) -> -
F15: =SUMIFS('Por Supervisor'!F:F,'Por Supervisor'!$A:$A,Tabela2[[#This Row],[Nome]]) -> 0 | G15: =SUMIFS('Por Supervisor'!G:G,'Por Supervisor'!$A:$A,Tabela2[[#This Row],[Nome]]) -> 0 | H15: =SUMIFS('Por Supervisor'!H:H,'Por Supervisor'!$A:$A,Tabela2[[#This Row],[Nome]]) -> 0 | I15: =SUMIFS('Por Supervisor'!I:I,'Por Supervisor'!$A:$A,Tabela2[[#This Row],[Nome]]) -> 0 | J15: =SUM(Tabela2[[#This Row],[Valor KM]:[Diversas]]) -> 0 | K15: =SUMIFS('Por Supervisor'!K:K,'Por Supervisor'!$A:$A,Tabela2[[#This Row],[Nome]]) -> 0 | M15: =IF(AND(J15=0,Tabela2[[#This Row],[Adiantamento / Saldo]]=""),"-",(Tabela2[[#This Row],[TT Reembolsavel]]+Tabela2[[#This Row],[Adiantamento / Saldo]])) -> -
F16: =SUMIFS('Por Supervisor'!F:F,'Por Supervisor'!$A:$A,Tabela2[[#This Row],[Nome]]) -> 0 | G16: =SUMIFS('Por Supervisor'!G:G,'Por Supervisor'!$A:$A,Tabela2[[#This Row],[Nome]]) -> 0 | H16: =SUMIFS('Por Supervisor'!H:H,'Por Supervisor'!$A:$A,Tabela2[[#This Row],[Nome]]) -> 0 | I16: =SUMIFS('Por Supervisor'!I:I,'Por Supervisor'!$A:$A,Tabela2[[#This Row],[Nome]]) -> 0 | J16: =SUM(Tabela2[[#This Row],[Valor KM]:[Diversas]]) -> 0 | K16: =SUMIFS('Por Supervisor'!K:K,'Por Supervisor'!$A:$A,Tabela2[[#This Row],[Nome]]) -> 0 | M16: =IF(AND(J16=0,Tabela2[[#This Row],[Adiantamento / Saldo]]=""),"-",(Tabela2[[#This Row],[TT Reembolsavel]]+Tabela2[[#This Row],[Adiantamento / Saldo]])) -> -
J17: =SUBTOTAL(109,Tabela2[TT Reembolsavel]) -> 5567.61 | M17: =SUBTOTAL(109,Tabela2[Valor a depositar]) -> 5567.61

Sheet Por Supervisor
A1: Mês | B1: SETEMBRO
A2: Quinzena | B2: 1ª Quinzena
A4: Selecione o Usuário | B4: Data | C4: KM inicial | D4: KM final | E4: KM Rodado | F4: Valor KM | G4: Pedágio $ | H4: Estacionamento $ | I4: Diversas $ | J4: Valor reembolsavel | K4: Hospedagem $
A5: Geovana Duarte Farias | B5: 46267 | C5: 137264 | D5: 137535 | E5: 271 | F5: 333.33 | G5: 5.7 | H5: 0 | I5: 0 | J5: 339.03 | K5: 0
A6: Geovana Duarte Farias | B6: 46268 | C6: 137535 | D6: 137607 | E6: 72 | F6: 88.56 | G6: 0 | H6: 0 | I6: 0 | J6: 88.56 | K6: 0
A7: Geovana Duarte Farias | B7: 46269 | C7: 137607 | D7: 137672 | E7: 65 | F7: 79.95 | G7: 0 | H7: 0 | I7: 0 | J7: 79.95 | K7: 0
A8: Geovana Duarte Farias | B8: 46273 | C8: 137727 | D8: 137804 | E8: 77 | F8: 94.71 | G8: 0 | H8: 0 | I8: 0 | J8: 94.71 | K8: 0
A9: Geovana Duarte Farias | B9: 46274 | C9: 137804 | D9: 137852 | E9: 48 | F9: 59.04 | G9: 0 | H9: 0 | I9: 0 | J9: 59.04 | K9: 0
A10: Geovana Duarte Farias | B10: 46280 | C10: 138221 | D10: 138309 | E10: 88 | F10: 108.24 | G10: 0 | H10: 0 | I10: 0 | J10: 108.24 | K10: 0
A11: Geovana Duarte Farias Total | F11: 763.83 | G11: 5.7 | H11: 0 | I11: 0 | J11: 769.53 | K11: 0
A12: CAMILA CRISTINE ALTHOFF | B12: 46266 | C12: 198047 | D12: 198102 | E12: 55 | F12: 67.65 | G12: 0 | H12: 0 | I12: 0 | J12: 67.65 | K12: 0
A13: CAMILA CRISTINE ALTHOFF | B13: 46267 | C13: 198102 | D13: 198175 | E13: 73 | F13: 89.79 | G13: 0 | H13: 0 | I13: 0 | J13: 89.79 | K13: 0
A14: CAMILA CRISTINE ALTHOFF | B14: 46268 | C14: 198175 | D14: 198212 | E14: 37 | F14: 45.51 | G14: 0 | H14: 0 | I14: 0 | J14: 45.51 | K14: 0
A15: CAMILA CRISTINE ALTHOFF | B15: 46269 | C15: 198212 | D15: 198255 | E15: 43 | F15: 52.89 | G15: 0 | H15: 0 | I15: 0 | J15: 52.89 | K15: 0
A16: CAMILA CRISTINE ALTHOFF | B16: 46273 | C16: 198280 | D16: 198693 | E16: 413 | F16: 507.99 | G16: 28.5 | H16: 0 | I16: 43 | J16: 579.49 | K16: 0
A17: CAMILA CRISTINE ALTHOFF | B17: 46274 | C17: 198693 | D17: 198766 | E17: 73 | F17: 89.79 | G17: 0 | H17: 0 | I17: 0 | J17: 89.79 | K17: 0
A18: CAMILA CRISTINE ALTHOFF | B18: 46276 | C18: 198766 | D18: 198841 | E18: 75 | F18: 92.25 | G18: 0 | H18: 0 | I18: 0 | J18: 92.25 | K18: 0
A19: CAMILA CRISTINE ALTHOFF | B19: 46277 | C19: 198841 | D19: 198876 | E19: 35 | F19: 43.05 | G19: 0 | H19: 0 | I19: 0 | J19: 43.05 | K19: 0
A20: CAMILA CRISTINE ALTHOFF | B20: 46280 | C20: 198901 | D20: 198910 | E20: 9 | F20: 11.07 | G20: 0 | H20: 0 | I20: 0 | J20: 11.07 | K20: 0
A21: CAMILA CRISTINE ALTHOFF Total | F21: 999.99 | G21: 28.5 | H21: 0 | I21: 43 | J21: 1071.49 | K21: 0
A22: GUSTAVO MATHEUS DE OLIVEIRA | B22: 46280 | C22: 178367 | D22: 178622 | E22: 255 | F22: 313.65 | G22: 0 | H22: 0 | I22: 0 | J22: 313.65 | K22: 0
A23: GUSTAVO MATHEUS DE OLIVEIRA Total | F23: 313.65 | G23: 0 | H23: 0 | I23: 0 | J23: 313.65 | K23: 0
A24: RICARDO ALEXANDRE LOMBARDI | B24: 46273 | C24: 135217 | D24: 135269 | E24: 52 | F24: 63.96 | G24: 0 | H24: 0 | I24: 0 | J24: 63.96 | K24: 0
A25: RICARDO ALEXANDRE LOMBARDI | B25: 46274 | C25: 135269 | D25: 135400 | E25: 131 | F25: 161.13 | G25: 0 | H25: 0 | I25: 0 | J25: 161.13 | K25: 0
A26: RICARDO ALEXANDRE LOMBARDI | B26: 46276 | C26: 135511 | D26: 135555 | E26: 44 | F26: 54.12 | G26: 0 | H26: 0 | I26: 0 | J26: 54.12 | K26: 0
A27: RICARDO ALEXANDRE LOMBARDI | B27: 46279 | C27: 135669 | D27: 135703 | E27: 34 | F27: 41.82 | G27: 0 | H27: 0 | I27: 0 | J27: 41.82 | K27: 0
A28: RICARDO ALEXANDRE LOMBARDI Total | F28: 321.03 | G28: 0 | H28: 0 | I28: 0 | J28: 321.03 | K28: 0
A29: MATHEUS DA SILVA MORAES | B29: 46266 | C29: 137979 | D29: 138138 | E29: 85 | F29: 104.55 | G29: 0 | H29: 0 | I29: 0 | J29: 104.55 | K29: 0
A30: MATHEUS DA SILVA MORAES | B30: 46267 | C30: 138138 | D30: 138256 | E30: 118 | F30: 145.14 | G30: 0 | H30: 0 | I30: 0 | J30: 145.14 | K30: 0
A31: MATHEUS DA SILVA MORAES | B31: 46274 | C31: 138585 | D31: 138807 | E31: 222 | F31: 273.06 | G31: 0 | H31: 0 | I31: 0 | J31: 273.06 | K31: 0
A32: MATHEUS DA SILVA MORAES | B32: 46275 | C32: 138807 | D32: 138941 | E32: 134 | F32: 164.82 | G32: 0 | H32: 0 | I32: 0 | J32: 164.82 | K32: 0
A33: MATHEUS DA SILVA MORAES Total | F33: 687.57 | G33: 0 | H33: 0 | I33: 0 | J33: 687.57 | K33: 0
A34: CARLOS PROENÇA | B34: 46269 | C34: 56611 | D34: 57011 | E34: 400 | F34: 492 | G34: 23.4 | H34: 0 | I34: 0 | J34: 515.4 | K34: 0
A35: CARLOS PROENÇA | B35: 46274 | C35: 57684 | D35: 58079 | E35: 395 | F35: 485.85 | G35: 10.4 | H35: 0 | I35: 0 | J35: 496.25 | K35: 0
A36: CARLOS PROENÇA Total | F36: 977.85 | G36: 33.8 | H36: 0 | I36: 0 | J36: 1011.65 | K36: 0
A37: JOÃO MARTINS NETO | B37: 46266 | C37: 110218 | D37: 110316 | E37: 98 | F37: 120.54 | G37: 0 | H37: 0 | I37: 0 | J37: 120.54 | K37: 0
A38: JOÃO MARTINS NETO | B38: 46273 | C38: 110616 | D38: 110668 | E38: 52 | F38: 63.96 | G38: 0 | H38: 0 | I38: 0 | J38: 63.96 | K38: 0
A39: JOÃO MARTINS NETO | B39: 46274 | C39: 110668 | D39: 110811 | E39: 143 | F39: 175.89 | G39: 11.4 | H39: 0 | I39: 0 | J39: 187.29 | K39: 0
A40: JOÃO MARTINS NETO | B40: 46275 | C40: 110812 | D40: 110916 | E40: 104 | F40: 127.92 | G40: 0 | H40: 0 | I40: 0 | J40: 127.92 | K40: 0
A41: JOÃO MARTINS NETO | B41: 46280 | C41: 110965 | D41: 111077 | E41: 112 | F41: 137.76 | G41: 0 | H41: 0 | I41: 0 | J41: 137.76 | K41: 0
A42: JOÃO MARTINS NETO Total | F42: 626.07 | G42: 11.4 | H42: 0 | I42: 0 | J42: 637.47 | K42: 0
A43: THAYS APARECIDA CARVALHO | B43: 46266 | C43: 121870 | D43: 122012 | E43: 142 | F43: 174.66 | G43: 0 | H43: 0 | I43: 0 | J43: 174.66 | K43: 0
A44: THAYS APARECIDA CARVALHO | B44: 46267 | C44: 122044 | D44: 122139 | E44: 95 | F44: 116.85 | G44: 0 | H44: 0 | I44: 0 | J44: 116.85 | K44: 0
A45: THAYS APARECIDA CARVALHO | B45: 46273 | C45: 122274 | D45: 122397 | E45: 123 | F45: 151.29 | G45: 0 | H45: 0 | I45: 0 | J45: 151.29 | K45: 0
A46: THAYS APARECIDA CARVALHO | B46: 46276 | C46: 122529 | D46: 122720 | E46: 191 | F46: 234.93 | G46: 0 | H46: 0 | I46: 0 | J46: 234.93 | K46: 0
A47: THAYS APARECIDA CARVALHO | B47: 46280 | C47: 122796 | D47: 122859 | E47: 63 | F47: 77.49 | G47: 0 | H47: 0 | I47: 0 | J47: 77.49 | K47: 0
A48: THAYS APARECIDA CARVALHO Total | F48: 755.22 | G48: 0 | H48: 0 | I48: 0 | J48: 755.22 | K48: 0
A49: Total Geral | F49: 5445.21 | G49: 79.4 | H49: 0 | I49: 43 | J49: 5567.61 | K49: 0

Sheet Pesquisa
A1: Carimbo de data/hora | B1: Endereço de e-mail | C1: Selecione o Usuário | D1: Informe a placa do veículo | E1: Informe a data | F1: Informe o KM inicial do dia | G1: Insira a foto do hodômetro inicial | H1: Informe o KM final do dia | I1: Insira a foto do hodômetro final | J1: Quais lojas você visitou? | K1: Caso tenha rodado particular alguma parte do trajeto, informe o total de KM a ser deduzido. | L1: Possui despesas a serem lançadas | M1: Pedágio | N1: Insira as fotos dos recibos de pedágio | O1: Estacionamento | P1: Insira as fotos dos recibos de estacionamento | Q1: Despesas Diversas (Jantar em viagem, Impressões, Etc) | R1: Insira as fotos das notas de outras despesas | S1: Hospedagem | T1: Caso possua alguma observação sobre as despesas favor informar | U1: KM Rodado | V1: Valor KM | W1: Pedágio $ | X1: Estacionamento $ | Y1: Diversas $ | Z1: Hospedagem $ | AA1: Quinzena | AB1: Mês | AC1: Filtro mês dia
A2: 46034.351 | B2: sussuazevedo.com@icloud.com | C2: SUELEN DOS SANTOS AZEVEDO | D2: MFW6D17 | E2: 46024 | F2: 105642 | G2: https://drive.google.com/open?id=1KYNmN07uoNR2n42B3FXEHGxaV6cLYPEG | H2: 105788 | I2: https://drive.google.com/open?id=1m19T-228b0cuj3S9Zr2krHBB_ogorrGk | J2: Carrefour, Koch floripa, Komprão 55 | L2: Não | U2: =(Tabela1[[#This Row],[Informe o KM final do dia]]-Tabela1[[#This Row],[Informe o KM inicial do dia]])-Tabela1[[#This Row],[Caso tenha rodado particular alguma parte do trajeto, informe o total de KM a ser deduzido.]] -> 146 | V2: =IF(Tabela1[[#This Row],[Informe a data]]<DATE(2026,3,16), Tabela1[[#This Row],[KM Rodado]]*1.1, Tabela1[[#This Row],[KM Rodado]]*1.23) -> 160.6 | W2: =IFERROR(SUBSTITUTE(Tabela1[[#This Row],[Pedágio]],".",",",1)*1,0) -> 0 | X2: =IFERROR(SUBSTITUTE(Tabela1[[#This Row],[Estacionamento]],".",",",1)*1,0) -> 0 | Y2: =IFERROR(SUBSTITUTE(Tabela1[[#This Row],[Despesas Diversas (Jantar em viagem, Impressões, Etc)]],".",",",1)*1,0) -> 0 | Z2: =IFERROR(SUBSTITUTE(Tabela1[[#This Row],[Hospedagem]],".",",",1)*1,0) -> 0 | AA2: =IF(DAY(Tabela1[[#This Row],[Informe a data]])<=15,"1ª Quinzena","2ª Quinzena") -> 1ª Quinzena | AB2: =UPPER(TEXT(Tabela1[[#This Row],[Informe a data]],"mmmm")) -> JANEIRO | AC2: =_xlfn.CONCAT(Tabela1[[#This Row],[Selecione o Usuário]]," - ",TEXT(Tabela1[[#This Row],[Informe a data]],"dd-mm-aa")) -> #NAME?
A3: 46031.608 | B3: vinicioskerber@gmail.com | C3: VINICIUS ROBERTO KERBER | D3: MHO9G63 | E3: 46024 | F3: 212986 | G3: https://drive.google.com/open?id=1qYI936hO5BKGjC-5APmVsr8w2BOKfpwu | H3: 213022 | I3: https://drive.google.com/open?id=1vS2ku8_7ioiRf7PO1ekIz9WeuBJZhzQ6 | J3: Cooper Garcia, cooper Glória | L3: Não | U3: =(Tabela1[[#This Row],[Informe o KM final do dia]]-Tabela1[[#This Row],[Informe o KM inicial do dia]])-Tabela1[[#This Row],[Caso tenha rodado particular alguma parte do trajeto, informe o total de KM a ser deduzido.]] -> 36 | V3: =IF(Tabela1[[#This Row],[Informe a data]]<DATE(2026,3,16), Tabela1[[#This Row],[KM Rodado]]*1.1, Tabela1[[#This Row],[KM Rodado]]*1.23) -> 39.6 | W3: =IFERROR(SUBSTITUTE(Tabela1[[#This Row],[Pedágio]],".",",",1)*1,0) -> 0 | X3: =IFERROR(SUBSTITUTE(Tabela1[[#This Row],[Estacionamento]],".",",",1)*1,0) -> 0 | Y3: =IFERROR(SUBSTITUTE(Tabela1[[#This Row],[Despesas Diversas (Jantar em viagem, Impressões, Etc)]],".",",",1)*1,0) -> 0 | Z3: =IFERROR(SUBSTITUTE(Tabela1[[#This Row],[Hospedagem]],".",",",1)*1,0) -> 0 | AA3: =IF(DAY(Tabela1[[#This Row],[Informe a data]])<=15,"1ª Quinzena","2ª Quinzena") -> 1ª Quinzena | AB3: =UPPER(TEXT(Tabela1[[#This Row],[Informe a data]],"mmmm")) -> JANEIRO | AC3: =_xlfn.CONCAT(Tabela1[[#This Row],[Selecione o Usuário]]," - ",TEXT(Tabela1[[#This Row],[Informe a data]],"dd-mm-aa")) -> #NAME?
A4: 46027.96 | B4: sabrina.pires@mazzini.com.br | C4: SABRINA DOS SANTOS PIRES | D4: AZC9E32 | E4: 46027 | F4: 172770 | G4: https://drive.google.com/open?id=1UavfH0mE7m_A6j4phdWhnux6CiTCGnX_ | H4: 172848 | I4: https://drive.google.com/open?id=1vNdIFFWbay4r8_xDZC5GHaqwts-29CFf | J4: Fort 130 Brasil atacadista Fort campeche | L4: Não | U4: =(Tabela1[[#This Row],[Informe o KM final do dia]]-Tabela1[[#This Row],[Informe o KM inicial do dia]])-Tabela1[[#This Row],[Caso tenha rodado particular alguma parte do trajeto, informe o total de KM a ser deduzido.]] -> 78 | V4: =IF(Tabela1[[#This Row],[Informe a data]]<DATE(2026,3,16), Tabela1[[#This Row],[KM Rodado]]*1.1, Tabela1[[#This Row],[KM Rodado]]*1.23) -> 85.8 | W4: =IFERROR(SUBSTITUTE(Tabela1[[#This Row],[Pedágio]],".",",",1)*1,0) -> 0 | X4: =IFERROR(SUBSTITUTE(Tabela1[[#This Row],[Estacionamento]],".",",",1)*1,0) -> 0 | Y4: =IFERROR(SUBSTITUTE(Tabela1[[#This Row],[Despesas Diversas (Jantar em viagem, Impressões, Etc)]],".",",",1)*1,0) -> 0 | Z4: =IFERROR(SUBSTITUTE(Tabela1[[#This Row],[Hospedagem]],".",",",1)*1,0) -> 0 | AA4: =IF(DAY(Tabela1[[#This Row],[Informe a data]])<=15,"1ª Quinzena","2ª Quinzena") -> 1ª Quinzena | AB4: =UPPER(TEXT(Tabela1[[#This Row],[Informe a data]],"mmmm")) -> JANEIRO | AC4: =_xlfn.CONCAT(Tabela1[[#This Row],[Selecione o Usuário]]," - ",TEXT(Tabela1[[#This Row],[Informe a data]],"dd-mm-aa")) -> #NAME?
A5: 46028.782 | B5: camila.althoff@mazzini.com.br | C5: CAMILA CRISTINE ALTHOFF | D5: Mlz4j72 | E5: 46028 | F5: 185450 | G5: https://drive.google.com/open?id=18j1kKdkPpHMRosNYZAJHGmUmZ-en4RmC | H5: 185504 | I5: https://drive.google.com/open?id=1ckMfdiuOwMXCAWy01Fz4SQZ-dlyZfvN2 | J5: Fort 365, Fort jardim atlântico, Zeus brasil | L5: Não | U5: =(Tabela1[[#This Row],[Informe o KM final do dia]]-Tabela1[[#This Row],[Informe o KM inicial do dia]])-Tabela1[[#This Row],[Caso tenha rodado particular alguma parte do trajeto, informe o total de KM a ser deduzido.]] -> 54 | V5: =IF(Tabela1[[#This Row],[Informe a data]]<DATE(2026,3,16), Tabela1[[#This Row],[KM Rodado]]*1.1, Tabela1[[#This Row],[KM Rodado]]*1.23) -> 59.4 | W5: =IFERROR(SUBSTITUTE(Tabela1[[#This Row],[Pedágio]],".",",",1)*1,0) -> 0 | X5: =IFERROR(SUBSTITUTE(Tabela1[[#This Row],[Estacionamento]],".",",",1)*1,0) -> 0 | Y5: =IFERROR(SUBSTITUTE(Tabela1[[#This Row],[Despesas Diversas (Jantar em viagem, Impressões, Etc)]],".",",",1)*1,0) -> 0 | Z5: =IFERROR(SUBSTITUTE(Tabela1[[#This Row],[Hospedagem]],".",",",1)*1,0) -> 0 | AA5: =IF(DAY(Tabela1[[#This Row],[Informe a data]])<=15,"1ª Quinzena","2ª Quinzena") -> 1ª Quinzena | AB5: =UPPER(TEXT(Tabela1[[#This Row],[Informe a data]],"mmmm")) -> JANEIRO | AC5: =_xlfn.CONCAT(Tabela1[[#This Row],[Selecione o Usuário]]," - ",TEXT(Tabela1[[#This Row],[Informe a data]],"dd-mm-aa")) -> #NAME?
A6: 46031.977 | B6: lombardi2025@gmail.com | C6: RICARDO ALEXANDRE LOMBARDI | D6: OWA4C07 | E6: 46028 | F6: 167575 | G6: https://drive.google.com/open?id=1xZ5kqU8hTlxlUIG4gcOqyO9CYGa27za2 | H6: 167625 | I6: https://drive.google.com/open?id=1vloXVEfCOLF22v-lv7GwtqsWtcfbl8u2 | J6: Komprao 77, komprao 45, imperatriz,komprao 59 | L6: Não | U6: =(Tabela1[[#This Row],[Informe o KM final do dia]]-Tabela1[[#This Row],[Informe o KM inicial do dia]])-Tabela1[[#This Row],[Caso tenha rodado particular alguma parte do trajeto, informe o total de KM a ser deduzido.]] -> 50 | V6: =IF(Tabela1[[#This Row],[Informe a data]]<DATE(2026,3,16), Tabela1[[#This Row],[KM Rodado]]*1.1, Tabela1[[#This Row],[KM Rodado]]*1.23) -> 55 | W6: =IFERROR(SUBSTITUTE(Tabela1[[#This Row],[Pedágio]],".",",",1)*1,0) -> 0 | X6: =IFERROR(SUBSTITUTE(Tabela1[[#This Row],[Estacionamento]],".",",",1)*1,0) -> 0 | Y6: =IFERROR(SUBSTITUTE(Tabela1[[#This Row],[Despesas Diversas (Jantar em viagem, Impressões, Etc)]],".",",",1)*1,0) -> 0 | Z6: =IFERROR(SUBSTITUTE(Tabela1[[#This Row],[Hospedagem]],".",",",1)*1,0) -> 0 | AA6: =IF(DAY(Tabela1[[#This Row],[Informe a data]])<=15,"1ª Quinzena","2ª Quinzena") -> 1ª Quinzena | AB6: =UPPER(TEXT(Tabela1[[#This Row],[Informe a data]],"mmmm")) -> JANEIRO | AC6: =_xlfn.CONCAT(Tabela1[[#This Row],[Selecione o Usuário]]," - ",TEXT(Tabela1[[#This Row],[Informe a data]],"dd-mm-aa")) -> #NAME?
A7: 46034.354 | B7: sussuazevedo.com@icloud.com | C7: SUELEN DOS SANTOS AZEVEDO | D7: MFW6D17 | E7: 46028 | F7: 105821 | G7: https://drive.google.com/open?id=1omA_eXctjnr4WwIoiJtXIzC1BToGua8d | H7: 105831 | I7: https://drive.google.com/open?id=1WYlS12BXIZAs5iNxNA-PkcV2_4ZI0Q3G | J7: Fui ao Komprão 18 e ao Koch 4 | L7: Não | U7: =(Tabela1[[#This Row],[Informe o KM final do dia]]-Tabela1[[#This Row],[Informe o KM inicial do dia]])-Tabela1[[#This Row],[Caso tenha rodado particular alguma parte do trajeto, informe o total de KM a ser deduzido.]] -> 10 | V7: =IF(Tabela1[[#This Row],[Informe a data]]<DATE(2026,3,16), Tabela1[[#This Row],[KM Rodado]]*1.1, Tabela1[[#This Row],[KM Rodado]]*1.23) -> 11 | W7: =IFERROR(SUBSTITUTE(Tabela1[[#This Row],[Pedágio]],".",",",1)*1,0) -> 0 | X7: =IFERROR(SUBSTITUTE(Tabela1[[#This Row],[Estacionamento]],".",",",1)*1,0) -> 0 | Y7: =IFERROR(SUBSTITUTE(Tabela1[[#This Row],[Despesas Diversas (Jantar em viagem, Impressões, Etc)]],".",",",1)*1,0) -> 0 | Z7: =IFERROR(SUBSTITUTE(Tabela1[[#This Row],[Hospedagem]],".",",",1)*1,0) -> 0 | AA7: =IF(DAY(Tabela1[[#This Row],[Informe a data]])<=15,"1ª Quinzena","2ª Quinzena") -> 1ª Quinzena | AB7: =UPPER(TEXT(Tabela1[[#This Row],[Informe a data]],"mmmm")) -> JANEIRO | AC7: =_xlfn.CONCAT(Tabela1[[#This Row],[Selecione o Usuário]]," - ",TEXT(Tabela1[[#This Row],[Informe a data]],"dd-mm-aa")) -> #NAME?
A8: 46031.61 | B8: vinicioskerber@gmail.com | C8: VINICIUS ROBERTO KERBER | D8: MHO9G63 | E8: 46028 | F8: 213548 | G8: https://drive.google.com/open?id=1kgu6lQ88Apv7GUU-4P17QGOmrAYG9kED | H8: 213630 | I8: https://drive.google.com/open?id=1l7XIxsTEwJX90j8_8ePvLYLoXg12_AM5 | J8: Komprao 40, top 104, Cooper Omino, super A | L8: Não | U8: =(Tabela1[[#This Row],[Informe o KM final do dia]]-Tabela1[[#This Row],[Informe o KM inicial do dia]])-Tabela1[[#This Row],[Caso tenha rodado particular alguma parte do trajeto, informe o total de KM a ser deduzido.]] -> 82 | V8: =IF(Tabela1[[#This Row],[Informe a data]]<DATE(2026,3,16), Tabela1[[#This Row],[KM Rodado]]*1.1, Tabela1[[#This Row],[KM Rodado]]*1.23) -> 90.2 | W8: =IFERROR(SUBSTITUTE(Tabela1[[#This Row],[Pedágio]],".",",",1)*1,0) -> 0 | X8: =IFERROR(SUBSTITUTE(Tabela1[[#This Row],[Estacionamento]],".",",",1)*1,0) -> 0 | Y8: =IFERROR(SUBSTITUTE(Tabela1[[#This Row],[Despesas Diversas (Jantar em viagem, Impressões, Etc)]],".",",",1)*1,0) -> 0 | Z8: =IFERROR(SUBSTITUTE(Tabela1[[#This Row],[Hospedagem]],".",",",1)*1,0) -> 0 | AA8: =IF(DAY(Tabela1[[#This Row],[Informe a data]])<=15,"1ª Quinzena","2ª Quinzena") -> 1ª Quinzena | AB8: =UPPER(TEXT(Tabela1[[#This Row],[Informe a data]],"mmmm")) -> JANEIRO | AC8: =_xlfn.CONCAT(Tabela1[[#This Row],[Selecione o Usuário]]," - ",TEXT(Tabela1[[#This Row],[Informe a data]],"dd-mm-aa")) -> #NAME?
A9: 46029.817 | B9: camila.althoff@mazzini.com.br | C9: CAMILA CRISTINE ALTHOFF | D9: Mlz4j72 | E9: 46029 | F9: 185504 | G9: https://drive.google.com/open?id=1nu8DrNJy1dUm1K66c3HCTZe6fGl2tLQW | H9: 185564 | I9: https://drive.google.com/open?id=1jlVjfylpz2NIezjqJHpoirEvIE-GUOYy | J9: Carrefour, Fort campeche, hiperbom | L9: Sim | O9: 18.00 | P9: https://drive.google.com/open?id=1KRpYPCL0Bg4ZUqDw96dC0T4966CaXL56 | U9: =(Tabela1[[#This Row],[Informe o KM final do dia]]-Tabela1[[#This Row],[Informe o KM inicial do dia]])-Tabela1[[#This Row],[Caso tenha rodado particular alguma parte do trajeto, informe o total de KM a ser deduzido.]] -> 60 | V9: =IF(Tabela1[[#This Row],[Informe a data]]<DATE(2026,3,16), Tabela1[[#This Row],[KM Rodado]]*1.1, Tabela1[[#This Row],[KM Rodado]]*1.23) -> 66 | W9: =IFERROR(SUBSTITUTE(Tabela1[[#This Row],[Pedágio]],".",",",1)*1,0) -> 0 | X9: =IFERROR(SUBSTITUTE(Tabela1[[#This Row],[Estacionamento]],".",",",1)*1,0) -> 18 | Y9: =IFERROR(SUBSTITUTE(Tabela1[[#This Row],[Despesas Diversas (Jantar em viagem, Impressões, Etc)]],".",",",1)*1,0) -> 0 | Z9: =IFERROR(SUBSTITUTE(Tabela1[[#This Row],[Hospedagem]],".",",",1)*1,0) -> 0 | AA9: =IF(DAY(Tabela1[[#This Row],[Informe a data]])<=15,"1ª Quinzena","2ª Quinzena") -> 1ª Quinzena | AB9: =UPPER(TEXT(Tabela1[[#This Row],[Informe a data]],"mmmm")) -> JANEIRO | AC9: =_xlfn.CONCAT(Tabela1[[#This Row],[Selecione o Usuário]]," - ",TEXT(Tabela1[[#This Row],[Informe a data]],"dd-mm-aa")) -> #NAME?
A10: 46031.98 | B10: lombardi2025@gmail.com | C10: RICARDO ALEXANDRE LOMBARDI | D10: OWA4C07 | E10: 46029 | F10: 167625 | G10: https://drive.google.com/open?id=13Tk9wQ7CNu2Qz1Rl5J8AHAdp9iX6VT7S | H10: 167732 | I10: https://drive.google.com/open?id=1O4RuK3ZypLPzwDU6-2s90egzCtDsvh84 | J10: Komprao 50,Fort Tuiuti,condor comasa,Fort 405,brasil atacadista,bistek | L10: Não | U10: =(Tabela1[[#This Row],[Informe o KM final do dia]]-Tabela1[[#This Row],[Informe o KM inicial do dia]])-Tabela1[[#This Row],[Caso tenha rodado particular alguma parte do trajeto, informe o total de KM a ser deduzido.]] -> 107 | V10: =IF(Tabela1[[#This Row],[Informe a data]]<DATE(2026,3,16), Tabela1[[#This Row],[KM Rodado]]*1.1, Tabela1[[#This Row],[KM Rodado]]*1.23) -> 117.7 | W10: =IFERROR(SUBSTITUTE(Tabela1[[#This Row],[Pedágio]],".",",",1)*1,0) -> 0 | X10: =IFERROR(SUBSTITUTE(Tabela1[[#This Row],[Estacionamento]],".",",",1)*1,0) -> 0 | Y10: =IFERROR(SUBSTITUTE(Tabela1[[#This Row],[Despesas Diversas (Jantar em viagem, Impressões, Etc)]],".",",",1)*1,0) -> 0 | Z10: =IFERROR(SUBSTITUTE(Tabela1[[#This Row],[Hospedagem]],".",",",1)*1,0) -> 0 | AA10: =IF(DAY(Tabela1[[#This Row],[Informe a data]])<=15,"1ª Quinzena","2ª Quinzena") -> 1ª Quinzena | AB10: =UPPER(TEXT(Tabela1[[#This Row],[Informe a data]],"mmmm")) -> JANEIRO | AC10: =_xlfn.CONCAT(Tabela1[[#This Row],[Selecione o Usuário]]," - ",TEXT(Tabela1[[#This Row],[Informe a data]],"dd-mm-aa")) -> #NAME?
A11: 46034.356 | B11: sussuazevedo.com@icloud.com | C11: SUELEN DOS SANTOS AZEVEDO | D11: Mfw6d17 | E11: 46029 | F11: 105842 | G11: https://drive.google.com/open?id=1Lv9VwLe1pEbpf4veXfmkoHMXj5Nu63RI | H11: 105850 | I11: https://drive.google.com/open?id=1W_7KRYLgBEOvssy_t9Lq6wwpjmmZCYL8 | J11: Komprão 37 Komprão 15 Koch 7 koch41 | L11: Não | U11: =(Tabela1[[#This Row],[Informe o KM final do dia]]-Tabela1[[#This Row],[Informe o KM inicial do dia]])-Tabela1[[#This Row],[Caso tenha rodado particular alguma parte do trajeto, informe o total de KM a ser deduzido.]] -> 8 | V11: =IF(Tabela1[[#This Row],[Informe a data]]<DATE(2026,3,16), Tabela1[[#This Row],[KM Rodado]]*1.1, Tabela1[[#This Row],[KM Rodado]]*1.23) -> 8.8 | W11: =IFERROR(SUBSTITUTE(Tabela1[[#This Row],[Pedágio]],".",",",1)*1,0) -> 0 | X11: =IFERROR(SUBSTITUTE(Tabela1[[#This Row],[Estacionamento]],".",",",1)*1,0) -> 0 | Y11: =IFERROR(SUBSTITUTE(Tabela1[[#This Row],[Despesas Diversas (Jantar em viagem, Impressões, Etc)]],".",",",1)*1,0) -> 0 | Z11: =IFERROR(SUBSTITUTE(Tabela1[[#This Row],[Hospedagem]],".",",",1)*1,0) -> 0 | AA11: =IF(DAY(Tabela1[[#This Row],[Informe a data]])<=15,"1ª Quinzena","2ª Quinzena") -> 1ª Quinzena | AB11: =UPPER(TEXT(Tabela1[[#This Row],[Informe a data]],"mmmm")) -> JANEIRO | AC11: =_xlfn.CONCAT(Tabela1[[#This Row],[Selecione o Usuário]]," - ",TEXT(Tabela1[[#This Row],[Informe a data]],"dd-mm-aa")) -> #NAME?
A12: 46031.48 | B12: camila.althoff@mazzini.com.br | C12: CAMILA CRISTINE ALTHOFF | D12: Mlz4j72 | E12: 46030 | F12: 151395 | G12: https://drive.google.com/open?id=1N8h61bOZYLyYe638o3_mvWAkZ1VW-npk | H12: 151755 | I12: https://drive.google.com/open?id=1hVkqxc8cgkNRDt8iM6-MzIDN2mEP77Ny | J12: Pegar cestas no Gustavo , Komprao água verde | L12: Sim | M12: 11.40 | N12: https://drive.google.com/open?id=1Guh61Oyl3HFOTcLNSGv0mQH4V4J9ebRH | U12: =(Tabela1[[#This Row],[Informe o KM final do dia]]-Tabela1[[#This Row],[Informe o KM inicial do dia]])-Tabela1[[#This Row],[Caso tenha rodado particular alguma parte do trajeto, informe o total de KM a ser deduzido.]] -> 360 | V12: =IF(Tabela1[[#This Row],[Informe a data]]<DATE(2026,3,16), Tabela1[[#This Row],[KM Rodado]]*1.1, Tabela1[[#This Row],[KM Rodado]]*1.23) -> 396 | W12: =IFERROR(SUBSTITUTE(Tabela1[[#This Row],[Pedágio]],".",",",1)*1,0) -> 11.4 | X12: =IFERROR(SUBSTITUTE(Tabela1[[#This Row],[Estacionamento]],".",",",1)*1,0) -> 0 | Y12: =IFERROR(SUBSTITUTE(Tabela1[[#This Row],[Despesas Diversas (Jantar em viagem, Impressões, Etc)]],".",",",1)*1,0) -> 0 | Z12: =IFERROR(SUBSTITUTE(Tabela1[[#This Row],[Hospedagem]],".",",",1)*1,0) -> 0 | AA12: =IF(DAY(Tabela1[[#This Row],[Informe a data]])<=15,"1ª Quinzena","2ª Quinzena") -> 1ª Quinzena | AB12: =UPPER(TEXT(Tabela1[[#This Row],[Informe a data]],"mmmm")) -> JANEIRO | AC12: =_xlfn.CONCAT(Tabela1[[#This Row],[Selecione o Usuário]]," - ",TEXT(Tabela1[[#This Row],[Informe a data]],"dd-mm-aa")) -> #NAME?
A13: 46034.361 | B13: sussuazevedo.com@icloud.com | C13: SUELEN DOS SANTOS AZEVEDO | D13: Mfw6d17 | E13: 46030 | F13: 105891 | G13: https://drive.google.com/open?id=1nww-76sgilmMbg5PKFBpw5eOqVVpxeNJ | H13: 105938 | I13: https://drive.google.com/open?id=1aTeS1MXlIxnPeY_JKJTZMKpOA4IJmmOD | J13: For 825, koch8 Komprão 38 Mesck atacadista | L13: Não | U13: =(Tabela1[[#This Row],[Informe o KM final do dia]]-Tabela1[[#This Row],[Informe o KM inicial do dia]])-Tabela1[[#This Row],[Caso tenha rodado particular alguma parte do trajeto, informe o total de KM a ser deduzido.]] -> 47 | V13: =IF(Tabela1[[#This Row],[Informe a data]]<DATE(2026,3,16), Tabela1[[#This Row],[KM Rodado]]*1.1, Tabela1[[#This Row],[KM Rodado]]*1.23) -> 51.7 | W13: =IFERROR(SUBSTITUTE(Tabela1[[#This Row],[Pedágio]],".",",",1)*1,0) -> 0 | X13: =IFERROR(SUBSTITUTE(Tabela1[[#This Row],[Estacionamento]],".",",",1)*1,0) -> 0 | Y13: =IFERROR(SUBSTITUTE(Tabela1[[#This Row],[Despesas Diversas (Jantar em viagem, Impressões, Etc)]],".",",",1)*1,0) -> 0 | Z13: =IFERROR(SUBSTITUTE(Tabela1[[#This Row],[Hospedagem]],".",",",1)*1,0) -> 0 | AA13: =IF(DAY(Tabela1[[#This Row],[Informe a data]])<=15,"1ª Quinzena","2ª Quinzena") -> 1ª Quinzena | AB13: =UPPER(TEXT(Tabela1[[#This Row],[Informe a data]],"mmmm")) -> JANEIRO | AC13: =_xlfn.CONCAT(Tabela1[[#This Row],[Selecione o Usuário]]," - ",TEXT(Tabela1[[#This Row],[Informe a data]],"dd-mm-aa")) -> #NAME?
A14: 46031.758 | B14: camila.althoff@mazzini.com.br | C14: CAMILA CRISTINE ALTHOFF | D14: Mlz4j72 | E14: 46031 | F14: 185564 | G14: https://drive.google.com/open?id=1uzoPl2u_v3TRDwT7CiimpjRgjU6IF71D | H14: 185593 | I14: https://drive.google.com/open?id=13VL6tqGt62MStI6lcmKByqH6oj5p-j_C | J14: Bistek costeira, brasil atacadista rio Tavares | L14: Não | U14: =(Tabela1[[#This Row],[Informe o KM final do dia]]-Tabela1[[#This Row],[Informe o KM inicial do dia]])-Tabela1[[#This Row],[Caso tenha rodado particular alguma parte do trajeto, informe o total de KM a ser deduzido.]] -> 29 | V14: =IF(Tabela1[[#This Row],[Informe a data]]<DATE(2026,3,16), Tabela1[[#This Row],[KM Rodado]]*1.1, Tabela1[[#This Row],[KM Rodado]]*1.23) -> 31.9 | W14: =IFERROR(SUBSTITUTE(Tabela1[[#This Row],[Pedágio]],".",",",1)*1,0) -> 0 | X14: =IFERROR(SUBSTITUTE(Tabela1[[#This Row],[Estacionamento]],".",",",1)*1,0) -> 0 | Y14: =IFERROR(SUBSTITUTE(Tabela1[[#This Row],[Despesas Diversas (Jantar em viagem, Impressões, Etc)]],".",",",1)*1,0) -> 0 | Z14: =IFERROR(SUBSTITUTE(Tabela1[[#This Row],[Hospedagem]],".",",",1)*1,0) -> 0 | AA14: =IF(DAY(Tabela1[[#This Row],[Informe a data]])<=15,"1ª Quinzena","2ª Quinzena") -> 1ª Quinzena | AB14: =UPPER(TEXT(Tabela1[[#This Row],[Informe a data]],"mmmm")) -> JANEIRO | AC14: =_xlfn.CONCAT(Tabela1[[#This Row],[Selecione o Usuário]]," - ",TEXT(Tabela1[[#This Row],[Informe a data]],"dd-mm-aa")) -> #NAME?
A15: 46031.988 | B15: lombardi2025@gmail.com | C15: RICARDO ALEXANDRE LOMBARDI | D15: OWA4C07 | E15: 46031 | F15: 167982 | G15: https://drive.google.com/open?id=1EYJ6QRpiYfbCGFKOqjwbU3b0LUP7Webn | H15: 168055 | I15: https://drive.google.com/open?id=1Pv7PHyKh379ZcICWKER-DUXXweGmaEWk | J15: Fort 250,sams club,Fort 905, komprao 51,condor 51,angeloni23, Angeloni 22 | L15: Não | U15: =(Tabela1[[#This Row],[Informe o KM final do dia]]-Tabela1[[#This Row],[Informe o KM inicial do dia]])-Tabela1[[#This Row],[Caso tenha rodado particular alguma parte do trajeto, informe o total de KM a ser deduzido.]] -> 73 | V15: =IF(Tabela1[[#This Row],[Informe a data]]<DATE(2026,3,16), Tabela1[[#This Row],[KM Rodado]]*1.1, Tabela1[[#This Row],[KM Rodado]]*1.23) -> 80.3 | W15: =IFERROR(SUBSTITUTE(Tabela1[[#This Row],[Pedágio]],".",",",1)*1,0) -> 0 | X15: =IFERROR(SUBSTITUTE(Tabela1[[#This Row],[Estacionamento]],".",",",1)*1,0) -> 0 | Y15: =IFERROR(SUBSTITUTE(Tabela1[[#This Row],[Despesas Diversas (Jantar em viagem, Impressões, Etc)]],".",",",1)*1,0) -> 0 | Z15: =IFERROR(SUBSTITUTE(Tabela1[[#This Row],[Hospedagem]],".",",",1)*1,0) -> 0 | AA15: =IF(DAY(Tabela1[[#This Row],[Informe a data]])<=15,"1ª Quinzena","2ª Quinzena") -> 1ª Quinzena | AB15: =UPPER(TEXT(Tabela1[[#This Row],[Informe a data]],"mmmm")) -> JANEIRO | AC15: =_xlfn.CONCAT(Tabela1[[#This Row],[Selecione o Usuário]]," - ",TEXT(Tabela1[[#This Row],[Informe a data]],"dd-mm-aa")) -> #NAME?
A16: 46031.745 | B16: sabrina.pires@mazzi.com.br | C16: SABRINA DOS SANTOS PIRES | D16: Azc9e32 | E16: 46031 | F16: 172907 | G16: https://drive.google.com/open?id=1w8M7KRWc8d4SWhuRpo7t2gcKbbEX8u2Q | H16: 173040 | I16: https://drive.google.com/open?id=1GU8YE6ECr8FFpdYMIRO0m10_rAk_g2Tk | J16: Komprao Tijucas Komprao Tijucas Fort 290 Fort 365 Komprao avenida das torres | L16: Não | U16: =(Tabela1[[#This Row],[Informe o KM final do dia]]-Tabela1[[#This Row],[Informe o KM inicial do dia]])-Tabela1[[#This Row],[Caso tenha rodado particular alguma parte do trajeto, informe o total de KM a ser deduzido.]] -> 133 | V16: =IF(Tabela1[[#This Row],[Informe a data]]<DATE(2026,3,16), Tabela1[[#This Row],[KM Rodado]]*1.1, Tabela1[[#This Row],[KM Rodado]]*1.23) -> 146.3 | W16: =IFERROR(SUBSTITUTE(Tabela1[[#This Row],[Pedágio]],".",",",1)*1,0) -> 0 | X16: =IFERROR(SUBSTITUTE(Tabela1[[#This Row],[Estacionamento]],".",",",1)*1,0) -> 0 | Y16: =IFERROR(SUBSTITUTE(Tabela1[[#This Row],[Despesas Diversas (Jantar em viagem, Impressões, Etc)]],".",",",1)*1,0) -> 0 | Z16: =IFERROR(SUBSTITUTE(Tabela1[[#This Row],[Hospedagem]],".",",",1)*1,0) -> 0 | AA16: =IF(DAY(Tabela1[[#This Row],[Informe a data]])<=15,"1ª Quinzena","2ª Quinzena") -> 1ª Quinzena | AB16: =UPPER(TEXT(Tabela1[[#This Row],[Informe a data]],"mmmm")) -> JANEIRO | AC16: =_xlfn.CONCAT(Tabela1[[#This Row],[Selecione o Usuário]]," - ",TEXT(Tabela1[[#This Row],[Informe a data]],"dd-mm-aa")) -> #NAME?
A17: 46035.388 | B17: camila.althoff@mazzini.com.br | C17: CAMILA CRISTINE ALTHOFF | D17: Mlz4j72 | E17: 46034 | F17: 185599 | G17: https://drive.google.com/open?id=1PD2xpvm1rXxZHPud1C3wTfxyW1LZ6IfH | H17: 185643 | I17: https://drive.google.com/open?id=12ra3N6T7q3FTSitBav3bT5myvEQJn6EA | J17: Fort 810, Fort 210 recolha de EPI Everton | L17: Não | U17: =(Tabela1[[#This Row],[Informe o KM final do dia]]-Tabela1[[#This Row],[Informe o KM inicial do dia]])-Tabela1[[#This Row],[Caso tenha rodado particular alguma parte do trajeto, informe o total de KM a ser deduzido.]] -> 44 | V17: =IF(Tabela1[[#This Row],[Informe a data]]<DATE(2026,3,16), Tabela1[[#This Row],[KM Rodado]]*1.1, Tabela1[[#This Row],[KM Rodado]]*1.23) -> 48.4 | W17: =IFERROR(SUBSTITUTE(Tabela1[[#This Row],[Pedágio]],".",",",1)*1,0) -> 0 | X17: =IFERROR(SUBSTITUTE(Tabela1[[#This Row],[Estacionamento]],".",",",1)*1,0) -> 0 | Y17: =IFERROR(SUBSTITUTE(Tabela1[[#This Row],[Despesas Diversas (Jantar em viagem, Impressões, Etc)]],".",",",1)*1,0) -> 0 | Z17: =IFERROR(SUBSTITUTE(Tabela1[[#This Row],[Hospedagem]],".",",",1)*1,0) -> 0 | AA17: =IF(DAY(Tabela1[[#This Row],[Informe a data]])<=15,"1ª Quinzena","2ª Quinzena") -> 1ª Quinzena | AB17: =UPPER(TEXT(Tabela1[[#This Row],[Informe a data]],"mmmm")) -> JANEIRO | AC17: =_xlfn.CONCAT(Tabela1[[#This Row],[Selecione o Usuário]]," - ",TEXT(Tabela1[[#This Row],[Informe a data]],"dd-mm-aa")) -> #NAME?
A18: 46035.806 | B18: michalski.ep@gmail.com | C18: ANDERSON MICHALSKI FERREIRA | D18: BCS7I80 | E18: 46035 | F18: 221889 | G18: https://drive.google.com/open?id=1pY4X-HNwcWapgYXMxlW2TZSFjG7D-bFY | H18: 221889 | I18: https://drive.google.com/open?id=1zat7qCqFXVcvF9Vql4O6T1qr74Nv5U06 | J18: ENVIO UNIFORMES | L18: Sim | Q18: 179.49 | R18: https://drive.google.com/open?id=14UEk1IkpAGmVOjXL4tfliK5-_9GinfaW | T18: Envio de Uniformes | U18: =(Tabela1[[#This Row],[Informe o KM final do dia]]-Tabela1[[#This Row],[Informe o KM inicial do dia]])-Tabela1[[#This Row],[Caso tenha rodado particular alguma parte do trajeto, informe o total de KM a ser deduzido.]] -> 0 | V18: =IF(Tabela1[[#This Row],[Informe a data]]<DATE(2026,3,16), Tabela1[[#This Row],[KM Rodado]]*1.1, Tabela1[[#This Row],[KM Rodado]]*1.23) -> 0 | W18: =IFERROR(SUBSTITUTE(Tabela1[[#This Row],[Pedágio]],".",",",1)*1,0) -> 0 | X18: =IFERROR(SUBSTITUTE(Tabela1[[#This Row],[Estacionamento]],".",",",1)*1,0) -> 0 | Y18: =IFERROR(SUBSTITUTE(Tabela1[[#This Row],[Despesas Diversas (Jantar em viagem, Impressões, Etc)]],".",",",1)*1,0) -> 179.49 | Z18: =IFERROR(SUBSTITUTE(Tabela1[[#This Row],[Hospedagem]],".",",",1)*1,0) -> 0 | AA18: =IF(DAY(Tabela1[[#This Row],[Informe a data]])<=15,"1ª Quinzena","2ª Quinzena") -> 1ª Quinzena | AB18: =UPPER(TEXT(Tabela1[[#This Row],[Informe a data]],"mmmm")) -> JANEIRO | AC18: =_xlfn.CONCAT(Tabela1[[#This Row],[Selecione o Usuário]]," - ",TEXT(Tabela1[[#This Row],[Informe a data]],"dd-mm-aa")) -> #NAME?
A19: 46035.762 | B19: oliiveiiraa7@gmail.com | C19: GUSTAVO MATHEUS DE OLIVEIRA | D19: EUF3090 | E19: 46035 | F19: 158913 | G19: https://drive.google.com/open?id=1-0BhC6YDZNaDTaBYS-i_TdgNBmUCwkLh | H19: 159149 | I19: https://drive.google.com/open?id=1eTlOZEu-_eFXyU2Z6kWjIh1j53F8YX66 | J19: Deslocamento Fort Chapeco | L19: Sim | S19: 219.94 | U19: =(Tabela1[[#This Row],[Informe o KM final do dia]]-Tabela1[[#This Row],[Informe o KM inicial do dia]])-Tabela1[[#This Row],[Caso tenha rodado particular alguma parte do trajeto, informe o total de KM a ser deduzido.]] -> 236 | V19: =IF(Tabela1[[#This Row],[Informe a data]]<DATE(2026,3,16), Tabela1[[#This Row],[KM Rodado]]*1.1, Tabela1[[#This Row],[KM Rodado]]*1.23) -> 259.6 | W19: =IFERROR(SUBSTITUTE(Tabela1[[#This Row],[Pedágio]],".",",",1)*1,0) -> 0 | X19: =IFERROR(SUBSTITUTE(Tabela1[[#This Row],[Estacionamento]],".",",",1)*1,0) -> 0 | Y19: =IFERROR(SUBSTITUTE(Tabela1[[#This Row],[Despesas Diversas (Jantar em viagem, Impressões, Etc)]],".",",",1)*1,0) -> 0 | Z19: =IFERROR(SUBSTITUTE(Tabela1[[#This Row],[Hospedagem]],".",",",1)*1,0) -> 219.94 | AA19: =IF(DAY(Tabela1[[#This Row],[Informe a data]])<=15,"1ª Quinzena","2ª Quinzena") -> 1ª Quinzena | AB19: =UPPER(TEXT(Tabela1[[#This Row],[Informe a data]],"mmmm")) -> JANEIRO | AC19: =_xlfn.CONCAT(Tabela1[[#This Row],[Selecione o Usuário]]," - ",TEXT(Tabela1[[#This Row],[Informe a data]],"dd-mm-aa")) -> #NAME?
A20: 46037.341 | B20: camila.althoff@mazzini.com.br | C20: CAMILA CRISTINE ALTHOFF | D20: Mlz4j72 | E20: 46036 | F20: 185662 | G20: https://drive.google.com/open?id=16bd2a0wg_uF7OIU-LmS20gupyXxpzxIU | H20: 185709 | I20: https://drive.google.com/open?id=1tNU22_rmd6TpdcXyoKtNGmjrsJ-Clovg | J20: Angeloni beira mar, atacadão via expressa, Angeloni capoeiras, Fort jardim atlântico | L20: Não | U20: =(Tabela1[[#This Row],[Informe o KM final do dia]]-Tabela1[[#This Row],[Informe o KM inicial do dia]])-Tabela1[[#This Row],[Caso tenha rodado particular alguma parte do trajeto, informe o total de KM a ser deduzido.]] -> 47 | V20: =IF(Tabela1[[#This Row],[Informe a data]]<DATE(2026,3,16), Tabela1[[#This Row],[KM Rodado]]*1.1, Tabela1[[#This Row],[KM Rodado]]*1.23) -> 51.7 | W20: =IFERROR(SUBSTITUTE(Tabela1[[#This Row],[Pedágio]],".",",",1)*1,0) -> 0 | X20: =IFERROR(SUBSTITUTE(Tabela1[[#This Row],[Estacionamento]],".",",",1)*1,0) -> 0 | Y20: =IFERROR(SUBSTITUTE(Tabela1[[#This Row],[Despesas Diversas (Jantar em viagem, Impressões, Etc)]],".",",",1)*1,0) -> 0 | Z20: =IFERROR(SUBSTITUTE(Tabela1[[#This Row],[Hospedagem]],".",",",1)*1,0) -> 0 | AA20: =IF(DAY(Tabela1[[#This Row],[Informe a data]])<=15,"1ª Quinzena","2ª Quinzena") -> 1ª Quinzena | AB20: =UPPER(TEXT(Tabela1[[#This Row],[Informe a data]],"mmmm")) -> JANEIRO | AC20: =_xlfn.CONCAT(Tabela1[[#This Row],[Selecione o Usuário]]," - ",TEXT(Tabela1[[#This Row],[Informe a data]],"dd-mm-aa")) -> #NAME?
A21: 46036.701 | B21: desyree.gaulke@mazzini.com.br | C21: Desyree Yasmin Gaulke Klebber | D21: QIL7H04 | E21: 46036 | F21: 117269 | G21: https://drive.google.com/open?id=1nz6okC6pw3Hytv7RaIvWfyGnNfWJOTzr | H21: 117506 | I21: https://drive.google.com/open?id=1RZEvaf1DkVshquScw34MBQcU0dyx3zhX | J21: BR ATACADISTA RIO DO SUL, FORT 255, COOPER IBIRAMA, COOPER RODEIO, MOCAM 403 | L21: Não | U21: =(Tabela1[[#This Row],[Informe o KM final do dia]]-Tabela1[[#This Row],[Informe o KM inicial do dia]])-Tabela1[[#This Row],[Caso tenha rodado particular alguma parte do trajeto, informe o total de KM a ser deduzido.]] -> 237 | V21: =IF(Tabela1[[#This Row],[Informe a data]]<DATE(2026,3,16), Tabela1[[#This Row],[KM Rodado]]*1.1, Tabela1[[#This Row],[KM Rodado]]*1.23) -> 260.7 | W21: =IFERROR(SUBSTITUTE(Tabela1[[#This Row],[Pedágio]],".",",",1)*1,0) -> 0 | X21: =IFERROR(SUBSTITUTE(Tabela1[[#This Row],[Estacionamento]],".",",",1)*1,0) -> 0 | Y21: =IFERROR(SUBSTITUTE(Tabela1[[#This Row],[Despesas Diversas (Jantar em viagem, Impressões, Etc)]],".",",",1)*1,0) -> 0 | Z21: =IFERROR(SUBSTITUTE(Tabela1[[#This Row],[Hospedagem]],".",",",1)*1,0) -> 0 | AA21: =IF(DAY(Tabela1[[#This Row],[Informe a data]])<=15,"1ª Quinzena","2ª Quinzena") -> 1ª Quinzena | AB21: =UPPER(TEXT(Tabela1[[#This Row],[Informe a data]],"mmmm")) -> JANEIRO | AC21: =_xlfn.CONCAT(Tabela1[[#This Row],[Selecione o Usuário]]," - ",TEXT(Tabela1[[#This Row],[Informe a data]],"dd-mm-aa")) -> #NAME?
A22: 46036.801 | B22: oliiveiiraa7@gmail.com | C22: GUSTAVO MATHEUS DE OLIVEIRA | D22: EUF3090 | E22: 46036 | F22: 159149 | G22: https://drive.google.com/open?id=16FEsnAg4spPtqAvXuKezJfoX9qMUTrxh | H22: 159414 | I22: https://drive.google.com/open?id=16dO2AfLsy6iNzerGw4qIUYD3XtSLz_uj | J22: Fort Chapeco, Atacadao avenida senador, Atacadao Chapecó e deslocamento | L22: Não | U22: =(Tabela1[[#This Row],[Informe o KM final do dia]]-Tabela1[[#This Row],[Informe o KM inicial do dia]])-Tabela1[[#This Row],[Caso tenha rodado particular alguma parte do trajeto, informe o total de KM a ser deduzido.]] -> 265 | V22: =IF(Tabela1[[#This Row],[Informe a data]]<DATE(2026,3,16), Tabela1[[#This Row],[KM Rodado]]*1.1, Tabela1[[#This Row],[KM Rodado]]*1.23) -> 291.5 | W22: =IFERROR(SUBSTITUTE(Tabela1[[#This Row],[Pedágio]],".",",",1)*1,0) -> 0 | X22: =IFERROR(SUBSTITUTE(Tabela1[[#This Row],[Estacionamento]],".",",",1)*1,0) -> 0 | Y22: =IFERROR(SUBSTITUTE(Tabela1[[#This Row],[Despesas Diversas (Jantar em viagem, Impressões, Etc)]],".",",",1)*1,0) -> 0 | Z22: =IFERROR(SUBSTITUTE(Tabela1[[#This Row],[Hospedagem]],".",",",1)*1,0) -> 0 | AA22: =IF(DAY(Tabela1[[#This Row],[Informe a data]])<=15,"1ª Quinzena","2ª Quinzena") -> 1ª Quinzena | AB22: =UPPER(TEXT(Tabela1[[#This Row],[Informe a data]],"mmmm")) -> JANEIRO | AC22: =_xlfn.CONCAT(Tabela1[[#This Row],[Selecione o Usuário]]," - ",TEXT(Tabela1[[#This Row],[Informe a data]],"dd-mm-aa")) -> #NAME?
A23: 46036.828 | B23: lombardi2025@gmail.com | C23: RICARDO ALEXANDRE LOMBARDI | D23: OWA4C07 | E23: 46036 | F23: 168113 | G23: https://drive.google.com/open?id=11IodFoCASvGaTdCmPaFQav7G8cFHYRiO | H23: 168215 | I23: https://drive.google.com/open?id=1up7n9UC13aQd1uK_4ItlyH7EBGOPv3Tq | J23: Komprao 51,brasil atacadista,condor comasa,casa Leandro,Fort Tuiuti,komprao 45,Fort 405,fort 905, komprao 50,Fort 250 | L23: Não | U23: =(Tabela1[[#This Row],[Informe o KM final do dia]]-Tabela1[[#This Row],[Informe o KM inicial do dia]])-Tabela1[[#This Row],[Caso tenha rodado particular alguma parte do trajeto, informe o total de KM a ser deduzido.]] -> 102 | V23: =IF(Tabela1[[#This Row],[Informe a data]]<DATE(2026,3,16), Tabela1[[#This Row],[KM Rodado]]*1.1, Tabela1[[#This Row],[KM Rodado]]*1.23) -> 112.2 | W23: =IFERROR(SUBSTITUTE(Tabela1[[#This Row],[Pedágio]],".",",",1)*1,0) -> 0 | X23: =IFERROR(SUBSTITUTE(Tabela1[[#This Row],[Estacionamento]],".",",",1)*1,0) -> 0 | Y23: =IFERROR(SUBSTITUTE(Tabela1[[#This Row],[Despesas Diversas (Jantar em viagem, Impressões, Etc)]],".",",",1)*1,0) -> 0 | Z23: =IFERROR(SUBSTITUTE(Tabela1[[#This Row],[Hospedagem]],".",",",1)*1,0) -> 0 | AA23: =IF(DAY(Tabela1[[#This Row],[Informe a data]])<=15,"1ª Quinzena","2ª Quinzena") -> 1ª Quinzena | AB23: =UPPER(TEXT(Tabela1[[#This Row],[Informe a data]],"mmmm")) -> JANEIRO | AC23: =_xlfn.CONCAT(Tabela1[[#This Row],[Selecione o Usuário]]," - ",TEXT(Tabela1[[#This Row],[Informe a data]],"dd-mm-aa")) -> #NAME?
A24: 46036.701 | B24: sabrina.pires@mazzini.com.br | C24: SABRINA DOS SANTOS PIRES | D24: azc9e32 | E24: 46036 | F24: 173277 | G24: https://drive.google.com/open?id=1lmqkqJRGldxk0YxFfRrgFuSTY3Ktp8AU | H24: 173401 | I24: https://drive.google.com/open?id=1_80jiqas8NG0LqhrPML0Aggj06tdFzCj | J24: Fort biguaçu Komprao não viver Fort barreiros Fort São José Komprao forquilhas Komprao ponte do imaruim | L24: Não | U24: =(Tabela1[[#This Row],[Informe o KM final do dia]]-Tabela1[[#This Row],[Informe o KM inicial do dia]])-Tabela1[[#This Row],[Caso tenha rodado particular alguma parte do trajeto, informe o total de KM a ser deduzido.]] -> 124 | V24: =IF(Tabela1[[#This Row],[Informe a data]]<DATE(2026,3,16), Tabela1[[#This Row],[KM Rodado]]*1.1, Tabela1[[#This Row],[KM Rodado]]*1.23) -> 136.4 | W24: =IFERROR(SUBSTITUTE(Tabela1[[#This Row],[Pedágio]],".",",",1)*1,0) -> 0 | X24: =IFERROR(SUBSTITUTE(Tabela1[[#This Row],[Estacionamento]],".",",",1)*1,0) -> 0 | Y24: =IFERROR(SUBSTITUTE(Tabela1[[#This Row],[Despesas Diversas (Jantar em viagem, Impressões, Etc)]],".",",",1)*1,0) -> 0 | Z24: =IFERROR(SUBSTITUTE(Tabela1[[#This Row],[Hospedagem]],".",",",1)*1,0) -> 0 | AA24: =IF(DAY(Tabela1[[#This Row],[Informe a data]])<=15,"1ª Quinzena","2ª Quinzena") -> 1ª Quinzena | AB24: =UPPER(TEXT(Tabela1[[#This Row],[Informe a data]],"mmmm")) -> JANEIRO | AC24: =_xlfn.CONCAT(Tabela1[[#This Row],[Selecione o Usuário]]," - ",TEXT(Tabela1[[#This Row],[Informe a data]],"dd-mm-aa")) -> #NAME?
A25: 46037.841 | B25: camila.althoff@mazzini.com.br | C25: CAMILA CRISTINE ALTHOFF | D25: Mlz4j72 | E25: 46037 | F25: 185709 | G25: https://drive.google.com/open?id=1HtVmdAdVtxxwySruCnc5U9ynTf37Nim3 | H25: 185799 | I25: https://drive.google.com/open?id=1qAppb28zIO0xulaZKQeSzkNaZ3Kbu7yS | J25: Zeus brasil, imperatriz Lagoa, Fort campeche | L25: Não | U25: =(Tabela1[[#This Row],[Informe o KM final do dia]]-Tabela1[[#This Row],[Informe o KM inicial do dia]])-Tabela1[[#This Row],[Caso tenha rodado particular alguma parte do trajeto, informe o total de KM a ser deduzido.]] -> 90 | V25: =IF(Tabela1[[#This Row],[Informe a data]]<DATE(2026,3,16), Tabela1[[#This Row],[KM Rodado]]*1.1, Tabela1[[#This Row],[KM Rodado]]*1.23) -> 99 | W25: =IFERROR(SUBSTITUTE(Tabela1[[#This Row],[Pedágio]],".",",",1)*1,0) -> 0 | X25: =IFERROR(SUBSTITUTE(Tabela1[[#This Row],[Estacionamento]],".",",",1)*1,0) -> 0 | Y25: =IFERROR(SUBSTITUTE(Tabela1[[#This Row],[Despesas Diversas (Jantar em viagem, Impressões, Etc)]],".",",",1)*1,0) -> 0 | Z25: =IFERROR(SUBSTITUTE(Tabela1[[#This Row],[Hospedagem]],".",",",1)*1,0) -> 0 | AA25: =IF(DAY(Tabela1[[#This Row],[Informe a data]])<=15,"1ª Quinzena","2ª Quinzena") -> 1ª Quinzena | AB25: =UPPER(TEXT(Tabela1[[#This Row],[Informe a data]],"mmmm")) -> JANEIRO | AC25: =_xlfn.CONCAT(Tabela1[[#This Row],[Selecione o Usuário]]," - ",TEXT(Tabela1[[#This Row],[Informe a data]],"dd-mm-aa")) -> #NAME?
A26: 46037.741 | B26: desyree.gaulke@mazzini.com.br | C26: Desyree Yasmin Gaulke Klebber | D26: QIL7H04 | E26: 46037 | F26: 117508 | G26: https://drive.google.com/open?id=101YYzxtGhhUZ9p_cFBoQcP8EThwSx9GX | H26: 117599 | I26: https://drive.google.com/open?id=12e1B5poMUOhkR8Ws6y2_UnsnzhxKEoGS | J26: central 101, brasil atacadista, bisteck park europeu e central 103 | L26: Não | U26: =(Tabela1[[#This Row],[Informe o KM final do dia]]-Tabela1[[#This Row],[Informe o KM inicial do dia]])-Tabela1[[#This Row],[Caso tenha rodado particular alguma parte do trajeto, informe o total de KM a ser deduzido.]] -> 91 | V26: =IF(Tabela1[[#This Row],[Informe a data]]<DATE(2026,3,16), Tabela1[[#This Row],[KM Rodado]]*1.1, Tabela1[[#This Row],[KM Rodado]]*1.23) -> 100.1 | W26: =IFERROR(SUBSTITUTE(Tabela1[[#This Row],[Pedágio]],".",",",1)*1,0) -> 0 | X26: =IFERROR(SUBSTITUTE(Tabela1[[#This Row],[Estacionamento]],".",",",1)*1,0) -> 0 | Y26: =IFERROR(SUBSTITUTE(Tabela1[[#This Row],[Despesas Diversas (Jantar em viagem, Impressões, Etc)]],".",",",1)*1,0) -> 0 | Z26: =IFERROR(SUBSTITUTE(Tabela1[[#This Row],[Hospedagem]],".",",",1)*1,0) -> 0 | AA26: =IF(DAY(Tabela1[[#This Row],[Informe a data]])<=15,"1ª Quinzena","2ª Quinzena") -> 1ª Quinzena | AB26: =UPPER(TEXT(Tabela1[[#This Row],[Informe a data]],"mmmm")) -> JANEIRO | AC26: =_xlfn.CONCAT(Tabela1[[#This Row],[Selecione o Usuário]]," - ",TEXT(Tabela1[[#This Row],[Informe a data]],"dd-mm-aa")) -> #NAME?
A27: 46031.984 | B27: lombardi2025@gmail.com | C27: RICARDO ALEXANDRE LOMBARDI | D27: OWA4C07 | E27: 46037 | F27: 167732 | G27: https://drive.google.com/open?id=1AXvwZRv892_hprYewYcHXx84QHYr1qH7 | H27: 167982 | I27: https://drive.google.com/open?id=1Q1_kRkJ2sX-7oQ3DBRYM7fdiwltKBH1h | J27: Blumenau buscar cestas | L27: Não | U27: =(Tabela1[[#This Row],[Informe o KM final do dia]]-Tabela1[[#This Row],[Informe o KM inicial do dia]])-Tabela1[[#This Row],[Caso tenha rodado particular alguma parte do trajeto, informe o total de KM a ser deduzido.]] -> 250 | V27: =IF(Tabela1[[#This Row],[Informe a data]]<DATE(2026,3,16), Tabela1[[#This Row],[KM Rodado]]*1.1, Tabela1[[#This Row],[KM Rodado]]*1.23) -> 275 | W27: =IFERROR(SUBSTITUTE(Tabela1[[#This Row],[Pedágio]],".",",",1)*1,0) -> 0 | X27: =IFERROR(SUBSTITUTE(Tabela1[[#This Row],[Estacionamento]],".",",",1)*1,0) -> 0 | Y27: =IFERROR(SUBSTITUTE(Tabela1[[#This Row],[Despesas Diversas (Jantar em viagem, Impressões, Etc)]],".",",",1)*1,0) -> 0 | Z27: =IFERROR(SUBSTITUTE(Tabela1[[#This Row],[Hospedagem]],".",",",1)*1,0) -> 0 | AA27: =IF(DAY(Tabela1[[#This Row],[Informe a data]])<=15,"1ª Quinzena","2ª Quinzena") -> 1ª Quinzena | AB27: =UPPER(TEXT(Tabela1[[#This Row],[Informe a data]],"mmmm")) -> JANEIRO | AC27: =_xlfn.CONCAT(Tabela1[[#This Row],[Selecione o Usuário]]," - ",TEXT(Tabela1[[#This Row],[Informe a data]],"dd-mm-aa")) -> #NAME?
A28: 46039.758 | B28: lombardi2025@gmail.com | C28: RICARDO ALEXANDRE LOMBARDI | D28: OWA4C07 | E28: 46037 | F28: 168215 | G28: https://drive.google.com/open?id=1ouE6eSrVHXymBJFB_k3BeJ9XFnm1ToRH | H28: 168251 | I28: https://drive.google.com/open?id=1DC_zfbetQ_HfThKiu77mnGRCgZQkHqC- | J28: Komprao 51, brasil atacadista,condor comasa,Fort Tuiuti, imperatriz | L28: Não | U28: =(Tabela1[[#This Row],[Informe o KM final do dia]]-Tabela1[[#This Row],[Informe o KM inicial do dia]])-Tabela1[[#This Row],[Caso tenha rodado particular alguma parte do trajeto, informe o total de KM a ser deduzido.]] -> 36 | V28: =IF(Tabela1[[#This Row],[Informe a data]]<DATE(2026,3,16), Tabela1[[#This Row],[KM Rodado]]*1.1, Tabela1[[#This Row],[KM Rodado]]*1.23) -> 39.6 | W28: =IFERROR(SUBSTITUTE(Tabela1[[#This Row],[Pedágio]],".",",",1)*1,0) -> 0 | X28: =IFERROR(SUBSTITUTE(Tabela1[[#This Row],[Estacionamento]],".",",",1)*1,0) -> 0 | Y28: =IFERROR(SUBSTITUTE(Tabela1[[#This Row],[Despesas Diversas (Jantar em viagem, Impressões, Etc)]],".",",",1)*1,0) -> 0 | Z28: =IFERROR(SUBSTITUTE(Tabela1[[#This Row],[Hospedagem]],".",",",1)*1,0) -> 0 | AA28: =IF(DAY(Tabela1[[#This Row],[Informe a data]])<=15,"1ª Quinzena","2ª Quinzena") -> 1ª Quinzena | AB28: =UPPER(TEXT(Tabela1[[#This Row],[Informe a data]],"mmmm")) -> JANEIRO | AC28: =_xlfn.CONCAT(Tabela1[[#This Row],[Selecione o Usuário]]," - ",TEXT(Tabela1[[#This Row],[Informe a data]],"dd-mm-aa")) -> #NAME?
A29: 46037.748 | B29: sabrina.pires@mazzini.com.br | C29: SABRINA DOS SANTOS PIRES | D29: Azc9e32 | E29: 46037 | F29: 173440 | G29: https://drive.google.com/open?id=1u7-tiIgVHFBB-dnS3fN077IvI7wRDsav | H29: 173510 | I29: https://drive.google.com/open?id=1kjVJQKGP8CE_wSOOrJ3byhnLPdPhMi3S | J29: Komprao pedra branca Fort 130 Fort kobrasol Fort biguaçu Komprao forquilhas | L29: Não | U29: =(Tabela1[[#This Row],[Informe o KM final do dia]]-Tabela1[[#This Row],[Informe o KM inicial do dia]])-Tabela1[[#This Row],[Caso tenha rodado particular alguma parte do trajeto, informe o total de KM a ser deduzido.]] -> 70 | V29: =IF(Tabela1[[#This Row],[Informe a data]]<DATE(2026,3,16), Tabela1[[#This Row],[KM Rodado]]*1.1, Tabela1[[#This Row],[KM Rodado]]*1.23) -> 77 | W29: =IFERROR(SUBSTITUTE(Tabela1[[#This Row],[Pedágio]],".",",",1)*1,0) -> 0 | X29: =IFERROR(SUBSTITUTE(Tabela1[[#This Row],[Estacionamento]],".",",",1)*1,0) -> 0 | Y29: =IFERROR(SUBSTITUTE(Tabela1[[#This Row],[Despesas Diversas (Jantar em viagem, Impressões, Etc)]],".",",",1)*1,0) -> 0 | Z29: =IFERROR(SUBSTITUTE(Tabela1[[#This Row],[Hospedagem]],".",",",1)*1,0) -> 0 | AA29: =IF(DAY(Tabela1[[#This Row],[Informe a data]])<=15,"1ª Quinzena","2ª Quinzena") -> 1ª Quinzena | AB29: =UPPER(TEXT(Tabela1[[#This Row],[Informe a data]],"mmmm")) -> JANEIRO | AC29: =_xlfn.CONCAT(Tabela1[[#This Row],[Selecione o Usuário]]," - ",TEXT(Tabela1[[#This Row],[Informe a data]],"dd-mm-aa")) -> #NAME?
A30: 46038.382 | B30: suelen.azevedo@mazzini.com.br | C30: SUELEN DOS SANTOS AZEVEDO | D30: Mfw6D17 | E30: 46037 | F30: 105938 | G30: https://drive.google.com/open?id=1ilqg8CyOvxRY6w9pWkwxvgP4QbgbeQua | H30: 105978 | I30: https://drive.google.com/open?id=1Xwh5s0I9SNmtUAS_XuxJyxhOPUmUXXpB | J30: Fui na loja 9 loja 82 loja 4 | L30: Não | U30: =(Tabela1[[#This Row],[Informe o KM final do dia]]-Tabela1[[#This Row],[Informe o KM inicial do dia]])-Tabela1[[#This Row],[Caso tenha rodado particular alguma parte do trajeto, informe o total de KM a ser deduzido.]] -> 40 | V30: =IF(Tabela1[[#This Row],[Informe a data]]<DATE(2026,3,16), Tabela1[[#This Row],[KM Rodado]]*1.1, Tabela1[[#This Row],[KM Rodado]]*1.23) -> 44 | W30: =IFERROR(SUBSTITUTE(Tabela1[[#This Row],[Pedágio]],".",",",1)*1,0) -> 0 | X30: =IFERROR(SUBSTITUTE(Tabela1[[#This Row],[Estacionamento]],".",",",1)*1,0) -> 0 | Y30: =IFERROR(SUBSTITUTE(Tabela1[[#This Row],[Despesas Diversas (Jantar em viagem, Impressões, Etc)]],".",",",1)*1,0) -> 0 | Z30: =IFERROR(SUBSTITUTE(Tabela1[[#This Row],[Hospedagem]],".",",",1)*1,0) -> 0 | AA30: =IF(DAY(Tabela1[[#This Row],[Informe a data]])<=15,"1ª Quinzena","2ª Quinzena") -> 1ª Quinzena | AB30: =UPPER(TEXT(Tabela1[[#This Row],[Informe a data]],"mmmm")) -> JANEIRO | AC30: =_xlfn.CONCAT(Tabela1[[#This Row],[Selecione o Usuário]]," - ",TEXT(Tabela1[[#This Row],[Informe a data]],"dd-mm-aa")) -> #NAME?
A31: 46038.797 | B31: camila.althoff@mazzini.com.br | C31: CAMILA CRISTINE ALTHOFF | D31: Mlz4j72 | E31: 46038 | F31: 185799 | G31: https://drive.google.com/open?id=1401-bPasXzKWnHL16uoAMKuHzbbHBrth | H31: 185861 | I31: https://drive.google.com/open?id=1qgfZWCYwxANbzSC53-QTKV1hcgVhP-eK | J31: Angeloni beira mar, Fort vargem, kock 47 | L31: Não | U31: =(Tabela1[[#This Row],[Informe o KM final do dia]]-Tabela1[[#This Row],[Informe o KM inicial do dia]])-Tabela1[[#This Row],[Caso tenha rodado particular alguma parte do trajeto, informe o total de KM a ser deduzido.]] -> 62 | V31: =IF(Tabela1[[#This Row],[Informe a data]]<DATE(2026,3,16), Tabela1[[#This Row],[KM Rodado]]*1.1, Tabela1[[#This Row],[KM Rodado]]*1.23) -> 68.2 | W31: =IFERROR(SUBSTITUTE(Tabela1[[#This Row],[Pedágio]],".",",",1)*1,0) -> 0 | X31: =IFERROR(SUBSTITUTE(Tabela1[[#This Row],[Estacionamento]],".",",",1)*1,0) -> 0 | Y31: =IFERROR(SUBSTITUTE(Tabela1[[#This Row],[Despesas Diversas (Jantar em viagem, Impressões, Etc)]],".",",",1)*1,0) -> 0 | Z31: =IFERROR(SUBSTITUTE(Tabela1[[#This Row],[Hospedagem]],".",",",1)*1,0) -> 0 | AA31: =IF(DAY(Tabela1[[#This Row],[Informe a data]])<=15,"1ª Quinzena","2ª Quinzena") -> 2ª Quinzena | AB31: =UPPER(TEXT(Tabela1[[#This Row],[Informe a data]],"mmmm")) -> JANEIRO | AC31: =_xlfn.CONCAT(Tabela1[[#This Row],[Selecione o Usuário]]," - ",TEXT(Tabela1[[#This Row],[Informe a data]],"dd-mm-aa")) -> #NAME?
... A33: 46041.509 | B33: sabrina.pires@mazzini.com.br | C33: SABRINA DOS SANTOS PIRES | D33: Azc9e32 | E33: 46038 | F33: 173510 | G33: https://drive.google.com/open?id=1EOKcHF4bd0tJEVAWqag1h2e-6i47OIy8 | H33: 173601 | I33: https://drive.google.com/open?id=1tQGr8F2GwsRaqcQGPDPKeu36bYGZGvt6 | J33: Fort biguaçu Komprao bom viver | L33: Não | U33: =(Tabela1[[#This Row],[Informe o KM final do dia]]-Tabela1[[#This Row],[Informe o KM inicial do dia]])-Tabela1[[#This Row],[Caso tenha rodado particular alguma parte do trajeto, informe o total de KM a ser deduzido.]] -> 91 | V33: =IF(Tabela1[[#This Row],[Informe a data]]<DATE(2026,3,16), Tabela1[[#This Row],[KM Rodado]]*1.1, Tabela1[[#This Row],[KM Rodado]]*1.23) -> 100.1 | W33: =IFERROR(SUBSTITUTE(Tabela1[[#This Row],[Pedágio]],".",",",1)*1,0) -> 0 | X33: =IFERROR(SUBSTITUTE(Tabela1[[#This Row],[Estacionamento]],".",",",1)*1,0) -> 0 | Y33: =IFERROR(SUBSTITUTE(Tabela1[[#This Row],[Despesas Diversas (Jantar em viagem, Impressões, Etc)]],".",",",1)*1,0) -> 0 | Z33: =IFERROR(SUBSTITUTE(Tabela1[[#This Row],[Hospedagem]],".",",",1)*1,0) -> 0 | AA33: =IF(DAY(Tabela1[[#This Row],[Informe a data]])<=15,"1ª Quinzena","2ª Quinzena") -> 2ª Quinzena | AB33: =UPPER(TEXT(Tabela1[[#This Row],[Informe a data]],"mmmm")) -> JANEIRO | AC33: =_xlfn.CONCAT(Tabela1[[#This Row],[Selecione o Usuário]]," - ",TEXT(Tabela1[[#This Row],[Informe a data]],"dd-mm-aa")) -> #NAME?
A34: 46040.086 | B34: desyree.gaulke@mazzini.com.br | C34: Desyree Yasmin Gaulke Klebber | D34: QIL7H04 | E34: 46039 | F34: 117705 | G34: https://drive.google.com/open?id=1ODiTtJTYKTRkzrxjvjVAobRZPJVTsUDp | H34: 117852 | I34: https://drive.google.com/open?id=17jc_Ct1nN_9pLx_646N_M79k5QCqKclX | J34: Zeus, unibox velha, Komprão 40, Cooper itoupava norte | K34: 43 | L34: Não | U34: =(Tabela1[[#This Row],[Informe o KM final do dia]]-Tabela1[[#This Row],[Informe o KM inicial do dia]])-Tabela1[[#This Row],[Caso tenha rodado particular alguma parte do trajeto, informe o total de KM a ser deduzido.]] -> 104 | V34: =IF(Tabela1[[#This Row],[Informe a data]]<DATE(2026,3,16), Tabela1[[#This Row],[KM Rodado]]*1.1, Tabela1[[#This Row],[KM Rodado]]*1.23) -> 114.4 | W34: =IFERROR(SUBSTITUTE(Tabela1[[#This Row],[Pedágio]],".",",",1)*1,0) -> 0 | X34: =IFERROR(SUBSTITUTE(Tabela1[[#This Row],[Estacionamento]],".",",",1)*1,0) -> 0 | Y34: =IFERROR(SUBSTITUTE(Tabela1[[#This Row],[Despesas Diversas (Jantar em viagem, Impressões, Etc)]],".",",",1)*1,0) -> 0 | Z34: =IFERROR(SUBSTITUTE(Tabela1[[#This Row],[Hospedagem]],".",",",1)*1,0) -> 0 | AA34: =IF(DAY(Tabela1[[#This Row],[Informe a data]])<=15,"1ª Quinzena","2ª Quinzena") -> 2ª Quinzena | AB34: =UPPER(TEXT(Tabela1[[#This Row],[Informe a data]],"mmmm")) -> JANEIRO | AC34: =_xlfn.CONCAT(Tabela1[[#This Row],[Selecione o Usuário]]," - ",TEXT(Tabela1[[#This Row],[Informe a data]],"dd-mm-aa")) -> #NAME?
A35: 46042.939 | B35: camila.althoff@mazzini.com.br | C35: CAMILA CRISTINE ALTHOFF | D35: Mlz4j72 | E35: 46042 | F35: 185868 | G35: https://drive.google.com/open?id=1IixB5LARqZMJYQq63D0sMw_XFfH2usa9 | H35: 186075 | I35: https://drive.google.com/open?id=17wA3nsyrkevLqTeOp0Bas-1dSgJTZ-eD | J35: Bistek Blumenau, Bistek shopping europeu, giasse | L35: Sim | M35: 5.70 | N35: https://drive.google.com/open?id=1BcXY8QKVuZEeSyybJnnr-qVmsRu9EkKV | Q35: 36.00 | R35: https://drive.google.com/open?id=17wFRESNwuUZfQVtOEITOhQWIbwhfCZAR | U35: =(Tabela1[[#This Row],[Informe o KM final do dia]]-Tabela1[[#This Row],[Informe o KM inicial do dia]])-Tabela1[[#This Row],[Caso tenha rodado particular alguma parte do trajeto, informe o total de KM a ser deduzido.]] -> 207 | V35: =IF(Tabela1[[#This Row],[Informe a data]]<DATE(2026,3,16), Tabela1[[#This Row],[KM Rodado]]*1.1, Tabela1[[#This Row],[KM Rodado]]*1.23) -> 227.7 | W35: =IFERROR(SUBSTITUTE(Tabela1[[#This Row],[Pedágio]],".",",",1)*1,0) -> 5.7 | X35: =IFERROR(SUBSTITUTE(Tabela1[[#This Row],[Estacionamento]],".",",",1)*1,0) -> 0 | Y35: =IFERROR(SUBSTITUTE(Tabela1[[#This Row],[Despesas Diversas (Jantar em viagem, Impressões, Etc)]],".",",",1)*1,0) -> 36 | Z35: =IFERROR(SUBSTITUTE(Tabela1[[#This Row],[Hospedagem]],".",",",1)*1,0) -> 0 | AA35: =IF(DAY(Tabela1[[#This Row],[Informe a data]])<=15,"1ª Quinzena","2ª Quinzena") -> 2ª Quinzena | AB35: =UPPER(TEXT(Tabela1[[#This Row],[Informe a data]],"mmmm")) -> JANEIRO | AC35: =_xlfn.CONCAT(Tabela1[[#This Row],[Selecione o Usuário]]," - ",TEXT(Tabela1[[#This Row],[Informe a data]],"dd-mm-aa")) -> #NAME?
A36: 46043.576 | B36: desyree.gaulke@mazzini.com.br | C36: Desyree Yasmin Gaulke Klebber | D36: QIL7H04 | E36: 46042 | F36: 117878 | G36: https://drive.google.com/open?id=1dtTPcLJLdvwZV8UYfen8RnlI6DfbvjFE | H36: 117979 | I36: https://drive.google.com/open?id=1FM-Iaewk2j_THY0pzZLQW2xSB78KLKpQ | J36: Atacado Blumenau, Super A, Bisteck garcia, Bisteck park europeu e Giassi | L36: Sim | Q36: 16.20 | R36: https://drive.google.com/open?id=1uRzDEYGMBMGEmtYGFVzijBJzs0XVkuQU | U36: =(Tabela1[[#This Row],[Informe o KM final do dia]]-Tabela1[[#This Row],[Informe o KM inicial do dia]])-Tabela1[[#This Row],[Caso tenha rodado particular alguma parte do trajeto, informe o total de KM a ser deduzido.]] -> 101 | V36: =IF(Tabela1[[#This Row],[Informe a data]]<DATE(2026,3,16), Tabela1[[#This Row],[KM Rodado]]*1.1, Tabela1[[#This Row],[KM Rodado]]*1.23) -> 111.1 | W36: =IFERROR(SUBSTITUTE(Tabela1[[#This Row],[Pedágio]],".",",",1)*1,0) -> 0 | X36: =IFERROR(SUBSTITUTE(Tabela1[[#This Row],[Estacionamento]],".",",",1)*1,0) -> 0 | Y36: =IFERROR(SUBSTITUTE(Tabela1[[#This Row],[Despesas Diversas (Jantar em viagem, Impressões, Etc)]],".",",",1)*1,0) -> 16.2 | Z36: =IFERROR(SUBSTITUTE(Tabela1[[#This Row],[Hospedagem]],".",",",1)*1,0) -> 0 | AA36: =IF(DAY(Tabela1[[#This Row],[Informe a data]])<=15,"1ª Quinzena","2ª Quinzena") -> 2ª Quinzena | AB36: =UPPER(TEXT(Tabela1[[#This Row],[Informe a data]],"mmmm")) -> JANEIRO | AC36: =_xlfn.CONCAT(Tabela1[[#This Row],[Selecione o Usuário]]," - ",TEXT(Tabela1[[#This Row],[Informe a data]],"dd-mm-aa")) -> #NAME?
A37: 46044.329 | B37: matheus.moraes@mazzini.com.br | C37: MATHEUS DA SILVA MORAES | D37: LCX1B11 | E37: 46043 | F37: 117979 | G37: https://drive.google.com/open?id=12FDq6hZP4T6WCKiV0LyKjxynfT_HzV3w | H37: 118048 | I37: https://drive.google.com/open?id=1JoZNoA-2p_OUB3AiGIHjvYAPzMCB1xY2 | J37: Fort Indaial, Komprao Indaial | L37: Não | U37: =(Tabela1[[#This Row],[Informe o KM final do dia]]-Tabela1[[#This Row],[Informe o KM inicial do dia]])-Tabela1[[#This Row],[Caso tenha rodado particular alguma parte do trajeto, informe o total de KM a ser deduzido.]] -> 69 | V37: =IF(Tabela1[[#This Row],[Informe a data]]<DATE(2026,3,16), Tabela1[[#This Row],[KM Rodado]]*1.1, Tabela1[[#This Row],[KM Rodado]]*1.23) -> 75.9 | W37: =IFERROR(SUBSTITUTE(Tabela1[[#This Row],[Pedágio]],".",",",1)*1,0) -> 0 | X37: =IFERROR(SUBSTITUTE(Tabela1[[#This Row],[Estacionamento]],".",",",1)*1,0) -> 0 | Y37: =IFERROR(SUBSTITUTE(Tabela1[[#This Row],[Despesas Diversas (Jantar em viagem, Impressões, Etc)]],".",",",1)*1,0) -> 0 | Z37: =IFERROR(SUBSTITUTE(Tabela1[[#This Row],[Hospedagem]],".",",",1)*1,0) -> 0 | AA37: =IF(DAY(Tabela1[[#This Row],[Informe a data]])<=15,"1ª Quinzena","2ª Quinzena") -> 2ª Quinzena | AB37: =UPPER(TEXT(Tabela1[[#This Row],[Informe a data]],"mmmm")) -> JANEIRO | AC37: =_xlfn.CONCAT(Tabela1[[#This Row],[Selecione o Usuário]]," - ",TEXT(Tabela1[[#This Row],[Informe a data]],"dd-mm-aa")) -> #NAME?
A38: 46050.566 | B38: sussuazevedo.com@icloud.com | C38: SUELEN DOS SANTOS AZEVEDO | D38: Mfw6D17 | E38: 46043 | F38: 105979 | G38: https://drive.google.com/open?id=1AB714jGoFQ9D2xYBDJKEWHTMFkhZlskc | H38: 106037 | I38: https://drive.google.com/open?id=12lrURgqqun8GI-0i7KBwlfd4xncxDVtE | J38: Itajai e camboriu | L38: Não | U38: =(Tabela1[[#This Row],[Informe o KM final do dia]]-Tabela1[[#This Row],[Informe o KM inicial do dia]])-Tabela1[[#This Row],[Caso tenha rodado particular alguma parte do trajeto, informe o total de KM a ser deduzido.]] -> 58 | V38: =IF(Tabela1[[#This Row],[Informe a data]]<DATE(2026,3,16), Tabela1[[#This Row],[KM Rodado]]*1.1, Tabela1[[#This Row],[KM Rodado]]*1.23) -> 63.8 | W38: =IFERROR(SUBSTITUTE(Tabela1[[#This Row],[Pedágio]],".",",",1)*1,0) -> 0 | X38: =IFERROR(SUBSTITUTE(Tabela1[[#This Row],[Estacionamento]],".",",",1)*1,0) -> 0 | Y38: =IFERROR(SUBSTITUTE(Tabela1[[#This Row],[Despesas Diversas (Jantar em viagem, Impressões, Etc)]],".",",",1)*1,0) -> 0 | Z38: =IFERROR(SUBSTITUTE(Tabela1[[#This Row],[Hospedagem]],".",",",1)*1,0) -> 0 | AA38: =IF(DAY(Tabela1[[#This Row],[Informe a data]])<=15,"1ª Quinzena","2ª Quinzena") -> 2ª Quinzena | AB38: =UPPER(TEXT(Tabela1[[#This Row],[Informe a data]],"mmmm")) -> JANEIRO | AC38: =_xlfn.CONCAT(Tabela1[[#This Row],[Selecione o Usuário]]," - ",TEXT(Tabela1[[#This Row],[Informe a data]],"dd-mm-aa")) -> #NAME?
A39: 46050.58 | B39: sussuazevedo.com@icloud.com | C39: SUELEN DOS SANTOS AZEVEDO | D39: Mfw6d17 | E39: 46043 | F39: 106037 | G39: https://drive.google.com/open?id=1DCr--91rTOaEQet1tw6ys1dFcLq6PaMJ | H39: 106074 | I39: https://drive.google.com/open?id=1835HA697di9eJrV1p5nY1OzuFhx20-Ne | J39: Itapema porto belo | L39: Não | U39: =(Tabela1[[#This Row],[Informe o KM final do dia]]-Tabela1[[#This Row],[Informe o KM inicial do dia]])-Tabela1[[#This Row],[Caso tenha rodado particular alguma parte do trajeto, informe o total de KM a ser deduzido.]] -> 37 | V39: =IF(Tabela1[[#This Row],[Informe a data]]<DATE(2026,3,16), Tabela1[[#This Row],[KM Rodado]]*1.1, Tabela1[[#This Row],[KM Rodado]]*1.23) -> 40.7 | W39: =IFERROR(SUBSTITUTE(Tabela1[[#This Row],[Pedágio]],".",",",1)*1,0) -> 0 | X39: =IFERROR(SUBSTITUTE(Tabela1[[#This Row],[Estacionamento]],".",",",1)*1,0) -> 0 | Y39: =IFERROR(SUBSTITUTE(Tabela1[[#This Row],[Despesas Diversas (Jantar em viagem, Impressões, Etc)]],".",",",1)*1,0) -> 0 | Z39: =IFERROR(SUBSTITUTE(Tabela1[[#This Row],[Hospedagem]],".",",",1)*1,0) -> 0 | AA39: =IF(DAY(Tabela1[[#This Row],[Informe a data]])<=15,"1ª Quinzena","2ª Quinzena") -> 2ª Quinzena | AB39: =UPPER(TEXT(Tabela1[[#This Row],[Informe a data]],"mmmm")) -> JANEIRO | AC39: =_xlfn.CONCAT(Tabela1[[#This Row],[Selecione o Usuário]]," - ",TEXT(Tabela1[[#This Row],[Informe a data]],"dd-mm-aa")) -> #NAME?
A40: 46044.387 | B40: camila.althoff@mazzini.com.br | C40: CAMILA CRISTINE ALTHOFF | D40: Mlz4j72 | E40: 46044 | F40: 185868 | G40: https://drive.google.com/open?id=1wNE0V2_Dt8sbFDJ33t_fOoujQFfkhrKO | H40: 186244 | I40: https://drive.google.com/open?id=1RDPhnao_LiL9yXpeH5PnloPxuL8_2RYu | J40: Hotel Blumenau, casa | L40: Sim | M40: 5.70 | N40: https://drive.google.com/open?id=11MFU9nQtn94uwTv1qEDKfUnZ6hQ5vNaA | R40: https://drive.google.com/open?id=18ZTL7TwuiV_pNfJ8OfapuQW3VpPvsBhN | S40: 221.45 | U40: =(Tabela1[[#This Row],[Informe o KM final do dia]]-Tabela1[[#This Row],[Informe o KM inicial do dia]])-Tabela1[[#This Row],[Caso tenha rodado particular alguma parte do trajeto, informe o total de KM a ser deduzido.]] -> 376 | V40: =IF(Tabela1[[#This Row],[Informe a data]]<DATE(2026,3,16), Tabela1[[#This Row],[KM Rodado]]*1.1, Tabela1[[#This Row],[KM Rodado]]*1.23) -> 413.6 | W40: =IFERROR(SUBSTITUTE(Tabela1[[#This Row],[Pedágio]],".",",",1)*1,0) -> 5.7 | X40: =IFERROR(SUBSTITUTE(Tabela1[[#This Row],[Estacionamento]],".",",",1)*1,0) -> 0 | Y40: =IFERROR(SUBSTITUTE(Tabela1[[#This Row],[Despesas Diversas (Jantar em viagem, Impressões, Etc)]],".",",",1)*1,0) -> 0 | Z40: =IFERROR(SUBSTITUTE(Tabela1[[#This Row],[Hospedagem]],".",",",1)*1,0) -> 221.45 | AA40: =IF(DAY(Tabela1[[#This Row],[Informe a data]])<=15,"1ª Quinzena","2ª Quinzena") -> 2ª Quinzena | AB40: =UPPER(TEXT(Tabela1[[#This Row],[Informe a data]],"mmmm")) -> JANEIRO | AC40: =_xlfn.CONCAT(Tabela1[[#This Row],[Selecione o Usuário]]," - ",TEXT(Tabela1[[#This Row],[Informe a data]],"dd-mm-aa")) -> #NAME?
A41: 46044.98 | B41: camila.althoff@mazzini.com.br | C41: CAMILA CRISTINE ALTHOFF | D41: Mlz4j72 | E41: 46044 | F41: 186244 | G41: https://drive.google.com/open?id=17kiP2PnKa0h85Wn3hEvNkB-HKHZOXSpm | H41: 186271 | I41: https://drive.google.com/open?id=1Aq5r-yiyrz9JsRn2Krqxyolr6XtMGKZP | J41: Carrefour, Brasil Atacadista Rio Tavares | L41: Sim | O41: 20.00 | P41: https://drive.google.com/open?id=1ZqGpgSQQlOlNggkAcumH-WSKRsX6mifT | U41: =(Tabela1[[#This Row],[Informe o KM final do dia]]-Tabela1[[#This Row],[Informe o KM inicial do dia]])-Tabela1[[#This Row],[Caso tenha rodado particular alguma parte do trajeto, informe o total de KM a ser deduzido.]] -> 27 | V41: =IF(Tabela1[[#This Row],[Informe a data]]<DATE(2026,3,16), Tabela1[[#This Row],[KM Rodado]]*1.1, Tabela1[[#This Row],[KM Rodado]]*1.23) -> 29.7 | W41: =IFERROR(SUBSTITUTE(Tabela1[[#This Row],[Pedágio]],".",",",1)*1,0) -> 0 | X41: =IFERROR(SUBSTITUTE(Tabela1[[#This Row],[Estacionamento]],".",",",1)*1,0) -> 20 | Y41: =IFERROR(SUBSTITUTE(Tabela1[[#This Row],[Despesas Diversas (Jantar em viagem, Impressões, Etc)]],".",",",1)*1,0) -> 0 | Z41: =IFERROR(SUBSTITUTE(Tabela1[[#This Row],[Hospedagem]],".",",",1)*1,0) -> 0 | AA41: =IF(DAY(Tabela1[[#This Row],[Informe a data]])<=15,"1ª Quinzena","2ª Quinzena") -> 2ª Quinzena | AB41: =UPPER(TEXT(Tabela1[[#This Row],[Informe a data]],"mmmm")) -> JANEIRO | AC41: =_xlfn.CONCAT(Tabela1[[#This Row],[Selecione o Usuário]]," - ",TEXT(Tabela1[[#This Row],[Informe a data]],"dd-mm-aa")) -> #NAME?
A42: 46044.891 | B42: matheus.moraes@mazzini.com.br | C42: MATHEUS DA SILVA MORAES | D42: LCX1B11 | E42: 46044 | F42: 118050 | G42: https://drive.google.com/open?id=1HWp5cUN2ckfvU-Z25ATf-aHYKkV2dT8x | H42: 118169 | I42: https://drive.google.com/open?id=1kmuv7e1lImkB6vWW7JWkOvINP-Ff9ZgJ | J42: Brasil Atacadista, S5 Unibox, Komprao40 Agua Verde, Cooper Garcia Florianopolis Sc, Gtop Escola Agricola 20 | L42: Não | U42: =(Tabela1[[#This Row],[Informe o KM final do dia]]-Tabela1[[#This Row],[Informe o KM inicial do dia]])-Tabela1[[#This Row],[Caso tenha rodado particular alguma parte do trajeto, informe o total de KM a ser deduzido.]] -> 119 | V42: =IF(Tabela1[[#This Row],[Informe a data]]<DATE(2026,3,16), Tabela1[[#This Row],[KM Rodado]]*1.1, Tabela1[[#This Row],[KM Rodado]]*1.23) -> 130.9 | W42: =IFERROR(SUBSTITUTE(Tabela1[[#This Row],[Pedágio]],".",",",1)*1,0) -> 0 | X42: =IFERROR(SUBSTITUTE(Tabela1[[#This Row],[Estacionamento]],".",",",1)*1,0) -> 0 | Y42: =IFERROR(SUBSTITUTE(Tabela1[[#This Row],[Despesas Diversas (Jantar em viagem, Impressões, Etc)]],".",",",1)*1,0) -> 0 | Z42: =IFERROR(SUBSTITUTE(Tabela1[[#This Row],[Hospedagem]],".",",",1)*1,0) -> 0 | AA42: =IF(DAY(Tabela1[[#This Row],[Informe a data]])<=15,"1ª Quinzena","2ª Quinzena") -> 2ª Quinzena | AB42: =UPPER(TEXT(Tabela1[[#This Row],[Informe a data]],"mmmm")) -> JANEIRO | AC42: =_xlfn.CONCAT(Tabela1[[#This Row],[Selecione o Usuário]]," - ",TEXT(Tabela1[[#This Row],[Informe a data]],"dd-mm-aa")) -> #NAME?
A43: 46046.742 | B43: sabrina.pires@mazzini.vom.br | C43: SABRINA DOS SANTOS PIRES | D43: Azc9e32 | E43: 46044 | F43: 173758 | G43: https://drive.google.com/open?id=198YgsxkVElI5kvBFFKMbW1FScNZG9U0w | H43: 173852 | I43: https://drive.google.com/open?id=1349vFrcsP6nLXZxcMNVgRSHZmuEjmOMx | J43: Fort atacadista Komprao forquilhas | L43: Não | U43: =(Tabela1[[#This Row],[Informe o KM final do dia]]-Tabela1[[#This Row],[Informe o KM inicial do dia]])-Tabela1[[#This Row],[Caso tenha rodado particular alguma parte do trajeto, informe o total de KM a ser deduzido.]] -> 94 | V43: =IF(Tabela1[[#This Row],[Informe a data]]<DATE(2026,3,16), Tabela1[[#This Row],[KM Rodado]]*1.1, Tabela1[[#This Row],[KM Rodado]]*1.23) -> 103.4 | W43: =IFERROR(SUBSTITUTE(Tabela1[[#This Row],[Pedágio]],".",",",1)*1,0) -> 0 | X43: =IFERROR(SUBSTITUTE(Tabela1[[#This Row],[Estacionamento]],".",",",1)*1,0) -> 0 | Y43: =IFERROR(SUBSTITUTE(Tabela1[[#This Row],[Despesas Diversas (Jantar em viagem, Impressões, Etc)]],".",",",1)*1,0) -> 0 | Z43: =IFERROR(SUBSTITUTE(Tabela1[[#This Row],[Hospedagem]],".",",",1)*1,0) -> 0 | AA43: =IF(DAY(Tabela1[[#This Row],[Informe a data]])<=15,"1ª Quinzena","2ª Quinzena") -> 2ª Quinzena | AB43: =UPPER(TEXT(Tabela1[[#This Row],[Informe a data]],"mmmm")) -> JANEIRO | AC43: =_xlfn.CONCAT(Tabela1[[#This Row],[Selecione o Usuário]]," - ",TEXT(Tabela1[[#This Row],[Informe a data]],"dd-mm-aa")) -> #NAME?
A44: 46045.715 | B44: camila.althoff@mazzini.com.br | C44: CAMILA CRISTINE ALTHOFF | D44: Mlz4j72 | E44: 46045 | F44: 186271 | G44: https://drive.google.com/open?id=1Todrej8TjIj_vrgtnGvNl8ojzjOXGxOs | H44: 186306 | I44: https://drive.google.com/open?id=1zNTkIIzA0EGeZp6GPKyEABlXjNLSvfh7 | J44: Sams, Fort jardim atlântico, imperatriz coqueiros | L44: Não | U44: =(Tabela1[[#This Row],[Informe o KM final do dia]]-Tabela1[[#This Row],[Informe o KM inicial do dia]])-Tabela1[[#This Row],[Caso tenha rodado particular alguma parte do trajeto, informe o total de KM a ser deduzido.]] -> 35 | V44: =IF(Tabela1[[#This Row],[Informe a data]]<DATE(2026,3,16), Tabela1[[#This Row],[KM Rodado]]*1.1, Tabela1[[#This Row],[KM Rodado]]*1.23) -> 38.5 | W44: =IFERROR(SUBSTITUTE(Tabela1[[#This Row],[Pedágio]],".",",",1)*1,0) -> 0 | X44: =IFERROR(SUBSTITUTE(Tabela1[[#This Row],[Estacionamento]],".",",",1)*1,0) -> 0 | Y44: =IFERROR(SUBSTITUTE(Tabela1[[#This Row],[Despesas Diversas (Jantar em viagem, Impressões, Etc)]],".",",",1)*1,0) -> 0 | Z44: =IFERROR(SUBSTITUTE(Tabela1[[#This Row],[Hospedagem]],".",",",1)*1,0) -> 0 | AA44: =IF(DAY(Tabela1[[#This Row],[Informe a data]])<=15,"1ª Quinzena","2ª Quinzena") -> 2ª Quinzena | AB44: =UPPER(TEXT(Tabela1[[#This Row],[Informe a data]],"mmmm")) -> JANEIRO | AC44: =_xlfn.CONCAT(Tabela1[[#This Row],[Selecione o Usuário]]," - ",TEXT(Tabela1[[#This Row],[Informe a data]],"dd-mm-aa")) -> #NAME?
A45: 46045.777 | B45: matheus.moraes@mazzini.com.br | C45: MATHEUS DA SILVA MORAES | D45: LCX1B11 | E45: 46045 | F45: 118174 | G45: https://drive.google.com/open?id=1bLSoBfQUXz-MQZ9reu6YBDvu9pFDYJbf | H45: 118341 | I45: https://drive.google.com/open?id=1Jjy-4yWTFWpC_tFvaonRhtVHB0MdoCel | J45: Supermercados Central 104, Komprao36 Brusque Guarani, Fort Brusque | L45: Sim | Q45: 9.00 | R45: https://drive.google.com/open?id=1NmurPePapOdfIZSLkJ07Lhvwg7fPcftb | T45: Crachá de supervisor | U45: =(Tabela1[[#This Row],[Informe o KM final do dia]]-Tabela1[[#This Row],[Informe o KM inicial do dia]])-Tabela1[[#This Row],[Caso tenha rodado particular alguma parte do trajeto, informe o total de KM a ser deduzido.]] -> 167 | V45: =IF(Tabela1[[#This Row],[Informe a data]]<DATE(2026,3,16), Tabela1[[#This Row],[KM Rodado]]*1.1, Tabela1[[#This Row],[KM Rodado]]*1.23) -> 183.7 | W45: =IFERROR(SUBSTITUTE(Tabela1[[#This Row],[Pedágio]],".",",",1)*1,0) -> 0 | X45: =IFERROR(SUBSTITUTE(Tabela1[[#This Row],[Estacionamento]],".",",",1)*1,0) -> 0 | Y45: =IFERROR(SUBSTITUTE(Tabela1[[#This Row],[Despesas Diversas (Jantar em viagem, Impressões, Etc)]],".",",",1)*1,0) -> 9 | Z45: =IFERROR(SUBSTITUTE(Tabela1[[#This Row],[Hospedagem]],".",",",1)*1,0) -> 0 | AA45: =IF(DAY(Tabela1[[#This Row],[Informe a data]])<=15,"1ª Quinzena","2ª Quinzena") -> 2ª Quinzena | AB45: =UPPER(TEXT(Tabela1[[#This Row],[Informe a data]],"mmmm")) -> JANEIRO | AC45: =_xlfn.CONCAT(Tabela1[[#This Row],[Selecione o Usuário]]," - ",TEXT(Tabela1[[#This Row],[Informe a data]],"dd-mm-aa")) -> #NAME?
A46: 46048.91 | B46: lombardi2025@gmail.com | C46: RICARDO ALEXANDRE LOMBARDI | D46: OWA4C07 | E46: 46045 | F46: 168367 | G46: https://drive.google.com/open?id=1p3AgKlCEHpAmKgeaB6e9JCsRHNukQpJz | H46: 168479 | I46: https://drive.google.com/open?id=1OpxKZbx-Frq0o-_JdHRTs4ln0zV1NdLy | J46: Komprao 50,Ervino busca de material | L46: Não | U46: =(Tabela1[[#This Row],[Informe o KM final do dia]]-Tabela1[[#This Row],[Informe o KM inicial do dia]])-Tabela1[[#This Row],[Caso tenha rodado particular alguma parte do trajeto, informe o total de KM a ser deduzido.]] -> 112 | V46: =IF(Tabela1[[#This Row],[Informe a data]]<DATE(2026,3,16), Tabela1[[#This Row],[KM Rodado]]*1.1, Tabela1[[#This Row],[KM Rodado]]*1.23) -> 123.2 | W46: =IFERROR(SUBSTITUTE(Tabela1[[#This Row],[Pedágio]],".",",",1)*1,0) -> 0 | X46: =IFERROR(SUBSTITUTE(Tabela1[[#This Row],[Estacionamento]],".",",",1)*1,0) -> 0 | Y46: =IFERROR(SUBSTITUTE(Tabela1[[#This Row],[Despesas Diversas (Jantar em viagem, Impressões, Etc)]],".",",",1)*1,0) -> 0 | Z46: =IFERROR(SUBSTITUTE(Tabela1[[#This Row],[Hospedagem]],".",",",1)*1,0) -> 0 | AA46: =IF(DAY(Tabela1[[#This Row],[Informe a data]])<=15,"1ª Quinzena","2ª Quinzena") -> 2ª Quinzena | AB46: =UPPER(TEXT(Tabela1[[#This Row],[Informe a data]],"mmmm")) -> JANEIRO | AC46: =_xlfn.CONCAT(Tabela1[[#This Row],[Selecione o Usuário]]," - ",TEXT(Tabela1[[#This Row],[Informe a data]],"dd-mm-aa")) -> #NAME?
A47: 46046.745 | B47: sabrina.pires@mazzini.com.br | C47: SABRINA DOS SANTOS PIRES | D47: Azc9E32 | E47: 46045 | F47: 173852 | G47: https://drive.google.com/open?id=1840PHBhKeWRx1ByapMfvfObqGKcv43r5 | H47: 173935 | I47: https://drive.google.com/open?id=1F8JCua_RiNqCLINcFTk3iUTJSsYzVYFj | J47: Fort atacadista Brasil atacadista Komprao Komprao Fort | L47: Não | U47: =(Tabela1[[#This Row],[Informe o KM final do dia]]-Tabela1[[#This Row],[Informe o KM inicial do dia]])-Tabela1[[#This Row],[Caso tenha rodado particular alguma parte do trajeto, informe o total de KM a ser deduzido.]] -> 83 | V47: =IF(Tabela1[[#This Row],[Informe a data]]<DATE(2026,3,16), Tabela1[[#This Row],[KM Rodado]]*1.1, Tabela1[[#This Row],[KM Rodado]]*1.23) -> 91.3 | W47: =IFERROR(SUBSTITUTE(Tabela1[[#This Row],[Pedágio]],".",",",1)*1,0) -> 0 | X47: =IFERROR(SUBSTITUTE(Tabela1[[#This Row],[Estacionamento]],".",",",1)*1,0) -> 0 | Y47: =IFERROR(SUBSTITUTE(Tabela1[[#This Row],[Despesas Diversas (Jantar em viagem, Impressões, Etc)]],".",",",1)*1,0) -> 0 | Z47: =IFERROR(SUBSTITUTE(Tabela1[[#This Row],[Hospedagem]],".",",",1)*1,0) -> 0 | AA47: =IF(DAY(Tabela1[[#This Row],[Informe a data]])<=15,"1ª Quinzena","2ª Quinzena") -> 2ª Quinzena | AB47: =UPPER(TEXT(Tabela1[[#This Row],[Informe a data]],"mmmm")) -> JANEIRO | AC47: =_xlfn.CONCAT(Tabela1[[#This Row],[Selecione o Usuário]]," - ",TEXT(Tabela1[[#This Row],[Informe a data]],"dd-mm-aa")) -> #NAME?
A48: 46048.962 | B48: matheus.moraes@mazzini.com.br | C48: MATHEUS DA SILVA MORAES | D48: LCX1B11 | E48: 46048 | F48: 118516 | G48: https://drive.google.com/open?id=1qjrq6I3g_2UkqJYgb_xBrXn94rcHzYxw | H48: 118690 | I48: https://drive.google.com/open?id=1xZBCmfUAVQak-smXin6f_NvLcjMlWUE1 | J48: Cooper Caçadores, Cooper Gen. Osorio, Cooper Filial Vila N, Gtop Escola Agricola, Komprao36 Brusque Guarani, Fort Brusque | L48: Não | U48: =(Tabela1[[#This Row],[Informe o KM final do dia]]-Tabela1[[#This Row],[Informe o KM inicial do dia]])-Tabela1[[#This Row],[Caso tenha rodado particular alguma parte do trajeto, informe o total de KM a ser deduzido.]] -> 174 | V48: =IF(Tabela1[[#This Row],[Informe a data]]<DATE(2026,3,16), Tabela1[[#This Row],[KM Rodado]]*1.1, Tabela1[[#This Row],[KM Rodado]]*1.23) -> 191.4 | W48: =IFERROR(SUBSTITUTE(Tabela1[[#This Row],[Pedágio]],".",",",1)*1,0) -> 0 | X48: =IFERROR(SUBSTITUTE(Tabela1[[#This Row],[Estacionamento]],".",",",1)*1,0) -> 0 | Y48: =IFERROR(SUBSTITUTE(Tabela1[[#This Row],[Despesas Diversas (Jantar em viagem, Impressões, Etc)]],".",",",1)*1,0) -> 0 | Z48: =IFERROR(SUBSTITUTE(Tabela1[[#This Row],[Hospedagem]],".",",",1)*1,0) -> 0 | AA48: =IF(DAY(Tabela1[[#This Row],[Informe a data]])<=15,"1ª Quinzena","2ª Quinzena") -> 2ª Quinzena | AB48: =UPPER(TEXT(Tabela1[[#This Row],[Informe a data]],"mmmm")) -> JANEIRO | AC48: =_xlfn.CONCAT(Tabela1[[#This Row],[Selecione o Usuário]]," - ",TEXT(Tabela1[[#This Row],[Informe a data]],"dd-mm-aa")) -> #NAME?
A49: 46048.913 | B49: lombardi2025@gmail.com | C49: RICARDO ALEXANDRE LOMBARDI | D49: OWA4C07 | E49: 46048 | F49: 168525 | G49: https://drive.google.com/open?id=16ZbJiqGNFJbYGpgZwneW9Vwp7R1Nllce | H49: 168556 | I49: https://drive.google.com/open?id=1mqn3uWVohBSmOb3IrjGd33Q8PhbH-fHu | J49: Brasília rua tupi,komprao 51, Brasília | L49: Não | U49: =(Tabela1[[#This Row],[Informe o KM final do dia]]-Tabela1[[#This Row],[Informe o KM inicial do dia]])-Tabela1[[#This Row],[Caso tenha rodado particular alguma parte do trajeto, informe o total de KM a ser deduzido.]] -> 31 | V49: =IF(Tabela1[[#This Row],[Informe a data]]<DATE(2026,3,16), Tabela1[[#This Row],[KM Rodado]]*1.1, Tabela1[[#This Row],[KM Rodado]]*1.23) -> 34.1 | W49: =IFERROR(SUBSTITUTE(Tabela1[[#This Row],[Pedágio]],".",",",1)*1,0) -> 0 | X49: =IFERROR(SUBSTITUTE(Tabela1[[#This Row],[Estacionamento]],".",",",1)*1,0) -> 0 | Y49: =IFERROR(SUBSTITUTE(Tabela1[[#This Row],[Despesas Diversas (Jantar em viagem, Impressões, Etc)]],".",",",1)*1,0) -> 0 | Z49: =IFERROR(SUBSTITUTE(Tabela1[[#This Row],[Hospedagem]],".",",",1)*1,0) -> 0 | AA49: =IF(DAY(Tabela1[[#This Row],[Informe a data]])<=15,"1ª Quinzena","2ª Quinzena") -> 2ª Quinzena | AB49: =UPPER(TEXT(Tabela1[[#This Row],[Informe a data]],"mmmm")) -> JANEIRO | AC49: =_xlfn.CONCAT(Tabela1[[#This Row],[Selecione o Usuário]]," - ",TEXT(Tabela1[[#This Row],[Informe a data]],"dd-mm-aa")) -> #NAME?
A50: 46050.563 | B50: sussuazevedo.com@icloud.com | C50: SUELEN DOS SANTOS AZEVEDO | D50: MFW6D17 | E50: 46048 | F50: 106211 | G50: https://drive.google.com/open?id=1dfV85vO3LuQgkem8jFoWmWmlwBV4G-vz | H50: 106294 | I50: https://drive.google.com/open?id=1tksS1GNjF61GQM9ThJp5AxgcugxW7_Kr | J50: Todas de camboriu | L50: Não | U50: =(Tabela1[[#This Row],[Informe o KM final do dia]]-Tabela1[[#This Row],[Informe o KM inicial do dia]])-Tabela1[[#This Row],[Caso tenha rodado particular alguma parte do trajeto, informe o total de KM a ser deduzido.]] -> 83 | V50: =IF(Tabela1[[#This Row],[Informe a data]]<DATE(2026,3,16), Tabela1[[#This Row],[KM Rodado]]*1.1, Tabela1[[#This Row],[KM Rodado]]*1.23) -> 91.3 | W50: =IFERROR(SUBSTITUTE(Tabela1[[#This Row],[Pedágio]],".",",",1)*1,0) -> 0 | X50: =IFERROR(SUBSTITUTE(Tabela1[[#This Row],[Estacionamento]],".",",",1)*1,0) -> 0 | Y50: =IFERROR(SUBSTITUTE(Tabela1[[#This Row],[Despesas Diversas (Jantar em viagem, Impressões, Etc)]],".",",",1)*1,0) -> 0 | Z50: =IFERROR(SUBSTITUTE(Tabela1[[#This Row],[Hospedagem]],".",",",1)*1,0) -> 0 | AA50: =IF(DAY(Tabela1[[#This Row],[Informe a data]])<=15,"1ª Quinzena","2ª Quinzena") -> 2ª Quinzena | AB50: =UPPER(TEXT(Tabela1[[#This Row],[Informe a data]],"mmmm")) -> JANEIRO | AC50: =_xlfn.CONCAT(Tabela1[[#This Row],[Selecione o Usuário]]," - ",TEXT(Tabela1[[#This Row],[Informe a data]],"dd-mm-aa")) -> #NAME?
A51: 46050.57 | B51: camila.althoff@mazzini.com.br | C51: CAMILA CRISTINE ALTHOFF | D51: Mlz4j72 | E51: 46049 | F51: 186316 | G51: https://drive.google.com/open?id=1gh1UKg0iTDnBw6eGkoKfb3QGv8lHhrZb | H51: 186535 | I51: https://drive.google.com/open?id=1QqW6izTO_FHKmThCMp2h5uYpGy6mYZ7b | J51: Komprao Laguna, Fort tubarão, combo içara | L51: Sim | M51: 10.50 | N51: https://drive.google.com/open?id=1hA8a5eBR_el2CfQkp2V0hDyfRdOFs-z3 | O51: 10.00 | P51: https://drive.google.com/open?id=1pqJ0-Or0-2ofKQ1VgoLipizSuU2DltoX | Q51: 35.00 | S51: 192 | T51: Não tem nota da janta pois a loja se recusou a enviar a nota pelo motoboy | U51: =(Tabela1[[#This Row],[Informe o KM final do dia]]-Tabela1[[#This Row],[Informe o KM inicial do dia]])-Tabela1[[#This Row],[Caso tenha rodado particular alguma parte do trajeto, informe o total de KM a ser deduzido.]] -> 219 | V51: =IF(Tabela1[[#This Row],[Informe a data]]<DATE(2026,3,16), Tabela1[[#This Row],[KM Rodado]]*1.1, Tabela1[[#This Row],[KM Rodado]]*1.23) -> 240.9 | W51: =IFERROR(SUBSTITUTE(Tabela1[[#This Row],[Pedágio]],".",",",1)*1,0) -> 10.5 | X51: =IFERROR(SUBSTITUTE(Tabela1[[#This Row],[Estacionamento]],".",",",1)*1,0) -> 10 | Y51: =IFERROR(SUBSTITUTE(Tabela1[[#This Row],[Despesas Diversas (Jantar em viagem, Impressões, Etc)]],".",",",1)*1,0) -> 35 | Z51: =IFERROR(SUBSTITUTE(Tabela1[[#This Row],[Hospedagem]],".",",",1)*1,0) -> 192 | AA51: =IF(DAY(Tabela1[[#This Row],[Informe a data]])<=15,"1ª Quinzena","2ª Quinzena") -> 2ª Quinzena | AB51: =UPPER(TEXT(Tabela1[[#This Row],[Informe a data]],"mmmm")) -> JANEIRO | AC51: =_xlfn.CONCAT(Tabela1[[#This Row],[Selecione o Usuário]]," - ",TEXT(Tabela1[[#This Row],[Informe a data]],"dd-mm-aa")) -> #NAME?
A52: 46049.904 | B52: oliiveiiraa7@gmail.com | C52: GUSTAVO MATHEUS DE OLIVEIRA | D52: EUF3090 | E52: 46049 | F52: 160176 | G52: https://drive.google.com/open?id=1LNWafjbzmLYh8MCxmeKWSarTtl7QcM17 | H52: 160553 | I52: https://drive.google.com/open?id=1sogDqfbeSTJGAXIqBfLPKlyZPNCnLb3W | J52: Deslocamento buscar materiais, Brasil atacadista Rio do Sul, Brasil atacadista bairro progresso | L52: Não | U52: =(Tabela1[[#This Row],[Informe o KM final do dia]]-Tabela1[[#This Row],[Informe o KM inicial do dia]])-Tabela1[[#This Row],[Caso tenha rodado particular alguma parte do trajeto, informe o total de KM a ser deduzido.]] -> 377 | V52: =IF(Tabela1[[#This Row],[Informe a data]]<DATE(2026,3,16), Tabela1[[#This Row],[KM Rodado]]*1.1, Tabela1[[#This Row],[KM Rodado]]*1.23) -> 414.7 | W52: =IFERROR(SUBSTITUTE(Tabela1[[#This Row],[Pedágio]],".",",",1)*1,0) -> 0 | X52: =IFERROR(SUBSTITUTE(Tabela1[[#This Row],[Estacionamento]],".",",",1)*1,0) -> 0 | Y52: =IFERROR(SUBSTITUTE(Tabela1[[#This Row],[Despesas Diversas (Jantar em viagem, Impressões, Etc)]],".",",",1)*1,0) -> 0 | Z52: =IFERROR(SUBSTITUTE(Tabela1[[#This Row],[Hospedagem]],".",",",1)*1,0) -> 0 | AA52: =IF(DAY(Tabela1[[#This Row],[Informe a data]])<=15,"1ª Quinzena","2ª Quinzena") -> 2ª Quinzena | AB52: =UPPER(TEXT(Tabela1[[#This Row],[Informe a data]],"mmmm")) -> JANEIRO | AC52: =_xlfn.CONCAT(Tabela1[[#This Row],[Selecione o Usuário]]," - ",TEXT(Tabela1[[#This Row],[Informe a data]],"dd-mm-aa")) -> #NAME?
A53: 46050.747 | B53: matheus.moraes@mazzini.com | C53: MATHEUS DA SILVA MORAES | D53: LCX1B11 | E53: 46049 | F53: 118690 | G53: https://drive.google.com/open?id=1Y7mcRSCv8Fv9hJNRkZM79wteQAAuYNuK | H53: 118931 | I53: https://drive.google.com/open?id=10YwnzQ_7XZSGGrKS71fIjRxt-aO9aNdn | J53: Brasil Atacadista 19 Rio do Sul, Recolhimento do Celular Corporativo JACQUELINE BELLI FRANÇA, Komprao Blumenau Loja32 | L53: Não | U53: =(Tabela1[[#This Row],[Informe o KM final do dia]]-Tabela1[[#This Row],[Informe o KM inicial do dia]])-Tabela1[[#This Row],[Caso tenha rodado particular alguma parte do trajeto, informe o total de KM a ser deduzido.]] -> 241 | V53: =IF(Tabela1[[#This Row],[Informe a data]]<DATE(2026,3,16), Tabela1[[#This Row],[KM Rodado]]*1.1, Tabela1[[#This Row],[KM Rodado]]*1.23) -> 265.1 | W53: =IFERROR(SUBSTITUTE(Tabela1[[#This Row],[Pedágio]],".",",",1)*1,0) -> 0 | X53: =IFERROR(SUBSTITUTE(Tabela1[[#This Row],[Estacionamento]],".",",",1)*1,0) -> 0 | Y53: =IFERROR(SUBSTITUTE(Tabela1[[#This Row],[Despesas Diversas (Jantar em viagem, Impressões, Etc)]],".",",",1)*1,0) -> 0 | Z53: =IFERROR(SUBSTITUTE(Tabela1[[#This Row],[Hospedagem]],".",",",1)*1,0) -> 0 | AA53: =IF(DAY(Tabela1[[#This Row],[Informe a data]])<=15,"1ª Quinzena","2ª Quinzena") -> 2ª Quinzena | AB53: =UPPER(TEXT(Tabela1[[#This Row],[Informe a data]],"mmmm")) -> JANEIRO | AC53: =_xlfn.CONCAT(Tabela1[[#This Row],[Selecione o Usuário]]," - ",TEXT(Tabela1[[#This Row],[Informe a data]],"dd-mm-aa")) -> #NAME?
A54: 46051.561 | B54: sabrina.pires@mazzini.com.br | C54: SABRINA DOS SANTOS PIRES | D54: Azc9E32 | E54: 46049 | F54: 174037 | G54: https://drive.google.com/open?id=1j99scv_3Ye_zHldHAF6XB_U24YbYyLOV | H54: 174108 | I54: https://drive.google.com/open?id=1nEe8Nf1RHyeHTK5WMq8c9tQp9wVZz1_Q | J54: Atacadao Fort atacadista Koch Fort atacadista | L54: Não | U54: =(Tabela1[[#This Row],[Informe o KM final do dia]]-Tabela1[[#This Row],[Informe o KM inicial do dia]])-Tabela1[[#This Row],[Caso tenha rodado particular alguma parte do trajeto, informe o total de KM a ser deduzido.]] -> 71 | V54: =IF(Tabela1[[#This Row],[Informe a data]]<DATE(2026,3,16), Tabela1[[#This Row],[KM Rodado]]*1.1, Tabela1[[#This Row],[KM Rodado]]*1.23) -> 78.1 | W54: =IFERROR(SUBSTITUTE(Tabela1[[#This Row],[Pedágio]],".",",",1)*1,0) -> 0 | X54: =IFERROR(SUBSTITUTE(Tabela1[[#This Row],[Estacionamento]],".",",",1)*1,0) -> 0 | Y54: =IFERROR(SUBSTITUTE(Tabela1[[#This Row],[Despesas Diversas (Jantar em viagem, Impressões, Etc)]],".",",",1)*1,0) -> 0 | Z54: =IFERROR(SUBSTITUTE(Tabela1[[#This Row],[Hospedagem]],".",",",1)*1,0) -> 0 | AA54: =IF(DAY(Tabela1[[#This Row],[Informe a data]])<=15,"1ª Quinzena","2ª Quinzena") -> 2ª Quinzena | AB54: =UPPER(TEXT(Tabela1[[#This Row],[Informe a data]],"mmmm")) -> JANEIRO | AC54: =_xlfn.CONCAT(Tabela1[[#This Row],[Selecione o Usuário]]," - ",TEXT(Tabela1[[#This Row],[Informe a data]],"dd-mm-aa")) -> #NAME?
A55: 46050.828 | B55: camila.althoff@mazzini.com.br | C55: CAMILA CRISTINE ALTHOFF | D55: Mlz4j72 | E55: 46050 | F55: 186535 | G55: https://drive.google.com/open?id=1anr5Cq4aQOeES1Ull2zfbz6T7waT1vVP | H55: 186761 | I55: https://drive.google.com/open?id=1yqfxgzLG2FEnX6R3ILsI3i3w17sLki3U | J55: Atacadão içara, komprao Garopaba | L55: Sim | M55: 10.50 | N55: https://drive.google.com/open?id=1N500xKzKfXhnLnh2dCgGMt7H8pzloGDt | U55: =(Tabela1[[#This Row],[Informe o KM final do dia]]-Tabela1[[#This Row],[Informe o KM inicial do dia]])-Tabela1[[#This Row],[Caso tenha rodado particular alguma parte do trajeto, informe o total de KM a ser deduzido.]] -> 226 | V55: =IF(Tabela1[[#This Row],[Informe a data]]<DATE(2026,3,16), Tabela1[[#This Row],[KM Rodado]]*1.1, Tabela1[[#This Row],[KM Rodado]]*1.23) -> 248.6 | W55: =IFERROR(SUBSTITUTE(Tabela1[[#This Row],[Pedágio]],".",",",1)*1,0) -> 10.5 | X55: =IFERROR(SUBSTITUTE(Tabela1[[#This Row],[Estacionamento]],".",",",1)*1,0) -> 0 | Y55: =IFERROR(SUBSTITUTE(Tabela1[[#This Row],[Despesas Diversas (Jantar em viagem, Impressões, Etc)]],".",",",1)*1,0) -> 0 | Z55: =IFERROR(SUBSTITUTE(Tabela1[[#This Row],[Hospedagem]],".",",",1)*1,0) -> 0 | AA55: =IF(DAY(Tabela1[[#This Row],[Informe a data]])<=15,"1ª Quinzena","2ª Quinzena") -> 2ª Quinzena | AB55: =UPPER(TEXT(Tabela1[[#This Row],[Informe a data]],"mmmm")) -> JANEIRO | AC55: =_xlfn.CONCAT(Tabela1[[#This Row],[Selecione o Usuário]]," - ",TEXT(Tabela1[[#This Row],[Informe a data]],"dd-mm-aa")) -> #NAME?
A56: 46050.83 | B56: oliiveiira7@gmail.com | C56: GUSTAVO MATHEUS DE OLIVEIRA | D56: EUF3090 | E56: 46050 | F56: 160592 | G56: https://drive.google.com/open?id=1ZuHzdcnii6j9MFtNe3oBWp5Ho7m59Ty4 | H56: 160992 | I56: https://drive.google.com/open?id=1_xNUV4nKT06l-6q3OiEHgN11cPFC7-xn | J56: Super pão Porto União | L56: Não | U56: =(Tabela1[[#This Row],[Informe o KM final do dia]]-Tabela1[[#This Row],[Informe o KM inicial do dia]])-Tabela1[[#This Row],[Caso tenha rodado particular alguma parte do trajeto, informe o total de KM a ser deduzido.]] -> 400 | V56: =IF(Tabela1[[#This Row],[Informe a data]]<DATE(2026,3,16), Tabela1[[#This Row],[KM Rodado]]*1.1, Tabela1[[#This Row],[KM Rodado]]*1.23) -> 440 | W56: =IFERROR(SUBSTITUTE(Tabela1[[#This Row],[Pedágio]],".",",",1)*1,0) -> 0 | X56: =IFERROR(SUBSTITUTE(Tabela1[[#This Row],[Estacionamento]],".",",",1)*1,0) -> 0 | Y56: =IFERROR(SUBSTITUTE(Tabela1[[#This Row],[Despesas Diversas (Jantar em viagem, Impressões, Etc)]],".",",",1)*1,0) -> 0 | Z56: =IFERROR(SUBSTITUTE(Tabela1[[#This Row],[Hospedagem]],".",",",1)*1,0) -> 0 | AA56: =IF(DAY(Tabela1[[#This Row],[Informe a data]])<=15,"1ª Quinzena","2ª Quinzena") -> 2ª Quinzena | AB56: =UPPER(TEXT(Tabela1[[#This Row],[Informe a data]],"mmmm")) -> JANEIRO | AC56: =_xlfn.CONCAT(Tabela1[[#This Row],[Selecione o Usuário]]," - ",TEXT(Tabela1[[#This Row],[Informe a data]],"dd-mm-aa")) -> #NAME?
A57: 46052.835 | B57: lombardi2025@gmail.com | C57: RICARDO ALEXANDRE LOMBARDI | D57: OWA4C07 | E57: 46050 | F57: 168587 | G57: https://drive.google.com/open?id=19AdjbCkQ-rSFdvsbIPtiYvVJ4_LlL84l | H57: 168628 | I57: https://drive.google.com/open?id=1wGyU2QL1P2C702yHAg1Om3avtlM82Vds | J57: Brasília rua tupi,komprao 59 Brasília rua tupi,komprao 45.angeloni 23,Fort 905 | L57: Não | U57: =(Tabela1[[#This Row],[Informe o KM final do dia]]-Tabela1[[#This Row],[Informe o KM inicial do dia]])-Tabela1[[#This Row],[Caso tenha rodado particular alguma parte do trajeto, informe o total de KM a ser deduzido.]] -> 41 | V57: =IF(Tabela1[[#This Row],[Informe a data]]<DATE(2026,3,16), Tabela1[[#This Row],[KM Rodado]]*1.1, Tabela1[[#This Row],[KM Rodado]]*1.23) -> 45.1 | W57: =IFERROR(SUBSTITUTE(Tabela1[[#This Row],[Pedágio]],".",",",1)*1,0) -> 0 | X57: =IFERROR(SUBSTITUTE(Tabela1[[#This Row],[Estacionamento]],".",",",1)*1,0) -> 0 | Y57: =IFERROR(SUBSTITUTE(Tabela1[[#This Row],[Despesas Diversas (Jantar em viagem, Impressões, Etc)]],".",",",1)*1,0) -> 0 | Z57: =IFERROR(SUBSTITUTE(Tabela1[[#This Row],[Hospedagem]],".",",",1)*1,0) -> 0 | AA57: =IF(DAY(Tabela1[[#This Row],[Informe a data]])<=15,"1ª Quinzena","2ª Quinzena") -> 2ª Quinzena | AB57: =UPPER(TEXT(Tabela1[[#This Row],[Informe a data]],"mmmm")) -> JANEIRO | AC57: =_xlfn.CONCAT(Tabela1[[#This Row],[Selecione o Usuário]]," - ",TEXT(Tabela1[[#This Row],[Informe a data]],"dd-mm-aa")) -> #NAME?
A58: 46051.563 | B58: sabrina.pires@mazzini.com.br | C58: SABRINA DOS SANTOS PIRES | D58: Azc9E32 | E58: 46050 | F58: 237957 | G58: https://drive.google.com/open?id=1v1Tq8mDb9t2pVc2uCG5mncb_ulX0Gc9o | H58: 238004 | I58: https://drive.google.com/open?id=1wcE6e9gNH--jkryfCP0OOq0ToXUAX1dx | J58: Komprao Fort atacadista Brasil atacadista | L58: Não | U58: =(Tabela1[[#This Row],[Informe o KM final do dia]]-Tabela1[[#This Row],[Informe o KM inicial do dia]])-Tabela1[[#This Row],[Caso tenha rodado particular alguma parte do trajeto, informe o total de KM a ser deduzido.]] -> 47 | V58: =IF(Tabela1[[#This Row],[Informe a data]]<DATE(2026,3,16), Tabela1[[#This Row],[KM Rodado]]*1.1, Tabela1[[#This Row],[KM Rodado]]*1.23) -> 51.7 | W58: =IFERROR(SUBSTITUTE(Tabela1[[#This Row],[Pedágio]],".",",",1)*1,0) -> 0 | X58: =IFERROR(SUBSTITUTE(Tabela1[[#This Row],[Estacionamento]],".",",",1)*1,0) -> 0 | Y58: =IFERROR(SUBSTITUTE(Tabela1[[#This Row],[Despesas Diversas (Jantar em viagem, Impressões, Etc)]],".",",",1)*1,0) -> 0 | Z58: =IFERROR(SUBSTITUTE(Tabela1[[#This Row],[Hospedagem]],".",",",1)*1,0) -> 0 | AA58: =IF(DAY(Tabela1[[#This Row],[Informe a data]])<=15,"1ª Quinzena","2ª Quinzena") -> 2ª Quinzena | AB58: =UPPER(TEXT(Tabela1[[#This Row],[Informe a data]],"mmmm")) -> JANEIRO | AC58: =_xlfn.CONCAT(Tabela1[[#This Row],[Selecione o Usuário]]," - ",TEXT(Tabela1[[#This Row],[Informe a data]],"dd-mm-aa")) -> #NAME?
A59: 46051.852 | B59: camila.althoff@mazzini.com.br | C59: CAMILA CRISTINE ALTHOFF | D59: Mlz4j72 | E59: 46051 | F59: 186761 | G59: https://drive.google.com/open?id=1IC2I3MHVBnWmxz5eP63nUXhA83WBqMQ9 | H59: 186837 | I59: https://drive.google.com/open?id=13EXOW0wx_vWs3XWQ-_-Avendxip24kM8 | J59: Angeloni beira mar, Angeloni capoeiras, Zeus brasil,Bistek são José | L59: Sim | O59: 10.00 | P59: https://drive.google.com/open?id=1of3pBOPRnS6k45XZan68n1laFLi7nn0Q | U59: =(Tabela1[[#This Row],[Informe o KM final do dia]]-Tabela1[[#This Row],[Informe o KM inicial do dia]])-Tabela1[[#This Row],[Caso tenha rodado particular alguma parte do trajeto, informe o total de KM a ser deduzido.]] -> 76 | V59: =IF(Tabela1[[#This Row],[Informe a data]]<DATE(2026,3,16), Tabela1[[#This Row],[KM Rodado]]*1.1, Tabela1[[#This Row],[KM Rodado]]*1.23) -> 83.6 | W59: =IFERROR(SUBSTITUTE(Tabela1[[#This Row],[Pedágio]],".",",",1)*1,0) -> 0 | X59: =IFERROR(SUBSTITUTE(Tabela1[[#This Row],[Estacionamento]],".",",",1)*1,0) -> 10 | Y59: =IFERROR(SUBSTITUTE(Tabela1[[#This Row],[Despesas Diversas (Jantar em viagem, Impressões, Etc)]],".",",",1)*1,0) -> 0 | Z59: =IFERROR(SUBSTITUTE(Tabela1[[#This Row],[Hospedagem]],".",",",1)*1,0) -> 0 | AA59: =IF(DAY(Tabela1[[#This Row],[Informe a data]])<=15,"1ª Quinzena","2ª Quinzena") -> 2ª Quinzena | AB59: =UPPER(TEXT(Tabela1[[#This Row],[Informe a data]],"mmmm")) -> JANEIRO | AC59: =_xlfn.CONCAT(Tabela1[[#This Row],[Selecione o Usuário]]," - ",TEXT(Tabela1[[#This Row],[Informe a data]],"dd-mm-aa")) -> #NAME?
A60: 46052.617 | B60: matheus.moraes@mazzini.com.br | C60: MATHEUS DA SILVA MORAES | D60: LCX1B11 | E60: 46051 | F60: 119184 | G60: https://drive.google.com/open?id=1cIrucY7RzrRFmDiwW3tJmFnpMnv28z1l | H60: 119323 | I60: https://drive.google.com/open?id=1Y8zBj4oKcR22ivo3I6xlVnaxp_XtQ9Nh | J60: Gtop Escola Agricola 20, Otto Atacarejo 1470, Fort Indaial Lj 270 | K60: 9 | L60: Não | U60: =(Tabela1[[#This Row],[Informe o KM final do dia]]-Tabela1[[#This Row],[Informe o KM inicial do dia]])-Tabela1[[#This Row],[Caso tenha rodado particular alguma parte do trajeto, informe o total de KM a ser deduzido.]] -> 130 | V60: =IF(Tabela1[[#This Row],[Informe a data]]<DATE(2026,3,16), Tabela1[[#This Row],[KM Rodado]]*1.1, Tabela1[[#This Row],[KM Rodado]]*1.23) -> 143 | W60: =IFERROR(SUBSTITUTE(Tabela1[[#This Row],[Pedágio]],".",",",1)*1,0) -> 0 | X60: =IFERROR(SUBSTITUTE(Tabela1[[#This Row],[Estacionamento]],".",",",1)*1,0) -> 0 | Y60: =IFERROR(SUBSTITUTE(Tabela1[[#This Row],[Despesas Diversas (Jantar em viagem, Impressões, Etc)]],".",",",1)*1,0) -> 0 | Z60: =IFERROR(SUBSTITUTE(Tabela1[[#This Row],[Hospedagem]],".",",",1)*1,0) -> 0 | AA60: =IF(DAY(Tabela1[[#This Row],[Informe a data]])<=15,"1ª Quinzena","2ª Quinzena") -> 2ª Quinzena | AB60: =UPPER(TEXT(Tabela1[[#This Row],[Informe a data]],"mmmm")) -> JANEIRO | AC60: =_xlfn.CONCAT(Tabela1[[#This Row],[Selecione o Usuário]]," - ",TEXT(Tabela1[[#This Row],[Informe a data]],"dd-mm-aa")) -> #NAME?
A61: 46052.84 | B61: lombardi2025@gmail.com | C61: RICARDO ALEXANDRE LOMBARDI | D61: OWA4C07 | E61: 46051 | F61: 168628 | G61: https://drive.google.com/open?id=1irEs3O0ROkOlAY-UFewTdOiAnUxcxe1y | H61: 168973 | I61: https://drive.google.com/open?id=1V7TOKyC_yDCCiHqXd92FPuZlNF1onPD- | J61: Condor Mafra, komprao 65,condor rio negrinho,hiper sao bento ,super pão 41, super pão 42, | L61: Não | U61: =(Tabela1[[#This Row],[Informe o KM final do dia]]-Tabela1[[#This Row],[Informe o KM inicial do dia]])-Tabela1[[#This Row],[Caso tenha rodado particular alguma parte do trajeto, informe o total de KM a ser deduzido.]] -> 345 | V61: =IF(Tabela1[[#This Row],[Informe a data]]<DATE(2026,3,16), Tabela1[[#This Row],[KM Rodado]]*1.1, Tabela1[[#This Row],[KM Rodado]]*1.23) -> 379.5 | W61: =IFERROR(SUBSTITUTE(Tabela1[[#This Row],[Pedágio]],".",",",1)*1,0) -> 0 | X61: =IFERROR(SUBSTITUTE(Tabela1[[#This Row],[Estacionamento]],".",",",1)*1,0) -> 0 | Y61: =IFERROR(SUBSTITUTE(Tabela1[[#This Row],[Despesas Diversas (Jantar em viagem, Impressões, Etc)]],".",",",1)*1,0) -> 0 | Z61: =IFERROR(SUBSTITUTE(Tabela1[[#This Row],[Hospedagem]],".",",",1)*1,0) -> 0 | AA61: =IF(DAY(Tabela1[[#This Row],[Informe a data]])<=15,"1ª Quinzena","2ª Quinzena") -> 2ª Quinzena | AB61: =UPPER(TEXT(Tabela1[[#This Row],[Informe a data]],"mmmm")) -> JANEIRO | AC61: =_xlfn.CONCAT(Tabela1[[#This Row],[Selecione o Usuário]]," - ",TEXT(Tabela1[[#This Row],[Informe a data]],"dd-mm-aa")) -> #NAME?
A62: 46052.771 | B62: oliiveiira7@gmail.com | C62: GUSTAVO MATHEUS DE OLIVEIRA | D62: EUF3090 | E62: 46052 | F62: 161112 | G62: https://drive.google.com/open?id=1D6JgJSX2Kb4TugMA58U_kjlc2z6AEe5v | H62: 161321 | I62: https://drive.google.com/open?id=1pICA8jbru7QoLmScU6UHVOfIQsFAurrU | J62: Fort 960 Lages, Stok center Lages, Angeloni Lages, Fort 260 Lages | L62: Não | U62: =(Tabela1[[#This Row],[Informe o KM final do dia]]-Tabela1[[#This Row],[Informe o KM inicial do dia]])-Tabela1[[#This Row],[Caso tenha rodado particular alguma parte do trajeto, informe o total de KM a ser deduzido.]] -> 209 | V62: =IF(Tabela1[[#This Row],[Informe a data]]<DATE(2026,3,16), Tabela1[[#This Row],[KM Rodado]]*1.1, Tabela1[[#This Row],[KM Rodado]]*1.23) -> 229.9 | W62: =IFERROR(SUBSTITUTE(Tabela1[[#This Row],[Pedágio]],".",",",1)*1,0) -> 0 | X62: =IFERROR(SUBSTITUTE(Tabela1[[#This Row],[Estacionamento]],".",",",1)*1,0) -> 0 | Y62: =IFERROR(SUBSTITUTE(Tabela1[[#This Row],[Despesas Diversas (Jantar em viagem, Impressões, Etc)]],".",",",1)*1,0) -> 0 | Z62: =IFERROR(SUBSTITUTE(Tabela1[[#This Row],[Hospedagem]],".",",",1)*1,0) -> 0 | AA62: =IF(DAY(Tabela1[[#This Row],[Informe a data]])<=15,"1ª Quinzena","2ª Quinzena") -> 2ª Quinzena | AB62: =UPPER(TEXT(Tabela1[[#This Row],[Informe a data]],"mmmm")) -> JANEIRO | AC62: =_xlfn.CONCAT(Tabela1[[#This Row],[Selecione o Usuário]]," - ",TEXT(Tabela1[[#This Row],[Informe a data]],"dd-mm-aa")) -> #NAME?
A63: 46052.842 | B63: lombardi2025@gmail.com | C63: RICARDO ALEXANDRE LOMBARDI | D63: OWA4C07 | E63: 46052 | F63: 168973 | G63: https://drive.google.com/open?id=1jTwIxbS47fOGypC2lE2NI0p0GjgiszEu | H63: 169011 | I63: https://drive.google.com/open?id=1TojWAuI7BcJUVIqCbwYweP7mEQ_BZe-h | J63: Komprao 59, komprao 77,condor 51 | L63: Não | U63: =(Tabela1[[#This Row],[Informe o KM final do dia]]-Tabela1[[#This Row],[Informe o KM inicial do dia]])-Tabela1[[#This Row],[Caso tenha rodado particular alguma parte do trajeto, informe o total de KM a ser deduzido.]] -> 38 | V63: =IF(Tabela1[[#This Row],[Informe a data]]<DATE(2026,3,16), Tabela1[[#This Row],[KM Rodado]]*1.1, Tabela1[[#This Row],[KM Rodado]]*1.23) -> 41.8 | W63: =IFERROR(SUBSTITUTE(Tabela1[[#This Row],[Pedágio]],".",",",1)*1,0) -> 0 | X63: =IFERROR(SUBSTITUTE(Tabela1[[#This Row],[Estacionamento]],".",",",1)*1,0) -> 0 | Y63: =IFERROR(SUBSTITUTE(Tabela1[[#This Row],[Despesas Diversas (Jantar em viagem, Impressões, Etc)]],".",",",1)*1,0) -> 0 | Z63: =IFERROR(SUBSTITUTE(Tabela1[[#This Row],[Hospedagem]],".",",",1)*1,0) -> 0 | AA63: =IF(DAY(Tabela1[[#This Row],[Informe a data]])<=15,"1ª Quinzena","2ª Quinzena") -> 2ª Quinzena | AB63: =UPPER(TEXT(Tabela1[[#This Row],[Informe a data]],"mmmm")) -> JANEIRO | AC63: =_xlfn.CONCAT(Tabela1[[#This Row],[Selecione o Usuário]]," - ",TEXT(Tabela1[[#This Row],[Informe a data]],"dd-mm-aa")) -> #NAME?
A64: 46053.416 | B64: sabrina.pires@mazzini.com.br | C64: SABRINA DOS SANTOS PIRES | D64: Azc9e32 | E64: 46052 | F64: 238029 | G64: https://drive.google.com/open?id=19jrewGD2E7G4D3Xoj810-Y-CBUJkq1UJ | H64: 238246 | I64: https://drive.google.com/open?id=1ph1eQuq2DZ4ALo6AxIcEjbOkYWl8za-r | J64: Fort 130 Fort 462 Brasil atacadista Fort 306 Fort 365 Komprao Komprao pedra branca | L64: Não | U64: =(Tabela1[[#This Row],[Informe o KM final do dia]]-Tabela1[[#This Row],[Informe o KM inicial do dia]])-Tabela1[[#This Row],[Caso tenha rodado particular alguma parte do trajeto, informe o total de KM a ser deduzido.]] -> 217 | V64: =IF(Tabela1[[#This Row],[Informe a data]]<DATE(2026,3,16), Tabela1[[#This Row],[KM Rodado]]*1.1, Tabela1[[#This Row],[KM Rodado]]*1.23) -> 238.7 | W64: =IFERROR(SUBSTITUTE(Tabela1[[#This Row],[Pedágio]],".",",",1)*1,0) -> 0 | X64: =IFERROR(SUBSTITUTE(Tabela1[[#This Row],[Estacionamento]],".",",",1)*1,0) -> 0 | Y64: =IFERROR(SUBSTITUTE(Tabela1[[#This Row],[Despesas Diversas (Jantar em viagem, Impressões, Etc)]],".",",",1)*1,0) -> 0 | Z64: =IFERROR(SUBSTITUTE(Tabela1[[#This Row],[Hospedagem]],".",",",1)*1,0) -> 0 | AA64: =IF(DAY(Tabela1[[#This Row],[Informe a data]])<=15,"1ª Quinzena","2ª Quinzena") -> 2ª Quinzena | AB64: =UPPER(TEXT(Tabela1[[#This Row],[Informe a data]],"mmmm")) -> JANEIRO | AC64: =_xlfn.CONCAT(Tabela1[[#This Row],[Selecione o Usuário]]," - ",TEXT(Tabela1[[#This Row],[Informe a data]],"dd-mm-aa")) -> #NAME?
A65: 46053.41 | B65: camila.althoff@mazzini.com.br | C65: CAMILA CRISTINE ALTHOFF | D65: Mlz4j72 | E65: 46053 | F65: 186837 | G65: https://drive.google.com/open?id=1_GQvHi7DGvvIRbC-BqWJFyok5A_Eac_N | H65: 186895 | I65: https://drive.google.com/open?id=1mTr2Frwrz2coX9vKItf7fc2KtQT5j6rZ | J65: Angeloni beira mar, atacadão via expressa, Carrefour | L65: Não | U65: =(Tabela1[[#This Row],[Informe o KM final do dia]]-Tabela1[[#This Row],[Informe o KM inicial do dia]])-Tabela1[[#This Row],[Caso tenha rodado particular alguma parte do trajeto, informe o total de KM a ser deduzido.]] -> 58 | V65: =IF(Tabela1[[#This Row],[Informe a data]]<DATE(2026,3,16), Tabela1[[#This Row],[KM Rodado]]*1.1, Tabela1[[#This Row],[KM Rodado]]*1.23) -> 63.8 | W65: =IFERROR(SUBSTITUTE(Tabela1[[#This Row],[Pedágio]],".",",",1)*1,0) -> 0 | X65: =IFERROR(SUBSTITUTE(Tabela1[[#This Row],[Estacionamento]],".",",",1)*1,0) -> 0 | Y65: =IFERROR(SUBSTITUTE(Tabela1[[#This Row],[Despesas Diversas (Jantar em viagem, Impressões, Etc)]],".",",",1)*1,0) -> 0 | Z65: =IFERROR(SUBSTITUTE(Tabela1[[#This Row],[Hospedagem]],".",",",1)*1,0) -> 0 | AA65: =IF(DAY(Tabela1[[#This Row],[Informe a data]])<=15,"1ª Quinzena","2ª Quinzena") -> 2ª Quinzena | AB65: =UPPER(TEXT(Tabela1[[#This Row],[Informe a data]],"mmmm")) -> JANEIRO | AC65: =_xlfn.CONCAT(Tabela1[[#This Row],[Selecione o Usuário]]," - ",TEXT(Tabela1[[#This Row],[Informe a data]],"dd-mm-aa")) -> #NAME?
A66: 46053.826 | B66: matheus.moraes@mazzini.com.br | C66: MATHEUS DA SILVA MORAES | D66: LCX1B11 | E66: 46053 | F66: 119338 | G66: https://drive.google.com/open?id=1I80W8esWwOAC29l9n-P9W3Arx9XzBLvz | H66: 119420 | I66: https://drive.google.com/open?id=1Ca3PZvDdJnfzIcceqqvZOOBXHtPZwuFA | J66: Koch Lj 89 Blumenau, Supermercados Mocam Indaial, Komprao Timbó Lj34 | L66: Não | U66: =(Tabela1[[#This Row],[Informe o KM final do dia]]-Tabela1[[#This Row],[Informe o KM inicial do dia]])-Tabela1[[#This Row],[Caso tenha rodado particular alguma parte do trajeto, informe o total de KM a ser deduzido.]] -> 82 | V66: =IF(Tabela1[[#This Row],[Informe a data]]<DATE(2026,3,16), Tabela1[[#This Row],[KM Rodado]]*1.1, Tabela1[[#This Row],[KM Rodado]]*1.23) -> 90.2 | W66: =IFERROR(SUBSTITUTE(Tabela1[[#This Row],[Pedágio]],".",",",1)*1,0) -> 0 | X66: =IFERROR(SUBSTITUTE(Tabela1[[#This Row],[Estacionamento]],".",",",1)*1,0) -> 0 | Y66: =IFERROR(SUBSTITUTE(Tabela1[[#This Row],[Despesas Diversas (Jantar em viagem, Impressões, Etc)]],".",",",1)*1,0) -> 0 | Z66: =IFERROR(SUBSTITUTE(Tabela1[[#This Row],[Hospedagem]],".",",",1)*1,0) -> 0 | AA66: =IF(DAY(Tabela1[[#This Row],[Informe a data]])<=15,"1ª Quinzena","2ª Quinzena") -> 2ª Quinzena | AB66: =UPPER(TEXT(Tabela1[[#This Row],[Informe a data]],"mmmm")) -> JANEIRO | AC66: =_xlfn.CONCAT(Tabela1[[#This Row],[Selecione o Usuário]]," - ",TEXT(Tabela1[[#This Row],[Informe a data]],"dd-mm-aa")) -> #NAME?
A67: 46056.409 | B67: matheus.moraes@mazzini.com.br | C67: MATHEUS DA SILVA MORAES | D67: QIL7H04 | E67: 46055 | F67: 119499 | G67: https://drive.google.com/open?id=1ZqjQrleQUS6Sn1OciJ53hhtyv375IHyf | H67: 119665 | I67: https://drive.google.com/open?id=1wBpp45W-5EXCo1uAT4ENJgNdsy8iFZVv | J67: Archer matriz Brusque e Bistek park europeu | L67: Sim | Q67: 13.80 | R67: https://drive.google.com/open?id=1RgPY6LsOUHKnWxjr8bGGR1iKx7YEnQfX | T67: Impressões dos documentos do Archer | U67: =(Tabela1[[#This Row],[Informe o KM final do dia]]-Tabela1[[#This Row],[Informe o KM inicial do dia]])-Tabela1[[#This Row],[Caso tenha rodado particular alguma parte do trajeto, informe o total de KM a ser deduzido.]] -> 166 | V67: =IF(Tabela1[[#This Row],[Informe a data]]<DATE(2026,3,16), Tabela1[[#This Row],[KM Rodado]]*1.1, Tabela1[[#This Row],[KM Rodado]]*1.23) -> 182.6 | W67: =IFERROR(SUBSTITUTE(Tabela1[[#This Row],[Pedágio]],".",",",1)*1,0) -> 0 | X67: =IFERROR(SUBSTITUTE(Tabela1[[#This Row],[Estacionamento]],".",",",1)*1,0) -> 0 | Y67: =IFERROR(SUBSTITUTE(Tabela1[[#This Row],[Despesas Diversas (Jantar em viagem, Impressões, Etc)]],".",",",1)*1,0) -> 13.8 | Z67: =IFERROR(SUBSTITUTE(Tabela1[[#This Row],[Hospedagem]],".",",",1)*1,0) -> 0 | AA67: =IF(DAY(Tabela1[[#This Row],[Informe a data]])<=15,"1ª Quinzena","2ª Quinzena") -> 1ª Quinzena | AB67: =UPPER(TEXT(Tabela1[[#This Row],[Informe a data]],"mmmm")) -> FEVEREIRO | AC67: =_xlfn.CONCAT(Tabela1[[#This Row],[Selecione o Usuário]]," - ",TEXT(Tabela1[[#This Row],[Informe a data]],"dd-mm-aa")) -> #NAME?
A68: 46071.354 | B68: lombardi2025@gmail.com | C68: RICARDO ALEXANDRE LOMBARDI | D68: OWA4C07 | E68: 46055 | F68: 169047 | H68: 169070 | J68: Hiper Itinga ,samns club | L68: Não | U68: =(Tabela1[[#This Row],[Informe o KM final do dia]]-Tabela1[[#This Row],[Informe o KM inicial do dia]])-Tabela1[[#This Row],[Caso tenha rodado particular alguma parte do trajeto, informe o total de KM a ser deduzido.]] -> 23 | V68: =IF(Tabela1[[#This Row],[Informe a data]]<DATE(2026,3,16), Tabela1[[#This Row],[KM Rodado]]*1.1, Tabela1[[#This Row],[KM Rodado]]*1.23) -> 25.3 | W68: =IFERROR(SUBSTITUTE(Tabela1[[#This Row],[Pedágio]],".",",",1)*1,0) -> 0 | X68: =IFERROR(SUBSTITUTE(Tabela1[[#This Row],[Estacionamento]],".",",",1)*1,0) -> 0 | Y68: =IFERROR(SUBSTITUTE(Tabela1[[#This Row],[Despesas Diversas (Jantar em viagem, Impressões, Etc)]],".",",",1)*1,0) -> 0 | Z68: =IFERROR(SUBSTITUTE(Tabela1[[#This Row],[Hospedagem]],".",",",1)*1,0) -> 0 | AA68: =IF(DAY(Tabela1[[#This Row],[Informe a data]])<=15,"1ª Quinzena","2ª Quinzena") -> 1ª Quinzena | AB68: =UPPER(TEXT(Tabela1[[#This Row],[Informe a data]],"mmmm")) -> FEVEREIRO | AC68: =_xlfn.CONCAT(Tabela1[[#This Row],[Selecione o Usuário]]," - ",TEXT(Tabela1[[#This Row],[Informe a data]],"dd-mm-aa")) -> #NAME?
A69: 46056.774 | B69: camila.althoff@mazzini.com.br | C69: CAMILA CRISTINE ALTHOFF | D69: Mlz4j72 | E69: 46056 | F69: 186907 | G69: https://drive.google.com/open?id=1wWtbY0LNAak171WH3UdILHZ0YB8UdrOg | H69: 187112 | I69: https://drive.google.com/open?id=1wqYUSFnUT-TLos4LwY1y68XdXl5nviPe | J69: Brasil Atacadista porto belo, kock 04, Komprao Itapema | L69: Sim | M69: 11.40 | N69: https://drive.google.com/open?id=1tQYLoEa8YFoCzA6lJ5a3D4Q2l03HkKue | Q69: 106.76 | R69: https://drive.google.com/open?id=1efhBH9WAAC4fqSjPMKqfoJzcJ8yjaqGc | U69: =(Tabela1[[#This Row],[Informe o KM final do dia]]-Tabela1[[#This Row],[Informe o KM inicial do dia]])-Tabela1[[#This Row],[Caso tenha rodado particular alguma parte do trajeto, informe o total de KM a ser deduzido.]] -> 205 | V69: =IF(Tabela1[[#This Row],[Informe a data]]<DATE(2026,3,16), Tabela1[[#This Row],[KM Rodado]]*1.1, Tabela1[[#This Row],[KM Rodado]]*1.23) -> 225.5 | W69: =IFERROR(SUBSTITUTE(Tabela1[[#This Row],[Pedágio]],".",",",1)*1,0) -> 11.4 | X69: =IFERROR(SUBSTITUTE(Tabela1[[#This Row],[Estacionamento]],".",",",1)*1,0) -> 0 | Y69: =IFERROR(SUBSTITUTE(Tabela1[[#This Row],[Despesas Diversas (Jantar em viagem, Impressões, Etc)]],".",",",1)*1,0) -> 106.76 | Z69: =IFERROR(SUBSTITUTE(Tabela1[[#This Row],[Hospedagem]],".",",",1)*1,0) -> 0 | AA69: =IF(DAY(Tabela1[[#This Row],[Informe a data]])<=15,"1ª Quinzena","2ª Quinzena") -> 1ª Quinzena | AB69: =UPPER(TEXT(Tabela1[[#This Row],[Informe a data]],"mmmm")) -> FEVEREIRO | AC69: =_xlfn.CONCAT(Tabela1[[#This Row],[Selecione o Usuário]]," - ",TEXT(Tabela1[[#This Row],[Informe a data]],"dd-mm-aa")) -> #NAME?
A70: 46056.756 | B70: matheus.moraes@mazzini.com.br | C70: MATHEUS DA SILVA MORAES | D70: QIL7H04 | E70: 46056 | F70: 119764 | G70: https://drive.google.com/open?id=1hSYRhvDmkYDpL-C3N8CpANJme0eFKxMl | H70: 119931 | I70: https://drive.google.com/open?id=14ZvXM6bvFf-33Qr5V79LvAyFlZ9gwiWg | J70: COOPER IBIRAMA E REDE TOP IBIRAMA | L70: Não | U70: =(Tabela1[[#This Row],[Informe o KM final do dia]]-Tabela1[[#This Row],[Informe o KM inicial do dia]])-Tabela1[[#This Row],[Caso tenha rodado particular alguma parte do trajeto, informe o total de KM a ser deduzido.]] -> 167 | V70: =IF(Tabela1[[#This Row],[Informe a data]]<DATE(2026,3,16), Tabela1[[#This Row],[KM Rodado]]*1.1, Tabela1[[#This Row],[KM Rodado]]*1.23) -> 183.7 | W70: =IFERROR(SUBSTITUTE(Tabela1[[#This Row],[Pedágio]],".",",",1)*1,0) -> 0 | X70: =IFERROR(SUBSTITUTE(Tabela1[[#This Row],[Estacionamento]],".",",",1)*1,0) -> 0 | Y70: =IFERROR(SUBSTITUTE(Tabela1[[#This Row],[Despesas Diversas (Jantar em viagem, Impressões, Etc)]],".",",",1)*1,0) -> 0 | Z70: =IFERROR(SUBSTITUTE(Tabela1[[#This Row],[Hospedagem]],".",",",1)*1,0) -> 0 | AA70: =IF(DAY(Tabela1[[#This Row],[Informe a data]])<=15,"1ª Quinzena","2ª Quinzena") -> 1ª Quinzena | AB70: =UPPER(TEXT(Tabela1[[#This Row],[Informe a data]],"mmmm")) -> FEVEREIRO | AC70: =_xlfn.CONCAT(Tabela1[[#This Row],[Selecione o Usuário]]," - ",TEXT(Tabela1[[#This Row],[Informe a data]],"dd-mm-aa")) -> #NAME?
A71: 46057.722 | B71: sabrina.pires@mazzini.com.br | C71: SABRINA DOS SANTOS PIRES | D71: Azc9e32 | E71: 46056 | F71: 238029 | G71: https://drive.google.com/open?id=1fsSVTccl9bSmr4SzBDCexqS8vRgRHi1e | H71: 238353 | I71: https://drive.google.com/open?id=1m9rwpwDcYex90I5yT6ngrrcSfRou0WUG | J71: Brasil atacadista Fort atacadista Fort 130 Komprao Komprao | L71: Não | U71: =(Tabela1[[#This Row],[Informe o KM final do dia]]-Tabela1[[#This Row],[Informe o KM inicial do dia]])-Tabela1[[#This Row],[Caso tenha rodado particular alguma parte do trajeto, informe o total de KM a ser deduzido.]] -> 324 | V71: =IF(Tabela1[[#This Row],[Informe a data]]<DATE(2026,3,16), Tabela1[[#This Row],[KM Rodado]]*1.1, Tabela1[[#This Row],[KM Rodado]]*1.23) -> 356.4 | W71: =IFERROR(SUBSTITUTE(Tabela1[[#This Row],[Pedágio]],".",",",1)*1,0) -> 0 | X71: =IFERROR(SUBSTITUTE(Tabela1[[#This Row],[Estacionamento]],".",",",1)*1,0) -> 0 | Y71: =IFERROR(SUBSTITUTE(Tabela1[[#This Row],[Despesas Diversas (Jantar em viagem, Impressões, Etc)]],".",",",1)*1,0) -> 0 | Z71: =IFERROR(SUBSTITUTE(Tabela1[[#This Row],[Hospedagem]],".",",",1)*1,0) -> 0 | AA71: =IF(DAY(Tabela1[[#This Row],[Informe a data]])<=15,"1ª Quinzena","2ª Quinzena") -> 1ª Quinzena | AB71: =UPPER(TEXT(Tabela1[[#This Row],[Informe a data]],"mmmm")) -> FEVEREIRO | AC71: =_xlfn.CONCAT(Tabela1[[#This Row],[Selecione o Usuário]]," - ",TEXT(Tabela1[[#This Row],[Informe a data]],"dd-mm-aa")) -> #NAME?
A72: 46058.311 | B72: camila.althoff@mazzini.com.br | C72: CAMILA CRISTINE ALTHOFF | D72: Mlz4j72 | E72: 46057 | F72: 187112 | G72: https://drive.google.com/open?id=1pjOKOuzKgL3QpAYB_sla0T29P3jqK4I_ | H72: 187171 | I72: https://drive.google.com/open?id=1NRGOMY9Ax415RJI0gGPGJolu5SiZyil- | J72: Angeloni beira mar, Zeus ,Carrefour , brasil rio Tavares | L72: Sim | O72: 20.00 | P72: https://drive.google.com/open?id=1Dg8cSzPgDQgSBLDMUXjV9_u8lRSUqPJ6 | U72: =(Tabela1[[#This Row],[Informe o KM final do dia]]-Tabela1[[#This Row],[Informe o KM inicial do dia]])-Tabela1[[#This Row],[Caso tenha rodado particular alguma parte do trajeto, informe o total de KM a ser deduzido.]] -> 59 | V72: =IF(Tabela1[[#This Row],[Informe a data]]<DATE(2026,3,16), Tabela1[[#This Row],[KM Rodado]]*1.1, Tabela1[[#This Row],[KM Rodado]]*1.23) -> 64.9 | W72: =IFERROR(SUBSTITUTE(Tabela1[[#This Row],[Pedágio]],".",",",1)*1,0) -> 0 | X72: =IFERROR(SUBSTITUTE(Tabela1[[#This Row],[Estacionamento]],".",",",1)*1,0) -> 20 | Y72: =IFERROR(SUBSTITUTE(Tabela1[[#This Row],[Despesas Diversas (Jantar em viagem, Impressões, Etc)]],".",",",1)*1,0) -> 0 | Z72: =IFERROR(SUBSTITUTE(Tabela1[[#This Row],[Hospedagem]],".",",",1)*1,0) -> 0 | AA72: =IF(DAY(Tabela1[[#This Row],[Informe a data]])<=15,"1ª Quinzena","2ª Quinzena") -> 1ª Quinzena | AB72: =UPPER(TEXT(Tabela1[[#This Row],[Informe a data]],"mmmm")) -> FEVEREIRO | AC72: =_xlfn.CONCAT(Tabela1[[#This Row],[Selecione o Usuário]]," - ",TEXT(Tabela1[[#This Row],[Informe a data]],"dd-mm-aa")) -> #NAME?
A73: 46058.382 | B73: matheus.moraes@mazzini.com.br | C73: MATHEUS DA SILVA MORAES | D73: QIL7H04 | E73: 46057 | F73: 119931 | G73: https://drive.google.com/open?id=1JcaIkjWdFwb59Pf6WNbHpWs6XOpQmnc3 | H73: 120017 | I73: https://drive.google.com/open?id=1DYdKVIX7_acQ5DlbFotuKG2hTlft2-GG | J73: BISTEK GARCIA, COOPER ITOUPAVA NORTE E BISTEK PARK EUROPEU | L73: Não | U73: =(Tabela1[[#This Row],[Informe o KM final do dia]]-Tabela1[[#This Row],[Informe o KM inicial do dia]])-Tabela1[[#This Row],[Caso tenha rodado particular alguma parte do trajeto, informe o total de KM a ser deduzido.]] -> 86 | V73: =IF(Tabela1[[#This Row],[Informe a data]]<DATE(2026,3,16), Tabela1[[#This Row],[KM Rodado]]*1.1, Tabela1[[#This Row],[KM Rodado]]*1.23) -> 94.6 | W73: =IFERROR(SUBSTITUTE(Tabela1[[#This Row],[Pedágio]],".",",",1)*1,0) -> 0 | X73: =IFERROR(SUBSTITUTE(Tabela1[[#This Row],[Estacionamento]],".",",",1)*1,0) -> 0 | Y73: =IFERROR(SUBSTITUTE(Tabela1[[#This Row],[Despesas Diversas (Jantar em viagem, Impressões, Etc)]],".",",",1)*1,0) -> 0 | Z73: =IFERROR(SUBSTITUTE(Tabela1[[#This Row],[Hospedagem]],".",",",1)*1,0) -> 0 | AA73: =IF(DAY(Tabela1[[#This Row],[Informe a data]])<=15,"1ª Quinzena","2ª Quinzena") -> 1ª Quinzena | AB73: =UPPER(TEXT(Tabela1[[#This Row],[Informe a data]],"mmmm")) -> FEVEREIRO | AC73: =_xlfn.CONCAT(Tabela1[[#This Row],[Selecione o Usuário]]," - ",TEXT(Tabela1[[#This Row],[Informe a data]],"dd-mm-aa")) -> #NAME?
A74: 46058.864 | B74: sabrina.pires@mazzini.com.br | C74: SABRINA DOS SANTOS PIRES | D74: Azc9e32 | E74: 46057 | F74: 56431 | G74: https://drive.google.com/open?id=12AIoq0BFVilhzwUbc0V5nM7YlL6JBhNP | H74: 56555 | I74: https://drive.google.com/open?id=1BRfafYKZvSfTZX2_LUSuFBvMavUR99d- | J74: Komprao53 Komprao 01 Komprao 02 Komprao 20 Komprao 24 Tijucas | L74: Não | U74: =(Tabela1[[#This Row],[Informe o KM final do dia]]-Tabela1[[#This Row],[Informe o KM inicial do dia]])-Tabela1[[#This Row],[Caso tenha rodado particular alguma parte do trajeto, informe o total de KM a ser deduzido.]] -> 124 | V74: =IF(Tabela1[[#This Row],[Informe a data]]<DATE(2026,3,16), Tabela1[[#This Row],[KM Rodado]]*1.1, Tabela1[[#This Row],[KM Rodado]]*1.23) -> 136.4 | W74: =IFERROR(SUBSTITUTE(Tabela1[[#This Row],[Pedágio]],".",",",1)*1,0) -> 0 | X74: =IFERROR(SUBSTITUTE(Tabela1[[#This Row],[Estacionamento]],".",",",1)*1,0) -> 0 | Y74: =IFERROR(SUBSTITUTE(Tabela1[[#This Row],[Despesas Diversas (Jantar em viagem, Impressões, Etc)]],".",",",1)*1,0) -> 0 | Z74: =IFERROR(SUBSTITUTE(Tabela1[[#This Row],[Hospedagem]],".",",",1)*1,0) -> 0 | AA74: =IF(DAY(Tabela1[[#This Row],[Informe a data]])<=15,"1ª Quinzena","2ª Quinzena") -> 1ª Quinzena | AB74: =UPPER(TEXT(Tabela1[[#This Row],[Informe a data]],"mmmm")) -> FEVEREIRO | AC74: =_xlfn.CONCAT(Tabela1[[#This Row],[Selecione o Usuário]]," - ",TEXT(Tabela1[[#This Row],[Informe a data]],"dd-mm-aa")) -> #NAME?
A75: 46058.899 | B75: camila.althoff@mazzini.com.br | C75: CAMILA CRISTINE ALTHOFF | D75: Mlz4j72 | E75: 46058 | F75: 187171 | G75: https://drive.google.com/open?id=1muhhx2tI6O-dsWo4FP6ZKVzpHu_VbI-t | H75: 187393 | I75: https://drive.google.com/open?id=1oOCjPuYSRT8JE5vD6x3anGf6QMVoD-YB | J75: Angeloni beira mar, Bistek Itajaí, hotel Joinville | L75: Sim | M75: 11.40 | Q75: 57.90 | R75: https://drive.google.com/open?id=1I4B6mE9VpvAIn1Q-XeZWOaEjjW0GOKP- | U75: =(Tabela1[[#This Row],[Informe o KM final do dia]]-Tabela1[[#This Row],[Informe o KM inicial do dia]])-Tabela1[[#This Row],[Caso tenha rodado particular alguma parte do trajeto, informe o total de KM a ser deduzido.]] -> 222 | V75: =IF(Tabela1[[#This Row],[Informe a data]]<DATE(2026,3,16), Tabela1[[#This Row],[KM Rodado]]*1.1, Tabela1[[#This Row],[KM Rodado]]*1.23) -> 244.2 | W75: =IFERROR(SUBSTITUTE(Tabela1[[#This Row],[Pedágio]],".",",",1)*1,0) -> 11.4 | X75: =IFERROR(SUBSTITUTE(Tabela1[[#This Row],[Estacionamento]],".",",",1)*1,0) -> 0 | Y75: =IFERROR(SUBSTITUTE(Tabela1[[#This Row],[Despesas Diversas (Jantar em viagem, Impressões, Etc)]],".",",",1)*1,0) -> 57.9 | Z75: =IFERROR(SUBSTITUTE(Tabela1[[#This Row],[Hospedagem]],".",",",1)*1,0) -> 0 | AA75: =IF(DAY(Tabela1[[#This Row],[Informe a data]])<=15,"1ª Quinzena","2ª Quinzena") -> 1ª Quinzena | AB75: =UPPER(TEXT(Tabela1[[#This Row],[Informe a data]],"mmmm")) -> FEVEREIRO | AC75: =_xlfn.CONCAT(Tabela1[[#This Row],[Selecione o Usuário]]," - ",TEXT(Tabela1[[#This Row],[Informe a data]],"dd-mm-aa")) -> #NAME?
A76: 46065.766 | B76: martinsneto047@gmail.com | C76: JOÃO MARTINS NETO | D76: IUT1C03 | E76: 46058 | F76: 99405 | G76: https://drive.google.com/open?id=1JubQoPftcyavN702RamPqEFVHBL_eGax | H76: 99495 | I76: https://drive.google.com/open?id=1o79MAgYGHtyUrEVorBEnYoHP5IbNa7u6 | J76: BISTEK ITAJAI FAZER MINHA INTREGRAÇÃO COM A COORDENADORA SAIDDA, SAINDO DE LA PASSEI NA REGIAO DE ITAPEMA DO CENTRO MORRRETES E MEIA PRAIA PARA CONHECER AS LOJA E PEGAR CONTATOS DE CHEFE DE LOJA | L76: Não | U76: =(Tabela1[[#This Row],[Informe o KM final do dia]]-Tabela1[[#This Row],[Informe o KM inicial do dia]])-Tabela1[[#This Row],[Caso tenha rodado particular alguma parte do trajeto, informe o total de KM a ser deduzido.]] -> 90 | V76: =IF(Tabela1[[#This Row],[Informe a data]]<DATE(2026,3,16), Tabela1[[#This Row],[KM Rodado]]*1.1, Tabela1[[#This Row],[KM Rodado]]*1.23) -> 99 | W76: =IFERROR(SUBSTITUTE(Tabela1[[#This Row],[Pedágio]],".",",",1)*1,0) -> 0 | X76: =IFERROR(SUBSTITUTE(Tabela1[[#This Row],[Estacionamento]],".",",",1)*1,0) -> 0 | Y76: =IFERROR(SUBSTITUTE(Tabela1[[#This Row],[Despesas Diversas (Jantar em viagem, Impressões, Etc)]],".",",",1)*1,0) -> 0 | Z76: =IFERROR(SUBSTITUTE(Tabela1[[#This Row],[Hospedagem]],".",",",1)*1,0) -> 0 | AA76: =IF(DAY(Tabela1[[#This Row],[Informe a data]])<=15,"1ª Quinzena","2ª Quinzena") -> 1ª Quinzena | AB76: =UPPER(TEXT(Tabela1[[#This Row],[Informe a data]],"mmmm")) -> FEVEREIRO | AC76: =_xlfn.CONCAT(Tabela1[[#This Row],[Selecione o Usuário]]," - ",TEXT(Tabela1[[#This Row],[Informe a data]],"dd-mm-aa")) -> #NAME?
A77: 46060.394 | B77: matheus.moraes@mazzini.com.br | C77: MATHEUS DA SILVA MORAES | D77: KIL7H04 | E77: 46058 | F77: 120017 | G77: https://drive.google.com/open?id=14rty0RMEyUMlH2xj85XgMjTqsy3ssQak | H77: 120139 | I77: https://drive.google.com/open?id=1nORbTmcpxBPrftnjHw2261cffdPlvIVY | J77: Komprao40 Blumenau Agua Verde, Cooper Gen. Osório, Koch Lj 89 Blumenau, Rua Lontras 206 ( Busca de Material - Desligamento ), Giassi Blumenau, Komprao Blumenau Lj32, Super A Lj1 Blumenau. | K77: 9 | L77: Não | U77: =(Tabela1[[#This Row],[Informe o KM final do dia]]-Tabela1[[#This Row],[Informe o KM inicial do dia]])-Tabela1[[#This Row],[Caso tenha rodado particular alguma parte do trajeto, informe o total de KM a ser deduzido.]] -> 113 | V77: =IF(Tabela1[[#This Row],[Informe a data]]<DATE(2026,3,16), Tabela1[[#This Row],[KM Rodado]]*1.1, Tabela1[[#This Row],[KM Rodado]]*1.23) -> 124.3 | W77: =IFERROR(SUBSTITUTE(Tabela1[[#This Row],[Pedágio]],".",",",1)*1,0) -> 0 | X77: =IFERROR(SUBSTITUTE(Tabela1[[#This Row],[Estacionamento]],".",",",1)*1,0) -> 0 | Y77: =IFERROR(SUBSTITUTE(Tabela1[[#This Row],[Despesas Diversas (Jantar em viagem, Impressões, Etc)]],".",",",1)*1,0) -> 0 | Z77: =IFERROR(SUBSTITUTE(Tabela1[[#This Row],[Hospedagem]],".",",",1)*1,0) -> 0 | AA77: =IF(DAY(Tabela1[[#This Row],[Informe a data]])<=15,"1ª Quinzena","2ª Quinzena") -> 1ª Quinzena | AB77: =UPPER(TEXT(Tabela1[[#This Row],[Informe a data]],"mmmm")) -> FEVEREIRO | AC77: =_xlfn.CONCAT(Tabela1[[#This Row],[Selecione o Usuário]]," - ",TEXT(Tabela1[[#This Row],[Informe a data]],"dd-mm-aa")) -> #NAME?
A78: 46071.358 | B78: lombardi2025@gmail.com | C78: RICARDO ALEXANDRE LOMBARDI | D78: OWA4C07 | E78: 46058 | F78: 169262 | H78: 169277 | J78: Bistek,condor, Brasil atacadista | L78: Não | U78: =(Tabela1[[#This Row],[Informe o KM final do dia]]-Tabela1[[#This Row],[Informe o KM inicial do dia]])-Tabela1[[#This Row],[Caso tenha rodado particular alguma parte do trajeto, informe o total de KM a ser deduzido.]] -> 15 | V78: =IF(Tabela1[[#This Row],[Informe a data]]<DATE(2026,3,16), Tabela1[[#This Row],[KM Rodado]]*1.1, Tabela1[[#This Row],[KM Rodado]]*1.23) -> 16.5 | W78: =IFERROR(SUBSTITUTE(Tabela1[[#This Row],[Pedágio]],".",",",1)*1,0) -> 0 | X78: =IFERROR(SUBSTITUTE(Tabela1[[#This Row],[Estacionamento]],".",",",1)*1,0) -> 0 | Y78: =IFERROR(SUBSTITUTE(Tabela1[[#This Row],[Despesas Diversas (Jantar em viagem, Impressões, Etc)]],".",",",1)*1,0) -> 0 | Z78: =IFERROR(SUBSTITUTE(Tabela1[[#This Row],[Hospedagem]],".",",",1)*1,0) -> 0 | AA78: =IF(DAY(Tabela1[[#This Row],[Informe a data]])<=15,"1ª Quinzena","2ª Quinzena") -> 1ª Quinzena | AB78: =UPPER(TEXT(Tabela1[[#This Row],[Informe a data]],"mmmm")) -> FEVEREIRO | AC78: =_xlfn.CONCAT(Tabela1[[#This Row],[Selecione o Usuário]]," - ",TEXT(Tabela1[[#This Row],[Informe a data]],"dd-mm-aa")) -> #NAME?
A79: 46061.689 | B79: sabrina.pires@mazzini.com.br | C79: SABRINA DOS SANTOS PIRES | D79: Azc9e32 | E79: 46058 | F79: 56555 | G79: https://drive.google.com/open?id=1CQzBqF8RL5Lo-9CF1x_AnCSILBNMzppQ | H79: 56587 | I79: https://drive.google.com/open?id=1VtSq_6NCvm56bbJGBlkIKgx3FEE8a0VY | J79: Brasil atacadista central Fort atacadista 130 Fort 306 | L79: Não | U79: =(Tabela1[[#This Row],[Informe o KM final do dia]]-Tabela1[[#This Row],[Informe o KM inicial do dia]])-Tabela1[[#This Row],[Caso tenha rodado particular alguma parte do trajeto, informe o total de KM a ser deduzido.]] -> 32 | V79: =IF(Tabela1[[#This Row],[Informe a data]]<DATE(2026,3,16), Tabela1[[#This Row],[KM Rodado]]*1.1, Tabela1[[#This Row],[KM Rodado]]*1.23) -> 35.2 | W79: =IFERROR(SUBSTITUTE(Tabela1[[#This Row],[Pedágio]],".",",",1)*1,0) -> 0 | X79: =IFERROR(SUBSTITUTE(Tabela1[[#This Row],[Estacionamento]],".",",",1)*1,0) -> 0 | Y79: =IFERROR(SUBSTITUTE(Tabela1[[#This Row],[Despesas Diversas (Jantar em viagem, Impressões, Etc)]],".",",",1)*1,0) -> 0 | Z79: =IFERROR(SUBSTITUTE(Tabela1[[#This Row],[Hospedagem]],".",",",1)*1,0) -> 0 | AA79: =IF(DAY(Tabela1[[#This Row],[Informe a data]])<=15,"1ª Quinzena","2ª Quinzena") -> 1ª Quinzena | AB79: =UPPER(TEXT(Tabela1[[#This Row],[Informe a data]],"mmmm")) -> FEVEREIRO | AC79: =_xlfn.CONCAT(Tabela1[[#This Row],[Selecione o Usuário]]," - ",TEXT(Tabela1[[#This Row],[Informe a data]],"dd-mm-aa")) -> #NAME?
A80: 46063.693 | B80: aline.isacmoreira@gmail.com | C80: Aline Isac Moreira | D80: MHV7D46 | E80: 46059 | F80: 74739 | H80: 74851 | J80: De Jaraguá do Sul para Joinville mercado vizinhao bairro Guanabara | L80: Não | U80: =(Tabela1[[#This Row],[Informe o KM final do dia]]-Tabela1[[#This Row],[Informe o KM inicial do dia]])-Tabela1[[#This Row],[Caso tenha rodado particular alguma parte do trajeto, informe o total de KM a ser deduzido.]] -> 112 | V80: =IF(Tabela1[[#This Row],[Informe a data]]<DATE(2026,3,16), Tabela1[[#This Row],[KM Rodado]]*1.1, Tabela1[[#This Row],[KM Rodado]]*1.23) -> 123.2 | W80: =IFERROR(SUBSTITUTE(Tabela1[[#This Row],[Pedágio]],".",",",1)*1,0) -> 0 | X80: =IFERROR(SUBSTITUTE(Tabela1[[#This Row],[Estacionamento]],".",",",1)*1,0) -> 0 | Y80: =IFERROR(SUBSTITUTE(Tabela1[[#This Row],[Despesas Diversas (Jantar em viagem, Impressões, Etc)]],".",",",1)*1,0) -> 0 | Z80: =IFERROR(SUBSTITUTE(Tabela1[[#This Row],[Hospedagem]],".",",",1)*1,0) -> 0 | AA80: =IF(DAY(Tabela1[[#This Row],[Informe a data]])<=15,"1ª Quinzena","2ª Quinzena") -> 1ª Quinzena | AB80: =UPPER(TEXT(Tabela1[[#This Row],[Informe a data]],"mmmm")) -> FEVEREIRO | AC80: =_xlfn.CONCAT(Tabela1[[#This Row],[Selecione o Usuário]]," - ",TEXT(Tabela1[[#This Row],[Informe a data]],"dd-mm-aa")) -> #NAME?
A81: 46060.472 | B81: camila.althoff@mazzini.com.br | C81: CAMILA CRISTINE ALTHOFF | D81: Mlz4j72 | E81: 46059 | F81: 187393 | G81: https://drive.google.com/open?id=13Jy6mYP8_xyhCmB9-LOexm9w8uW4y6kN | H81: 187611 | I81: https://drive.google.com/open?id=1OB8HtjgnhJNEOJzgxVtkMj5G99Qs73W7 | J81: Reunião mercado Joinville | L81: Sim | M81: 11.40 | N81: https://drive.google.com/open?id=1UWabPjZTdzphkNtnhz7dsRKOV8l5UytL | R81: https://drive.google.com/open?id=1wPsf9dmAp665gGOoDNht8p8i7oFwEf8G | S81: 300.86 | U81: =(Tabela1[[#This Row],[Informe o KM final do dia]]-Tabela1[[#This Row],[Informe o KM inicial do dia]])-Tabela1[[#This Row],[Caso tenha rodado particular alguma parte do trajeto, informe o total de KM a ser deduzido.]] -> 218 | V81: =IF(Tabela1[[#This Row],[Informe a data]]<DATE(2026,3,16), Tabela1[[#This Row],[KM Rodado]]*1.1, Tabela1[[#This Row],[KM Rodado]]*1.23) -> 239.8 | W81: =IFERROR(SUBSTITUTE(Tabela1[[#This Row],[Pedágio]],".",",",1)*1,0) -> 11.4 | X81: =IFERROR(SUBSTITUTE(Tabela1[[#This Row],[Estacionamento]],".",",",1)*1,0) -> 0 | Y81: =IFERROR(SUBSTITUTE(Tabela1[[#This Row],[Despesas Diversas (Jantar em viagem, Impressões, Etc)]],".",",",1)*1,0) -> 0 | Z81: =IFERROR(SUBSTITUTE(Tabela1[[#This Row],[Hospedagem]],".",",",1)*1,0) -> 300.86 | AA81: =IF(DAY(Tabela1[[#This Row],[Informe a data]])<=15,"1ª Quinzena","2ª Quinzena") -> 1ª Quinzena | AB81: =UPPER(TEXT(Tabela1[[#This Row],[Informe a data]],"mmmm")) -> FEVEREIRO | AC81: =_xlfn.CONCAT(Tabela1[[#This Row],[Selecione o Usuário]]," - ",TEXT(Tabela1[[#This Row],[Informe a data]],"dd-mm-aa")) -> #NAME?
A82: 46061.437 | B82: sabrina.pires@mazzini.com.br | C82: SABRINA DOS SANTOS PIRES | D82: Azc9e32 | E82: 46059 | F82: 197216 | G82: https://drive.google.com/open?id=10aid5gfs8AkL4XHRsXLUdx4HaLcZwMc_ | H82: 197296 | I82: https://drive.google.com/open?id=14w-MQ4jGIKJRR-vLXV-36aIrIeQwcGVW | J82: Fort atacadista Fort 365 Komprao | L82: Não | U82: =(Tabela1[[#This Row],[Informe o KM final do dia]]-Tabela1[[#This Row],[Informe o KM inicial do dia]])-Tabela1[[#This Row],[Caso tenha rodado particular alguma parte do trajeto, informe o total de KM a ser deduzido.]] -> 80 | V82: =IF(Tabela1[[#This Row],[Informe a data]]<DATE(2026,3,16), Tabela1[[#This Row],[KM Rodado]]*1.1, Tabela1[[#This Row],[KM Rodado]]*1.23) -> 88 | W82: =IFERROR(SUBSTITUTE(Tabela1[[#This Row],[Pedágio]],".",",",1)*1,0) -> 0 | X82: =IFERROR(SUBSTITUTE(Tabela1[[#This Row],[Estacionamento]],".",",",1)*1,0) -> 0 | Y82: =IFERROR(SUBSTITUTE(Tabela1[[#This Row],[Despesas Diversas (Jantar em viagem, Impressões, Etc)]],".",",",1)*1,0) -> 0 | Z82: =IFERROR(SUBSTITUTE(Tabela1[[#This Row],[Hospedagem]],".",",",1)*1,0) -> 0 | AA82: =IF(DAY(Tabela1[[#This Row],[Informe a data]])<=15,"1ª Quinzena","2ª Quinzena") -> 1ª Quinzena | AB82: =UPPER(TEXT(Tabela1[[#This Row],[Informe a data]],"mmmm")) -> FEVEREIRO | AC82: =_xlfn.CONCAT(Tabela1[[#This Row],[Selecione o Usuário]]," - ",TEXT(Tabela1[[#This Row],[Informe a data]],"dd-mm-aa")) -> #NAME?
A83: 46063.698 | B83: aline.isacmoreira@gmail.com | C83: Aline Isac Moreira | D83: MHV7D46 | E83: 46062 | F83: 74913 | H83: 75117 | J83: De Jaraguá do Sul para komprao de Araquari, komprao de são Francisco do Sul, Angeloni SFS, komprao 50 SFS, Angeloni SFS,super Koch SFS , JOINVILLE , JARAGUÁ DO SUL | L83: Não | U83: =(Tabela1[[#This Row],[Informe o KM final do dia]]-Tabela1[[#This Row],[Informe o KM inicial do dia]])-Tabela1[[#This Row],[Caso tenha rodado particular alguma parte do trajeto, informe o total de KM a ser deduzido.]] -> 204 | V83: =IF(Tabela1[[#This Row],[Informe a data]]<DATE(2026,3,16), Tabela1[[#This Row],[KM Rodado]]*1.1, Tabela1[[#This Row],[KM Rodado]]*1.23) -> 224.4 | W83: =IFERROR(SUBSTITUTE(Tabela1[[#This Row],[Pedágio]],".",",",1)*1,0) -> 0 | X83: =IFERROR(SUBSTITUTE(Tabela1[[#This Row],[Estacionamento]],".",",",1)*1,0) -> 0 | Y83: =IFERROR(SUBSTITUTE(Tabela1[[#This Row],[Despesas Diversas (Jantar em viagem, Impressões, Etc)]],".",",",1)*1,0) -> 0 | Z83: =IFERROR(SUBSTITUTE(Tabela1[[#This Row],[Hospedagem]],".",",",1)*1,0) -> 0 | AA83: =IF(DAY(Tabela1[[#This Row],[Informe a data]])<=15,"1ª Quinzena","2ª Quinzena") -> 1ª Quinzena | AB83: =UPPER(TEXT(Tabela1[[#This Row],[Informe a data]],"mmmm")) -> FEVEREIRO | AC83: =_xlfn.CONCAT(Tabela1[[#This Row],[Selecione o Usuário]]," - ",TEXT(Tabela1[[#This Row],[Informe a data]],"dd-mm-aa")) -> #NAME?
A84: 46063.365 | B84: camila.althoff@mazzini.com.br | C84: CAMILA CRISTINE ALTHOFF | D84: Mlz4j72 | E84: 46062 | F84: 187617 | G84: https://drive.google.com/open?id=1-f7955OG0uaumVr8w7khA3GOTTXXexJc | H84: 187828 | I84: https://drive.google.com/open?id=1dMxld6xIS_DfCUfXD7IozHH0K4Sw-J2V | J84: Casa coordenadora, fórum Blumenau, hotel | L84: Sim | M84: 5.70 | N84: https://drive.google.com/open?id=1noq0udzq2cyXcvPQ8CqriVYKnZfRVq8Z | O84: 30.00 | P84: https://drive.google.com/open?id=1xVbDsVHXQiwL7cTsAm2__epsQ3vjqA9y | Q84: 37.90 | R84: https://drive.google.com/open?id=12ACsP5IqVOsyNaLhds7oKARdkimeeH7J | U84: =(Tabela1[[#This Row],[Informe o KM final do dia]]-Tabela1[[#This Row],[Informe o KM inicial do dia]])-Tabela1[[#This Row],[Caso tenha rodado particular alguma parte do trajeto, informe o total de KM a ser deduzido.]] -> 211 | V84: =IF(Tabela1[[#This Row],[Informe a data]]<DATE(2026,3,16), Tabela1[[#This Row],[KM Rodado]]*1.1, Tabela1[[#This Row],[KM Rodado]]*1.23) -> 232.1 | W84: =IFERROR(SUBSTITUTE(Tabela1[[#This Row],[Pedágio]],".",",",1)*1,0) -> 5.7 | X84: =IFERROR(SUBSTITUTE(Tabela1[[#This Row],[Estacionamento]],".",",",1)*1,0) -> 30 | Y84: =IFERROR(SUBSTITUTE(Tabela1[[#This Row],[Despesas Diversas (Jantar em viagem, Impressões, Etc)]],".",",",1)*1,0) -> 37.9 | Z84: =IFERROR(SUBSTITUTE(Tabela1[[#This Row],[Hospedagem]],".",",",1)*1,0) -> 0 | AA84: =IF(DAY(Tabela1[[#This Row],[Informe a data]])<=15,"1ª Quinzena","2ª Quinzena") -> 1ª Quinzena | AB84: =UPPER(TEXT(Tabela1[[#This Row],[Informe a data]],"mmmm")) -> FEVEREIRO | AC84: =_xlfn.CONCAT(Tabela1[[#This Row],[Selecione o Usuário]]," - ",TEXT(Tabela1[[#This Row],[Informe a data]],"dd-mm-aa")) -> #NAME?
A85: 46064.844 | B85: matheus.moraes@mazzini.com.br | C85: MATHEUS DA SILVA MORAES | D85: QLI7H04 | E85: 46062 | F85: 120436 | G85: https://drive.google.com/open?id=1gLZF0RRxXVdFhAAZjJ3FvTZA7Ot7Z8XV | H85: 120611 | I85: https://drive.google.com/open?id=1kg0gueQ3H5MGSy_Xd-K6FLWwpFKL9x3W | J85: Brasil atacadista Blumenau, Zeus, bisteck garcia e Archer 01 Brusque | L85: Sim | Q85: 3.70 | R85: https://drive.google.com/open?id=1w_iJKC_zWZ2qf5ahUQ4E57MkoIphorsf | U85: =(Tabela1[[#This Row],[Informe o KM final do dia]]-Tabela1[[#This Row],[Informe o KM inicial do dia]])-Tabela1[[#This Row],[Caso tenha rodado particular alguma parte do trajeto, informe o total de KM a ser deduzido.]] -> 175 | V85: =IF(Tabela1[[#This Row],[Informe a data]]<DATE(2026,3,16), Tabela1[[#This Row],[KM Rodado]]*1.1, Tabela1[[#This Row],[KM Rodado]]*1.23) -> 192.5 | W85: =IFERROR(SUBSTITUTE(Tabela1[[#This Row],[Pedágio]],".",",",1)*1,0) -> 0 | X85: =IFERROR(SUBSTITUTE(Tabela1[[#This Row],[Estacionamento]],".",",",1)*1,0) -> 0 | Y85: =IFERROR(SUBSTITUTE(Tabela1[[#This Row],[Despesas Diversas (Jantar em viagem, Impressões, Etc)]],".",",",1)*1,0) -> 3.7 | Z85: =IFERROR(SUBSTITUTE(Tabela1[[#This Row],[Hospedagem]],".",",",1)*1,0) -> 0 | AA85: =IF(DAY(Tabela1[[#This Row],[Informe a data]])<=15,"1ª Quinzena","2ª Quinzena") -> 1ª Quinzena | AB85: =UPPER(TEXT(Tabela1[[#This Row],[Informe a data]],"mmmm")) -> FEVEREIRO | AC85: =_xlfn.CONCAT(Tabela1[[#This Row],[Selecione o Usuário]]," - ",TEXT(Tabela1[[#This Row],[Informe a data]],"dd-mm-aa")) -> #NAME?
A86: 46064.95 | B86: sabrina.pires@mazzini.com.br | C86: SABRINA DOS SANTOS PIRES | D86: Azc9E32 | E86: 46062 | F86: 174328 | G86: https://drive.google.com/open?id=1XLyK_TImiOqmcqY5Hacmc3aFEVHjhHna | H86: 174413 | I86: https://drive.google.com/open?id=1j_XARqxjjPzZOYorBk_foeNERyZZuDqf | J86: Brasil atacadista Rio Tavares Fort atacadista Fort atacadista Komprao Koch | L86: Não | U86: =(Tabela1[[#This Row],[Informe o KM final do dia]]-Tabela1[[#This Row],[Informe o KM inicial do dia]])-Tabela1[[#This Row],[Caso tenha rodado particular alguma parte do trajeto, informe o total de KM a ser deduzido.]] -> 85 | V86: =IF(Tabela1[[#This Row],[Informe a data]]<DATE(2026,3,16), Tabela1[[#This Row],[KM Rodado]]*1.1, Tabela1[[#This Row],[KM Rodado]]*1.23) -> 93.5 | W86: =IFERROR(SUBSTITUTE(Tabela1[[#This Row],[Pedágio]],".",",",1)*1,0) -> 0 | X86: =IFERROR(SUBSTITUTE(Tabela1[[#This Row],[Estacionamento]],".",",",1)*1,0) -> 0 | Y86: =IFERROR(SUBSTITUTE(Tabela1[[#This Row],[Despesas Diversas (Jantar em viagem, Impressões, Etc)]],".",",",1)*1,0) -> 0 | Z86: =IFERROR(SUBSTITUTE(Tabela1[[#This Row],[Hospedagem]],".",",",1)*1,0) -> 0 | AA86: =IF(DAY(Tabela1[[#This Row],[Informe a data]])<=15,"1ª Quinzena","2ª Quinzena") -> 1ª Quinzena | AB86: =UPPER(TEXT(Tabela1[[#This Row],[Informe a data]],"mmmm")) -> FEVEREIRO | AC86: =_xlfn.CONCAT(Tabela1[[#This Row],[Selecione o Usuário]]," - ",TEXT(Tabela1[[#This Row],[Informe a data]],"dd-mm-aa")) -> #NAME?
A87: 46063.699 | B87: aline.isacmoreira@gmail.com | C87: Aline Isac Moreira | D87: MHV7D46 | E87: 46063 | F87: 75117 | H87: 75133 | J87: Angeloni 10 Jaraguá do Sul,Super A Jaraguá do Sul | L87: Não | U87: =(Tabela1[[#This Row],[Informe o KM final do dia]]-Tabela1[[#This Row],[Informe o KM inicial do dia]])-Tabela1[[#This Row],[Caso tenha rodado particular alguma parte do trajeto, informe o total de KM a ser deduzido.]] -> 16 | V87: =IF(Tabela1[[#This Row],[Informe a data]]<DATE(2026,3,16), Tabela1[[#This Row],[KM Rodado]]*1.1, Tabela1[[#This Row],[KM Rodado]]*1.23) -> 17.6 | W87: =IFERROR(SUBSTITUTE(Tabela1[[#This Row],[Pedágio]],".",",",1)*1,0) -> 0 | X87: =IFERROR(SUBSTITUTE(Tabela1[[#This Row],[Estacionamento]],".",",",1)*1,0) -> 0 | Y87: =IFERROR(SUBSTITUTE(Tabela1[[#This Row],[Despesas Diversas (Jantar em viagem, Impressões, Etc)]],".",",",1)*1,0) -> 0 | Z87: =IFERROR(SUBSTITUTE(Tabela1[[#This Row],[Hospedagem]],".",",",1)*1,0) -> 0 | AA87: =IF(DAY(Tabela1[[#This Row],[Informe a data]])<=15,"1ª Quinzena","2ª Quinzena") -> 1ª Quinzena | AB87: =UPPER(TEXT(Tabela1[[#This Row],[Informe a data]],"mmmm")) -> FEVEREIRO | AC87: =_xlfn.CONCAT(Tabela1[[#This Row],[Selecione o Usuário]]," - ",TEXT(Tabela1[[#This Row],[Informe a data]],"dd-mm-aa")) -> #NAME?
A88: 46065.356 | B88: camila.althoff@mazzini.com.br | C88: CAMILA CRISTINE ALTHOFF | D88: Mlz4j72 | E88: 46063 | F88: 187828 | G88: https://drive.google.com/open?id=14UIkzQ0U3YytrpTlBIfbPJ5-E_yHCeEI | H88: 188057 | I88: https://drive.google.com/open?id=1vOCstaTw0qawpUdRY-_LxfDXk06B5B5o | J88: Hotel Blumenau, Fort vargem, brasil ingleses | L88: Sim | M88: 5.70 | N88: https://drive.google.com/open?id=1p6G2JwVQgRroLOGuu1hzLwij3aRTZgtn | O88: 25.00 | P88: https://drive.google.com/open?id=1u6dCdfNtinTesprSra0Hy10_w0XRPPyQ | S88: 236.68 | U88: =(Tabela1[[#This Row],[Informe o KM final do dia]]-Tabela1[[#This Row],[Informe o KM inicial do dia]])-Tabela1[[#This Row],[Caso tenha rodado particular alguma parte do trajeto, informe o total de KM a ser deduzido.]] -> 229 | V88: =IF(Tabela1[[#This Row],[Informe a data]]<DATE(2026,3,16), Tabela1[[#This Row],[KM Rodado]]*1.1, Tabela1[[#This Row],[KM Rodado]]*1.23) -> 251.9 | W88: =IFERROR(SUBSTITUTE(Tabela1[[#This Row],[Pedágio]],".",",",1)*1,0) -> 5.7 | X88: =IFERROR(SUBSTITUTE(Tabela1[[#This Row],[Estacionamento]],".",",",1)*1,0) -> 25 | Y88: =IFERROR(SUBSTITUTE(Tabela1[[#This Row],[Despesas Diversas (Jantar em viagem, Impressões, Etc)]],".",",",1)*1,0) -> 0 | Z88: =IFERROR(SUBSTITUTE(Tabela1[[#This Row],[Hospedagem]],".",",",1)*1,0) -> 236.68 | AA88: =IF(DAY(Tabela1[[#This Row],[Informe a data]])<=15,"1ª Quinzena","2ª Quinzena") -> 1ª Quinzena | AB88: =UPPER(TEXT(Tabela1[[#This Row],[Informe a data]],"mmmm")) -> FEVEREIRO | AC88: =_xlfn.CONCAT(Tabela1[[#This Row],[Selecione o Usuário]]," - ",TEXT(Tabela1[[#This Row],[Informe a data]],"dd-mm-aa")) -> #NAME?
A89: 46069.699 | B89: oliiveiiraa7@gmail.com | C89: GUSTAVO MATHEUS DE OLIVEIRA | D89: EUF3090 | E89: 46063 | F89: 161736 | H89: 161964 | J89: Atacadao lages, Bistek Lages, Fort 960, angeloni Lages, Fort 960, Stok Center Lages | L89: Não | U89: =(Tabela1[[#This Row],[Informe o KM final do dia]]-Tabela1[[#This Row],[Informe o KM inicial do dia]])-Tabela1[[#This Row],[Caso tenha rodado particular alguma parte do trajeto, informe o total de KM a ser deduzido.]] -> 228 | V89: =IF(Tabela1[[#This Row],[Informe a data]]<DATE(2026,3,16), Tabela1[[#This Row],[KM Rodado]]*1.1, Tabela1[[#This Row],[KM Rodado]]*1.23) -> 250.8 | W89: =IFERROR(SUBSTITUTE(Tabela1[[#This Row],[Pedágio]],".",",",1)*1,0) -> 0 | X89: =IFERROR(SUBSTITUTE(Tabela1[[#This Row],[Estacionamento]],".",",",1)*1,0) -> 0 | Y89: =IFERROR(SUBSTITUTE(Tabela1[[#This Row],[Despesas Diversas (Jantar em viagem, Impressões, Etc)]],".",",",1)*1,0) -> 0 | Z89: =IFERROR(SUBSTITUTE(Tabela1[[#This Row],[Hospedagem]],".",",",1)*1,0) -> 0 | AA89: =IF(DAY(Tabela1[[#This Row],[Informe a data]])<=15,"1ª Quinzena","2ª Quinzena") -> 1ª Quinzena | AB89: =UPPER(TEXT(Tabela1[[#This Row],[Informe a data]],"mmmm")) -> FEVEREIRO | AC89: =_xlfn.CONCAT(Tabela1[[#This Row],[Selecione o Usuário]]," - ",TEXT(Tabela1[[#This Row],[Informe a data]],"dd-mm-aa")) -> #NAME?
A90: 46065.359 | B90: camila.althoff@mazzini.com.br | C90: CAMILA CRISTINE ALTHOFF | D90: Mlz4j72 | E90: 46064 | F90: 188057 | G90: https://drive.google.com/open?id=1KyZkHuSDZjLyezp3FBBWx5LjbuzCF2Dj | H90: 188096 | I90: https://drive.google.com/open?id=1ULQZZg3QzbcVvON3zBkzWAON0kFBUlMk | J90: Angeloni beira mar, Fort campeche ,Fort rio Tavares | L90: Não | U90: =(Tabela1[[#This Row],[Informe o KM final do dia]]-Tabela1[[#This Row],[Informe o KM inicial do dia]])-Tabela1[[#This Row],[Caso tenha rodado particular alguma parte do trajeto, informe o total de KM a ser deduzido.]] -> 39 | V90: =IF(Tabela1[[#This Row],[Informe a data]]<DATE(2026,3,16), Tabela1[[#This Row],[KM Rodado]]*1.1, Tabela1[[#This Row],[KM Rodado]]*1.23) -> 42.9 | W90: =IFERROR(SUBSTITUTE(Tabela1[[#This Row],[Pedágio]],".",",",1)*1,0) -> 0 | X90: =IFERROR(SUBSTITUTE(Tabela1[[#This Row],[Estacionamento]],".",",",1)*1,0) -> 0 | Y90: =IFERROR(SUBSTITUTE(Tabela1[[#This Row],[Despesas Diversas (Jantar em viagem, Impressões, Etc)]],".",",",1)*1,0) -> 0 | Z90: =IFERROR(SUBSTITUTE(Tabela1[[#This Row],[Hospedagem]],".",",",1)*1,0) -> 0 | AA90: =IF(DAY(Tabela1[[#This Row],[Informe a data]])<=15,"1ª Quinzena","2ª Quinzena") -> 1ª Quinzena | AB90: =UPPER(TEXT(Tabela1[[#This Row],[Informe a data]],"mmmm")) -> FEVEREIRO | AC90: =_xlfn.CONCAT(Tabela1[[#This Row],[Selecione o Usuário]]," - ",TEXT(Tabela1[[#This Row],[Informe a data]],"dd-mm-aa")) -> #NAME?
A91: 46065.769 | B91: martinsneto047@gmail.com | C91: JOÃO MARTINS NETO | D91: IUT1C03 | E91: 46064 | F91: 99748 | G91: https://drive.google.com/open?id=1Q5OjeaB07AatS3w5iDdlGnUB3BwhE6Ab | H91: 99857 | I91: https://drive.google.com/open?id=177wIGkq19RdrBPgQyiIoZ5S73xkwSSqA | J91: FUI FAZER INTREGRAÇAO DO JOAO GABRIEL PONTES KOCH 06 LOGO APOS SAI EM ROTA PARA ITAJAI, FAZER GSL ANDREY ANGELONI ITAJAI E CONHECER AS LOJA DA MINHA BASE. | L91: Não | U91: =(Tabela1[[#This Row],[Informe o KM final do dia]]-Tabela1[[#This Row],[Informe o KM inicial do dia]])-Tabela1[[#This Row],[Caso tenha rodado particular alguma parte do trajeto, informe o total de KM a ser deduzido.]] -> 109 | V91: =IF(Tabela1[[#This Row],[Informe a data]]<DATE(2026,3,16), Tabela1[[#This Row],[KM Rodado]]*1.1, Tabela1[[#This Row],[KM Rodado]]*1.23) -> 119.9 | W91: =IFERROR(SUBSTITUTE(Tabela1[[#This Row],[Pedágio]],".",",",1)*1,0) -> 0 | X91: =IFERROR(SUBSTITUTE(Tabela1[[#This Row],[Estacionamento]],".",",",1)*1,0) -> 0 | Y91: =IFERROR(SUBSTITUTE(Tabela1[[#This Row],[Despesas Diversas (Jantar em viagem, Impressões, Etc)]],".",",",1)*1,0) -> 0 | Z91: =IFERROR(SUBSTITUTE(Tabela1[[#This Row],[Hospedagem]],".",",",1)*1,0) -> 0 | AA91: =IF(DAY(Tabela1[[#This Row],[Informe a data]])<=15,"1ª Quinzena","2ª Quinzena") -> 1ª Quinzena | AB91: =UPPER(TEXT(Tabela1[[#This Row],[Informe a data]],"mmmm")) -> FEVEREIRO | AC91: =_xlfn.CONCAT(Tabela1[[#This Row],[Selecione o Usuário]]," - ",TEXT(Tabela1[[#This Row],[Informe a data]],"dd-mm-aa")) -> #NAME?
A92: 46064.943 | B92: sabrina.pires@mazzini.com.br | C92: SABRINA DOS SANTOS PIRES | D92: Azc9E32 | E92: 46064 | F92: 56587 | G92: https://drive.google.com/open?id=1k0urNLDawY7EGwbhi_xg_UumuguSKN4k | H92: 56769 | I92: https://drive.google.com/open?id=1l_D93bqziAri4Da5uyYMrgoxQwj0nxnf | J92: Brasil atacadista Fort 462 Fort 130 Fort 306 Fort 365 | L92: Não | U92: =(Tabela1[[#This Row],[Informe o KM final do dia]]-Tabela1[[#This Row],[Informe o KM inicial do dia]])-Tabela1[[#This Row],[Caso tenha rodado particular alguma parte do trajeto, informe o total de KM a ser deduzido.]] -> 182 | V92: =IF(Tabela1[[#This Row],[Informe a data]]<DATE(2026,3,16), Tabela1[[#This Row],[KM Rodado]]*1.1, Tabela1[[#This Row],[KM Rodado]]*1.23) -> 200.2 | W92: =IFERROR(SUBSTITUTE(Tabela1[[#This Row],[Pedágio]],".",",",1)*1,0) -> 0 | X92: =IFERROR(SUBSTITUTE(Tabela1[[#This Row],[Estacionamento]],".",",",1)*1,0) -> 0 | Y92: =IFERROR(SUBSTITUTE(Tabela1[[#This Row],[Despesas Diversas (Jantar em viagem, Impressões, Etc)]],".",",",1)*1,0) -> 0 | Z92: =IFERROR(SUBSTITUTE(Tabela1[[#This Row],[Hospedagem]],".",",",1)*1,0) -> 0 | AA92: =IF(DAY(Tabela1[[#This Row],[Informe a data]])<=15,"1ª Quinzena","2ª Quinzena") -> 1ª Quinzena | AB92: =UPPER(TEXT(Tabela1[[#This Row],[Informe a data]],"mmmm")) -> FEVEREIRO | AC92: =_xlfn.CONCAT(Tabela1[[#This Row],[Selecione o Usuário]]," - ",TEXT(Tabela1[[#This Row],[Informe a data]],"dd-mm-aa")) -> #NAME?
A93: 46066.349 | B93: camila.althoff@mazzini.com.br | C93: CAMILA CRISTINE ALTHOFF | D93: Mlz4j72 | E93: 46065 | F93: 188096 | G93: https://drive.google.com/open?id=1aCj0RAKwye0pxjw_zcaab-aCcx9y3kZg | H93: 188131 | I93: https://drive.google.com/open?id=13bmfQD2ACPir59SNxdS7d3rd_b7BEhiL | J93: Angeloni beira mar, Fort 810 | L93: Não | U93: =(Tabela1[[#This Row],[Informe o KM final do dia]]-Tabela1[[#This Row],[Informe o KM inicial do dia]])-Tabela1[[#This Row],[Caso tenha rodado particular alguma parte do trajeto, informe o total de KM a ser deduzido.]] -> 35 | V93: =IF(Tabela1[[#This Row],[Informe a data]]<DATE(2026,3,16), Tabela1[[#This Row],[KM Rodado]]*1.1, Tabela1[[#This Row],[KM Rodado]]*1.23) -> 38.5 | W93: =IFERROR(SUBSTITUTE(Tabela1[[#This Row],[Pedágio]],".",",",1)*1,0) -> 0 | X93: =IFERROR(SUBSTITUTE(Tabela1[[#This Row],[Estacionamento]],".",",",1)*1,0) -> 0 | Y93: =IFERROR(SUBSTITUTE(Tabela1[[#This Row],[Despesas Diversas (Jantar em viagem, Impressões, Etc)]],".",",",1)*1,0) -> 0 | Z93: =IFERROR(SUBSTITUTE(Tabela1[[#This Row],[Hospedagem]],".",",",1)*1,0) -> 0 | AA93: =IF(DAY(Tabela1[[#This Row],[Informe a data]])<=15,"1ª Quinzena","2ª Quinzena") -> 1ª Quinzena | AB93: =UPPER(TEXT(Tabela1[[#This Row],[Informe a data]],"mmmm")) -> FEVEREIRO | AC93: =_xlfn.CONCAT(Tabela1[[#This Row],[Selecione o Usuário]]," - ",TEXT(Tabela1[[#This Row],[Informe a data]],"dd-mm-aa")) -> #NAME?
A94: 46065.764 | B94: carlos.proenca@mazzini.com.br | C94: CARLOS PROENÇA | D94: qhd3d74 | E94: 46065 | F94: 302949 | G94: https://drive.google.com/open?id=1mcnTk4EqwNbVay3hlgvAt7127HWeU7vo | H94: 303109 | I94: https://drive.google.com/open?id=10GyuxMttWwVE_V3UvHC_lXCggQ_0VIm5 | J94: komprao 18, brasil atacadista porto belo, koch 07, komprao 37 | L94: Sim | M94: 5.70 | N94: https://drive.google.com/open?id=1IB5ro_5AcXU6xqLpQ5foKyeoWqbSCz5- | U94: =(Tabela1[[#This Row],[Informe o KM final do dia]]-Tabela1[[#This Row],[Informe o KM inicial do dia]])-Tabela1[[#This Row],[Caso tenha rodado particular alguma parte do trajeto, informe o total de KM a ser deduzido.]] -> 160 | V94: =IF(Tabela1[[#This Row],[Informe a data]]<DATE(2026,3,16), Tabela1[[#This Row],[KM Rodado]]*1.1, Tabela1[[#This Row],[KM Rodado]]*1.23) -> 176 | W94: =IFERROR(SUBSTITUTE(Tabela1[[#This Row],[Pedágio]],".",",",1)*1,0) -> 5.7 | X94: =IFERROR(SUBSTITUTE(Tabela1[[#This Row],[Estacionamento]],".",",",1)*1,0) -> 0 | Y94: =IFERROR(SUBSTITUTE(Tabela1[[#This Row],[Despesas Diversas (Jantar em viagem, Impressões, Etc)]],".",",",1)*1,0) -> 0 | Z94: =IFERROR(SUBSTITUTE(Tabela1[[#This Row],[Hospedagem]],".",",",1)*1,0) -> 0 | AA94: =IF(DAY(Tabela1[[#This Row],[Informe a data]])<=15,"1ª Quinzena","2ª Quinzena") -> 1ª Quinzena | AB94: =UPPER(TEXT(Tabela1[[#This Row],[Informe a data]],"mmmm")) -> FEVEREIRO | AC94: =_xlfn.CONCAT(Tabela1[[#This Row],[Selecione o Usuário]]," - ",TEXT(Tabela1[[#This Row],[Informe a data]],"dd-mm-aa")) -> #NAME?
A95: 46067.397 | B95: sabrina.pires@mazzini.com.br | C95: SABRINA DOS SANTOS PIRES | D95: Azc9E32 | E95: 46065 | F95: 56769 | G95: https://drive.google.com/open?id=1KTHegYB9KEjt7Q5ROf6XzbQcSWCDF2hy | H95: 56924 | I95: https://drive.google.com/open?id=19dh9NcudhKzrqWNYPB4nUsKyXwRgw_2k | J95: Brasil atacadista central Ângeloni beira mar Fort 365 Fort compacto Komprao | L95: Não | U95: =(Tabela1[[#This Row],[Informe o KM final do dia]]-Tabela1[[#This Row],[Informe o KM inicial do dia]])-Tabela1[[#This Row],[Caso tenha rodado particular alguma parte do trajeto, informe o total de KM a ser deduzido.]] -> 155 | V95: =IF(Tabela1[[#This Row],[Informe a data]]<DATE(2026,3,16), Tabela1[[#This Row],[KM Rodado]]*1.1, Tabela1[[#This Row],[KM Rodado]]*1.23) -> 170.5 | W95: =IFERROR(SUBSTITUTE(Tabela1[[#This Row],[Pedágio]],".",",",1)*1,0) -> 0 | X95: =IFERROR(SUBSTITUTE(Tabela1[[#This Row],[Estacionamento]],".",",",1)*1,0) -> 0 | Y95: =IFERROR(SUBSTITUTE(Tabela1[[#This Row],[Despesas Diversas (Jantar em viagem, Impressões, Etc)]],".",",",1)*1,0) -> 0 | Z95: =IFERROR(SUBSTITUTE(Tabela1[[#This Row],[Hospedagem]],".",",",1)*1,0) -> 0 | AA95: =IF(DAY(Tabela1[[#This Row],[Informe a data]])<=15,"1ª Quinzena","2ª Quinzena") -> 1ª Quinzena | AB95: =UPPER(TEXT(Tabela1[[#This Row],[Informe a data]],"mmmm")) -> FEVEREIRO | AC95: =_xlfn.CONCAT(Tabela1[[#This Row],[Selecione o Usuário]]," - ",TEXT(Tabela1[[#This Row],[Informe a data]],"dd-mm-aa")) -> #NAME?
A96: 46067.364 | B96: camila.althoff@mazzini.com.br | C96: CAMILA CRISTINE ALTHOFF | D96: Mlz4j72 | E96: 46066 | F96: 188145 | G96: https://drive.google.com/open?id=1ZFRQvtH_JWorZc2DkGdFDOiZWK3ijPsG | H96: 188157 | I96: https://drive.google.com/open?id=1tDRCo2DfiZGvP3U6AmgCmHfVKf-9-NgA | J96: Angeloni beira mar, Fort 810 | L96: Não | U96: =(Tabela1[[#This Row],[Informe o KM final do dia]]-Tabela1[[#This Row],[Informe o KM inicial do dia]])-Tabela1[[#This Row],[Caso tenha rodado particular alguma parte do trajeto, informe o total de KM a ser deduzido.]] -> 12 | V96: =IF(Tabela1[[#This Row],[Informe a data]]<DATE(2026,3,16), Tabela1[[#This Row],[KM Rodado]]*1.1, Tabela1[[#This Row],[KM Rodado]]*1.23) -> 13.2 | W96: =IFERROR(SUBSTITUTE(Tabela1[[#This Row],[Pedágio]],".",",",1)*1,0) -> 0 | X96: =IFERROR(SUBSTITUTE(Tabela1[[#This Row],[Estacionamento]],".",",",1)*1,0) -> 0 | Y96: =IFERROR(SUBSTITUTE(Tabela1[[#This Row],[Despesas Diversas (Jantar em viagem, Impressões, Etc)]],".",",",1)*1,0) -> 0 | Z96: =IFERROR(SUBSTITUTE(Tabela1[[#This Row],[Hospedagem]],".",",",1)*1,0) -> 0 | AA96: =IF(DAY(Tabela1[[#This Row],[Informe a data]])<=15,"1ª Quinzena","2ª Quinzena") -> 1ª Quinzena | AB96: =UPPER(TEXT(Tabela1[[#This Row],[Informe a data]],"mmmm")) -> FEVEREIRO | AC96: =_xlfn.CONCAT(Tabela1[[#This Row],[Selecione o Usuário]]," - ",TEXT(Tabela1[[#This Row],[Informe a data]],"dd-mm-aa")) -> #NAME?
A97: 46069.636 | B97: martinsneto047@gmail.com | C97: JOÃO MARTINS NETO | D97: IUT1C03 | E97: 46066 | F97: 100008 | G97: https://drive.google.com/open?id=1dZHqN4ZitjysKuzofaNLcnGf02g3KmY6 | H97: 100091 | I97: https://drive.google.com/open?id=1sXdAxiE2TlParUg6TQDWhmZoQgeFLOJm | J97: REVERSAO CAREFOUR CAMBORIU MESCHKE ATACADISTA GSL SUPER KOCH GSL E ENTREGA DE EPI | L97: Não | U97: =(Tabela1[[#This Row],[Informe o KM final do dia]]-Tabela1[[#This Row],[Informe o KM inicial do dia]])-Tabela1[[#This Row],[Caso tenha rodado particular alguma parte do trajeto, informe o total de KM a ser deduzido.]] -> 83 | V97: =IF(Tabela1[[#This Row],[Informe a data]]<DATE(2026,3,16), Tabela1[[#This Row],[KM Rodado]]*1.1, Tabela1[[#This Row],[KM Rodado]]*1.23) -> 91.3 | W97: =IFERROR(SUBSTITUTE(Tabela1[[#This Row],[Pedágio]],".",",",1)*1,0) -> 0 | X97: =IFERROR(SUBSTITUTE(Tabela1[[#This Row],[Estacionamento]],".",",",1)*1,0) -> 0 | Y97: =IFERROR(SUBSTITUTE(Tabela1[[#This Row],[Despesas Diversas (Jantar em viagem, Impressões, Etc)]],".",",",1)*1,0) -> 0 | Z97: =IFERROR(SUBSTITUTE(Tabela1[[#This Row],[Hospedagem]],".",",",1)*1,0) -> 0 | AA97: =IF(DAY(Tabela1[[#This Row],[Informe a data]])<=15,"1ª Quinzena","2ª Quinzena") -> 1ª Quinzena | AB97: =UPPER(TEXT(Tabela1[[#This Row],[Informe a data]],"mmmm")) -> FEVEREIRO | AC97: =_xlfn.CONCAT(Tabela1[[#This Row],[Selecione o Usuário]]," - ",TEXT(Tabela1[[#This Row],[Informe a data]],"dd-mm-aa")) -> #NAME?
A98: 46067.358 | B98: matheus.moraes@mazzini.com.br | C98: MATHEUS DA SILVA MORAES | D98: QIL7H04 | E98: 46066 | F98: 121039 | G98: https://drive.google.com/open?id=1rPIXDwmsCfu2wkNnIjo3BMUoRa5ryWUo | H98: 121136 | I98: https://drive.google.com/open?id=1wB-WtAMpVEaGNVHPtcM1RBbzJJeg03SG | J98: Komprão timbo, fort indaial, komprão 40, cooper caçadores e cooper general osorio. | L98: Não | U98: =(Tabela1[[#This Row],[Informe o KM final do dia]]-Tabela1[[#This Row],[Informe o KM inicial do dia]])-Tabela1[[#This Row],[Caso tenha rodado particular alguma parte do trajeto, informe o total de KM a ser deduzido.]] -> 97 | V98: =IF(Tabela1[[#This Row],[Informe a data]]<DATE(2026,3,16), Tabela1[[#This Row],[KM Rodado]]*1.1, Tabela1[[#This Row],[KM Rodado]]*1.23) -> 106.7 | W98: =IFERROR(SUBSTITUTE(Tabela1[[#This Row],[Pedágio]],".",",",1)*1,0) -> 0 | X98: =IFERROR(SUBSTITUTE(Tabela1[[#This Row],[Estacionamento]],".",",",1)*1,0) -> 0 | Y98: =IFERROR(SUBSTITUTE(Tabela1[[#This Row],[Despesas Diversas (Jantar em viagem, Impressões, Etc)]],".",",",1)*1,0) -> 0 | Z98: =IFERROR(SUBSTITUTE(Tabela1[[#This Row],[Hospedagem]],".",",",1)*1,0) -> 0 | AA98: =IF(DAY(Tabela1[[#This Row],[Informe a data]])<=15,"1ª Quinzena","2ª Quinzena") -> 1ª Quinzena | AB98: =UPPER(TEXT(Tabela1[[#This Row],[Informe a data]],"mmmm")) -> FEVEREIRO | AC98: =_xlfn.CONCAT(Tabela1[[#This Row],[Selecione o Usuário]]," - ",TEXT(Tabela1[[#This Row],[Informe a data]],"dd-mm-aa")) -> #NAME?
A99: 46067.458 | B99: sabrina.pires@mazzini.com.br | C99: SABRINA DOS SANTOS PIRES | D99: Azc9e32 | E99: 46066 | F99: 174413 | G99: https://drive.google.com/open?id=1Xdyi31juGN1FUxaYchsMhuYc1pOsbANN | H99: 174463 | I99: https://drive.google.com/open?id=1zB2x1NdqVbLMHFN5pkUB15_Rvif0xdvG | J99: Komprao 90 Komprao 91 | L99: Não | U99: =(Tabela1[[#This Row],[Informe o KM final do dia]]-Tabela1[[#This Row],[Informe o KM inicial do dia]])-Tabela1[[#This Row],[Caso tenha rodado particular alguma parte do trajeto, informe o total de KM a ser deduzido.]] -> 50 | V99: =IF(Tabela1[[#This Row],[Informe a data]]<DATE(2026,3,16), Tabela1[[#This Row],[KM Rodado]]*1.1, Tabela1[[#This Row],[KM Rodado]]*1.23) -> 55 | W99: =IFERROR(SUBSTITUTE(Tabela1[[#This Row],[Pedágio]],".",",",1)*1,0) -> 0 | X99: =IFERROR(SUBSTITUTE(Tabela1[[#This Row],[Estacionamento]],".",",",1)*1,0) -> 0 | Y99: =IFERROR(SUBSTITUTE(Tabela1[[#This Row],[Despesas Diversas (Jantar em viagem, Impressões, Etc)]],".",",",1)*1,0) -> 0 | Z99: =IFERROR(SUBSTITUTE(Tabela1[[#This Row],[Hospedagem]],".",",",1)*1,0) -> 0 | AA99: =IF(DAY(Tabela1[[#This Row],[Informe a data]])<=15,"1ª Quinzena","2ª Quinzena") -> 1ª Quinzena | AB99: =UPPER(TEXT(Tabela1[[#This Row],[Informe a data]],"mmmm")) -> FEVEREIRO | AC99: =_xlfn.CONCAT(Tabela1[[#This Row],[Selecione o Usuário]]," - ",TEXT(Tabela1[[#This Row],[Informe a data]],"dd-mm-aa")) -> #NAME?
A100: 46069.734 | B100: camila.althoff@mazzini.com.br | C100: CAMILA CRISTINE ALTHOFF | D100: Mlz4j72 | E100: 46067 | F100: 188178 | G100: https://drive.google.com/open?id=12_rbVetfYmPi6BVjzrId8Y9Fda6e1s7c | H100: 188220 | I100: https://drive.google.com/open?id=1JPAfzw6dq2nk8cLG8yNQfyZ2OOc-EPOb | J100: Fort kobrasol | L100: Não | U100: =(Tabela1[[#This Row],[Informe o KM final do dia]]-Tabela1[[#This Row],[Informe o KM inicial do dia]])-Tabela1[[#This Row],[Caso tenha rodado particular alguma parte do trajeto, informe o total de KM a ser deduzido.]] -> 42 | V100: =IF(Tabela1[[#This Row],[Informe a data]]<DATE(2026,3,16), Tabela1[[#This Row],[KM Rodado]]*1.1, Tabela1[[#This Row],[KM Rodado]]*1.23) -> 46.2 | W100: =IFERROR(SUBSTITUTE(Tabela1[[#This Row],[Pedágio]],".",",",1)*1,0) -> 0 | X100: =IFERROR(SUBSTITUTE(Tabela1[[#This Row],[Estacionamento]],".",",",1)*1,0) -> 0 | Y100: =IFERROR(SUBSTITUTE(Tabela1[[#This Row],[Despesas Diversas (Jantar em viagem, Impressões, Etc)]],".",",",1)*1,0) -> 0 | Z100: =IFERROR(SUBSTITUTE(Tabela1[[#This Row],[Hospedagem]],".",",",1)*1,0) -> 0 | AA100: =IF(DAY(Tabela1[[#This Row],[Informe a data]])<=15,"1ª Quinzena","2ª Quinzena") -> 1ª Quinzena | AB100: =UPPER(TEXT(Tabela1[[#This Row],[Informe a data]],"mmmm")) -> FEVEREIRO | AC100: =_xlfn.CONCAT(Tabela1[[#This Row],[Selecione o Usuário]]," - ",TEXT(Tabela1[[#This Row],[Informe a data]],"dd-mm-aa")) -> #NAME?
A101: 46069.701 | B101: oliiveiiraa7@gmail.com | C101: GUSTAVO MATHEUS DE OLIVEIRA | D101: EUF3090 | E101: 46067 | F101: 162415 | H101: 162741 | J101: Deslocamento para Florianópolis | L101: Não | U101: =(Tabela1[[#This Row],[Informe o KM final do dia]]-Tabela1[[#This Row],[Informe o KM inicial do dia]])-Tabela1[[#This Row],[Caso tenha rodado particular alguma parte do trajeto, informe o total de KM a ser deduzido.]] -> 326 | V101: =IF(Tabela1[[#This Row],[Informe a data]]<DATE(2026,3,16), Tabela1[[#This Row],[KM Rodado]]*1.1, Tabela1[[#This Row],[KM Rodado]]*1.23) -> 358.6 | W101: =IFERROR(SUBSTITUTE(Tabela1[[#This Row],[Pedágio]],".",",",1)*1,0) -> 0 | X101: =IFERROR(SUBSTITUTE(Tabela1[[#This Row],[Estacionamento]],".",",",1)*1,0) -> 0 | Y101: =IFERROR(SUBSTITUTE(Tabela1[[#This Row],[Despesas Diversas (Jantar em viagem, Impressões, Etc)]],".",",",1)*1,0) -> 0 | Z101: =IFERROR(SUBSTITUTE(Tabela1[[#This Row],[Hospedagem]],".",",",1)*1,0) -> 0 | AA101: =IF(DAY(Tabela1[[#This Row],[Informe a data]])<=15,"1ª Quinzena","2ª Quinzena") -> 1ª Quinzena | AB101: =UPPER(TEXT(Tabela1[[#This Row],[Informe a data]],"mmmm")) -> FEVEREIRO | AC101: =_xlfn.CONCAT(Tabela1[[#This Row],[Selecione o Usuário]]," - ",TEXT(Tabela1[[#This Row],[Informe a data]],"dd-mm-aa")) -> #NAME?
...

Sheet Consolidado gerencial
A3: Mês | B3: SM | C3: Valor KM | D3: Pedágio $ | E3: Estacionamento $ | F3: Diversas $ | G3: Hospedagem $ | H3: TT Gasto
A4: JANEIRO | B4: ANDERSON MICHALSKI FERREIRA | C4: 0 | D4: 0 | E4: 0 | F4: 179.49 | G4: 0 | H4: 179.49
A5: JANEIRO | B5: Desyree Yasmin Gaulke Klebber | C5: 586.3 | D5: 0 | E5: 0 | F5: 16.2 | G5: 0 | H5: 602.5
A6: JANEIRO | B6: CAMILA CRISTINE ALTHOFF | C6: 2167 | D6: 43.8 | E6: 58 | F6: 71 | G6: 413.45 | H6: 2753.25
A7: JANEIRO | B7: GUSTAVO MATHEUS DE OLIVEIRA | C7: 1635.7 | D7: 0 | E7: 0 | F7: 0 | G7: 219.94 | H7: 1855.64
A8: JANEIRO | B8: SUELEN DOS SANTOS AZEVEDO | C8: 471.9 | D8: 0 | E8: 0 | F8: 0 | G8: 0 | H8: 471.9
A9: JANEIRO | B9: RICARDO ALEXANDRE LOMBARDI | C9: 1423.4 | D9: 0 | E9: 0 | F9: 0 | G9: 0 | H9: 1423.4
A10: JANEIRO | B10: VINICIUS ROBERTO KERBER | C10: 129.8 | D10: 0 | E10: 0 | F10: 0 | G10: 0 | H10: 129.8
A11: JANEIRO | B11: SABRINA DOS SANTOS PIRES | C11: 1108.8 | D11: 0 | E11: 0 | F11: 0 | G11: 0 | H11: 1108.8
A12: JANEIRO | B12: MATHEUS DA SILVA MORAES | C12: 1080.2 | D12: 0 | E12: 0 | F12: 9 | G12: 0 | H12: 1089.2
A13: JANEIRO Total | C13: 8603.1 | D13: 43.8 | E13: 58 | F13: 275.69 | G13: 633.39 | H13: 9613.98
A14: FEVEREIRO | B14: BRENON LUCAS ALVES DE SOUZA | C14: 264 | D14: 0 | E14: 0 | F14: 0 | G14: 0 | H14: 264
A15: FEVEREIRO | B15: CAMILA CRISTINE ALTHOFF | C15: 2333.1 | D15: 78 | E15: 75 | F15: 202.56 | G15: 537.54 | H15: 3226.2
A16: FEVEREIRO | B16: GUSTAVO MATHEUS DE OLIVEIRA | C16: 1774.3 | D16: 0 | E16: 0 | F16: 0 | G16: 0 | H16: 1774.3
A17: FEVEREIRO | B17: RICARDO ALEXANDRE LOMBARDI | C17: 834.9 | D17: 0 | E17: 0 | F17: 0 | G17: 0 | H17: 834.9
A18: FEVEREIRO | B18: SABRINA DOS SANTOS PIRES | C18: 2047.1 | D18: 0 | E18: 0 | F18: 0 | G18: 0 | H18: 2047.1
A19: FEVEREIRO | B19: MATHEUS DA SILVA MORAES | C19: 1449.8 | D19: 0 | E19: 0 | F19: 17.5 | G19: 0 | H19: 1467.3
A20: FEVEREIRO | B20: Aline Isac Moreira | C20: 1111 | D20: 0 | E20: 0 | F20: 0 | G20: 0 | H20: 1111
A21: FEVEREIRO | B21: CARLOS PROENÇA | C21: 216.7 | D21: 5.7 | E21: 0 | F21: 0 | G21: 0 | H21: 222.4
A22: FEVEREIRO | B22: JOÃO MARTINS NETO | C22: 799.7 | D22: 0 | E22: 0 | F22: 0 | G22: 0 | H22: 799.7
A23: FEVEREIRO Total | C23: 10830.6 | D23: 83.7 | E23: 75 | F23: 220.06 | G23: 537.54 | H23: 11746.9
A24: MARÇO | B24: CAMILA CRISTINE ALTHOFF | C24: 1773.15 | D24: 50.4 | E24: 85 | F24: 48.72 | G24: 0 | H24: 1957.27
A25: MARÇO | B25: GUSTAVO MATHEUS DE OLIVEIRA | C25: 1407.13 | D25: 0 | E25: 0 | F25: 0 | G25: 0 | H25: 1407.13
A26: MARÇO | B26: RICARDO ALEXANDRE LOMBARDI | C26: 1549.24 | D26: 0 | E26: 0 | F26: 0 | G26: 0 | H26: 1549.24
A27: MARÇO | B27: SABRINA DOS SANTOS PIRES | C27: 1510.92 | D27: 0 | E27: 25 | F27: 0 | G27: 0 | H27: 1535.92
A28: MARÇO | B28: MATHEUS DA SILVA MORAES | C28: 1670.27 | D28: 0 | E28: 8 | F28: 31.45 | G28: 0 | H28: 1709.72
A29: MARÇO | B29: Aline Isac Moreira | C29: 1127.7 | D29: 0 | E29: 0 | F29: 0 | G29: 0 | H29: 1127.7
A30: MARÇO | B30: CARLOS PROENÇA | C30: 1448.84 | D30: 47.6 | E30: 20 | F30: 0 | G30: 0 | H30: 1516.44
A31: MARÇO | B31: JOÃO MARTINS NETO | C31: 1358.59 | D31: 0 | E31: 0 | F31: 240.7 | G31: 0 | H31: 1599.29
A32: MARÇO Total | C32: 11845.84 | D32: 98 | E32: 138 | F32: 320.87 | G32: 0 | H32: 12402.71
A33: ABRIL | B33: CAMILA CRISTINE ALTHOFF | C33: 1741.68 | D33: 43.8 | E33: 58 | F33: 110.83 | G33: 0 | H33: 1954.31
A34: ABRIL | B34: GUSTAVO MATHEUS DE OLIVEIRA | C34: 1324.71 | D34: 0 | E34: 0 | F34: 0 | G34: 0 | H34: 1324.71
A35: ABRIL | B35: RICARDO ALEXANDRE LOMBARDI | C35: 1332.09 | D35: 0 | E35: 0 | F35: 0 | G35: 0 | H35: 1332.09
A36: ABRIL | B36: SABRINA DOS SANTOS PIRES | C36: 568.26 | D36: 0 | E36: 0 | F36: 0 | G36: 0 | H36: 568.26
A37: ABRIL | B37: MATHEUS DA SILVA MORAES | C37: 1201.71 | D37: 0 | E37: 0 | F37: 20.75 | G37: 0 | H37: 1222.46
A38: ABRIL | B38: Aline Isac Moreira | C38: 630.99 | D38: 0 | E38: 0 | F38: 0 | G38: 0 | H38: 630.99
A39: ABRIL | B39: CARLOS PROENÇA | C39: 1185.72 | D39: 0 | E39: 0 | F39: 0 | G39: 0 | H39: 1185.72
A40: ABRIL | B40: JOÃO MARTINS NETO | C40: 1308.72 | D40: 0 | E40: 0 | F40: 40 | G40: 0 | H40: 1348.72
A41: ABRIL Total | C41: 9293.88 | D41: 43.8 | E41: 58 | F41: 171.58 | G41: 0 | H41: 9567.26
A42: MAIO | B42: CAMILA CRISTINE ALTHOFF | C42: 692.49 | D42: 0 | E42: 40 | F42: 0 | G42: 0 | H42: 732.49
A43: MAIO | B43: GUSTAVO MATHEUS DE OLIVEIRA | C43: 1356.69 | D43: 0 | E43: 0 | F43: 0 | G43: 0 | H43: 1356.69
A44: MAIO | B44: RICARDO ALEXANDRE LOMBARDI | C44: 1350.54 | D44: 0 | E44: 0 | F44: 0 | G44: 0 | H44: 1350.54
A45: MAIO | B45: SABRINA DOS SANTOS PIRES | C45: 790.89 | D45: 0 | E45: 18 | F45: 0 | G45: 0 | H45: 808.89
A46: MAIO | B46: MATHEUS DA SILVA MORAES | C46: 1407.12 | D46: 0 | E46: 0 | F46: 21.7 | G46: 0 | H46: 1428.82
A47: MAIO | B47: Aline Isac Moreira | C47: 1241.07 | D47: 0 | E47: 0 | F47: 0 | G47: 0 | H47: 1241.07
A48: MAIO | B48: CARLOS PROENÇA | C48: 731.85 | D48: 23.4 | E48: 0 | F48: 0 | G48: 0 | H48: 755.25
A49: MAIO | B49: JOÃO MARTINS NETO | C49: 1227.54 | D49: 0 | E49: 0 | F49: 0 | G49: 0 | H49: 1227.54
A50: MAIO Total | C50: 8798.19 | D50: 23.4 | E50: 58 | F50: 21.7 | G50: 0 | H50: 8901.29
A51: JUNHO | B51: BRENON LUCAS ALVES DE SOUZA | C51: 448.95 | D51: 0 | E51: 0 | F51: 0 | G51: 0 | H51: 448.95
A52: JUNHO | B52: CAMILA CRISTINE ALTHOFF | C52: 1860.99 | D52: 46.8 | E52: 0 | F52: 89.66 | G52: 0 | H52: 1997.45
A53: JUNHO | B53: GUSTAVO MATHEUS DE OLIVEIRA | C53: 1515.36 | D53: 0 | E53: 0 | F53: 0 | G53: 0 | H53: 1515.36
A54: JUNHO | B54: RICARDO ALEXANDRE LOMBARDI | C54: 1483.38 | D54: 0 | E54: 0 | F54: 0 | G54: 0 | H54: 1483.38
A55: JUNHO | B55: SABRINA DOS SANTOS PIRES | C55: 805.65 | D55: 0 | E55: 0 | F55: 0 | G55: 0 | H55: 805.65
A56: JUNHO | B56: MATHEUS DA SILVA MORAES | C56: 1169.73 | D56: 0 | E56: 15 | F56: 1.5 | G56: 0 | H56: 1186.23
A57: JUNHO | B57: Aline Isac Moreira | C57: 498.15 | D57: 0 | E57: 0 | F57: 0 | G57: 0 | H57: 498.15
A58: JUNHO | B58: CARLOS PROENÇA | C58: 511.68 | D58: 20.8 | E58: 0 | F58: 0 | G58: 0 | H58: 532.48
A59: JUNHO | B59: JOÃO MARTINS NETO | C59: 1164.81 | D59: 0 | E59: 0 | F59: 0 | G59: 0 | H59: 1164.81
A60: JUNHO Total | C60: 9458.7 | D60: 67.6 | E60: 15 | F60: 91.16 | G60: 0 | H60: 9632.46
A61: JULHO | B61: Geovana Duarte Farias | C61: 943.41 | D61: 0 | E61: 79 | F61: 26.85 | G61: 0 | H61: 1049.26
A62: JULHO | B62: BRENON LUCAS ALVES DE SOUZA | C62: 226.32 | D62: 0 | E62: 0 | F62: 0 | G62: 0 | H62: 226.32
A63: JULHO | B63: CAMILA CRISTINE ALTHOFF | C63: 1702.32 | D63: 29.1 | E63: 94 | F63: 250.6 | G63: 0 | H63: 2076.02
A64: JULHO | B64: GUSTAVO MATHEUS DE OLIVEIRA | C64: 1115.61 | D64: 0 | E64: 0 | F64: 0 | G64: 0 | H64: 1115.61
A65: JULHO | B65: RICARDO ALEXANDRE LOMBARDI | C65: 1536.27 | D65: 0 | E65: 0 | F65: 0 | G65: 0 | H65: 1536.27
A66: JULHO | B66: MATHEUS DA SILVA MORAES | C66: 1119.3 | D66: 0 | E66: 0 | F66: 66.2 | G66: 0 | H66: 1185.5
A67: JULHO | B67: CARLOS PROENÇA | C67: 999.99 | D67: 31.2 | E67: 0 | F67: 0 | G67: 0 | H67: 1031.19
A68: JULHO | B68: JOÃO MARTINS NETO | C68: 1511.67 | D68: 11.4 | E68: 18 | F68: 0 | G68: 0 | H68: 1541.07
A69: JULHO | B69: THAYS APARECIDA CARVALHO | C69: 1170.96 | D69: 0 | E69: 0 | F69: 0 | G69: 0 | H69: 1170.96
A70: JULHO Total | C70: 10325.85 | D70: 71.7 | E70: 191 | F70: 343.65 | G70: 0 | H70: 10932.2
A71: AGOSTO | B71: Geovana Duarte Farias | C71: 1040.58 | D71: 0 | E71: 0 | F71: 0 | G71: 0 | H71: 1040.58
A72: AGOSTO | B72: CAMILA CRISTINE ALTHOFF | C72: 2169.72 | D72: 43.4 | E72: 20 | F72: 164.4 | G72: 0 | H72: 2397.52
A73: AGOSTO | B73: GUSTAVO MATHEUS DE OLIVEIRA | C73: 2129.13 | D73: 0 | E73: 0 | F73: 0 | G73: 0 | H73: 2129.13
A74: AGOSTO | B74: RICARDO ALEXANDRE LOMBARDI | C74: 1346.85 | D74: 0 | E74: 0 | F74: 0 | G74: 0 | H74: 1346.85
A75: AGOSTO | B75: MATHEUS DA SILVA MORAES | C75: 305.04 | D75: 0 | E75: 0 | F75: 0 | G75: 0 | H75: 305.04
A76: AGOSTO | B76: CARLOS PROENÇA | C76: 940.95 | D76: 31.2 | E76: 0 | F76: 0 | G76: 0 | H76: 972.15
A77: AGOSTO | B77: JOÃO MARTINS NETO | C77: 1135.29 | D77: 11.4 | E77: 0 | F77: 96.6 | G77: 0 | H77: 1243.29
A78: AGOSTO | B78: THAYS APARECIDA CARVALHO | C78: 1190.64 | D78: 0 | E78: 0 | F78: 0 | G78: 0 | H78: 1190.64
A79: AGOSTO Total | C79: 10258.2 | D79: 86 | E79: 20 | F79: 261 | G79: 0 | H79: 10625.2
A80: SETEMBRO | B80: Geovana Duarte Farias | C80: 763.83 | D80: 5.7 | E80: 0 | F80: 0 | G80: 0 | H80: 769.53
A81: SETEMBRO | B81: CAMILA CRISTINE ALTHOFF | C81: 999.99 | D81: 28.5 | E81: 0 | F81: 43 | G81: 0 | H81: 1071.49
A82: SETEMBRO | B82: GUSTAVO MATHEUS DE OLIVEIRA | C82: 313.65 | D82: 0 | E82: 0 | F82: 0 | G82: 0 | H82: 313.65
A83: SETEMBRO | B83: RICARDO ALEXANDRE LOMBARDI | C83: 321.03 | D83: 0 | E83: 0 | F83: 0 | G83: 0 | H83: 321.03
A84: SETEMBRO | B84: MATHEUS DA SILVA MORAES | C84: 687.57 | D84: 0 | E84: 0 | F84: 0 | G84: 0 | H84: 687.57
A85: SETEMBRO | B85: CARLOS PROENÇA | C85: 977.85 | D85: 33.8 | E85: 0 | F85: 0 | G85: 0 | H85: 1011.65
A86: SETEMBRO | B86: JOÃO MARTINS NETO | C86: 626.07 | D86: 11.4 | E86: 0 | F86: 0 | G86: 0 | H86: 637.47
A87: SETEMBRO | B87: THAYS APARECIDA CARVALHO | C87: 755.22 | D87: 0 | E87: 0 | F87: 0 | G87: 0 | H87: 755.22
A88: SETEMBRO Total | C88: 5445.21 | D88: 79.4 | E88: 0 | F88: 43 | G88: 0 | H88: 5567.61
A89: Total Geral | C89: 84859.57 | D89: 597.4 | E89: 613 | F89: 1748.71 | G89: 1170.93 | H89: 88989.61

Sheet Controle mensal
B2: Meu orçamento
B4: Nome | C4: JANEIRO | D4: FEVEREIRO | E4: MARÇO | F4: ABRIL | G4: MAIO | H4: JUNHO | I4: JULHO | J4: AGOSTO | K4: SETEMBRO | L4: OUTUBRO | M4: NOVEMBRO | N4: DEZEMBRO
B5: CAMILA CRISTINE ALTHOFF | C5: 1250 | D5: 1500 | E5: 1500 | F5: 1200 | G5: 600 | H5: 1200 | I5: 1200 | J5: 1200 | K5: 1200 | Q5: 1500 | R5: Valor máximo
B6: GUSTAVO MATHEUS DE OLIVEIRA | C6: 1500 | D6: 1500 | E6: 1500 | F6: 1200 | G6: 1200 | H6: 1200 | I6: 1200 | J6: 1200 | K6: 1200 | Q6: 15 | R6: Dias
B7: MATHEUS DA SILVA MORAES | C7: 750 | D7: 1500 | E7: 1500 | F7: 1200 | G7: 1200 | H7: 1200 | I7: 1200 | J7: 1200 | K7: 440 | Q7: =(Q5/30)*Q6 -> 750 | R7: TT planejado
B8: THAYS APARECIDA CARVALHO | I8: 1200 | J8: 1200 | K8: 1200
B9: RICARDO ALEXANDRE LOMBARDI | C9: 1500 | D9: 1500 | E9: 1500 | F9: 1200 | G9: 1200 | H9: 1200 | I9: 1200 | J9: 1200 | K9: 1200
B10: CARLOS PROENÇA | D10: 1125 | E10: 1500 | F10: 1200 | G10: 1200 | H10: 1200 | I10: 1200 | J10: 1200 | K10: 1200
B11: JOÃO MARTINS NETO | D11: 1285 | E11: 1500 | F11: 1200 | G11: 1200 | H11: 1200 | I11: 1200 | J11: 1200 | K11: 1200
B12: GEOVANA DUARTE FARIAS | H12: 720 | I12: 1200 | J12: 1200 | K12: 1200
B13: SAIDDA KAULE ABDALA | C13: 0 | D13: 0 | E13: 0
B14: SABRINA DOS SANTOS PIRES | C14: 1500 | D14: 1500 | E14: 1500 | F14: 1200 | G14: 1200 | H14: 480
B15: Aline Isac Moreira | D15: 1400 | E15: 1500 | F15: 1200 | G15: 1200 | H15: 440
B16: SUELEN DOS SANTOS AZEVEDO | C16: 1350 | D16: 0
B17: VINICIUS ROBERTO KERBER | C17: 400 | D17: 0
B22: TT ORÇAMENTO | C22: =SUM(Tabela44[JANEIRO]) -> 8250 | D22: =SUM(Tabela44[FEVEREIRO]) -> 11310 | E22: =SUM(Tabela44[MARÇO]) -> 12000 | F22: =SUM(Tabela44[ABRIL]) -> 9600 | G22: =SUM(Tabela44[MAIO]) -> 9000 | H22: =SUM(Tabela44[JUNHO]) -> 8840 | I22: =SUM(Tabela44[JULHO]) -> 9600 | J22: =SUM(Tabela44[AGOSTO]) -> 9600 | K22: =SUM(Tabela44[SETEMBRO]) -> 8840 | L22: =SUM(Tabela44[OUTUBRO]) -> 0 | M22: =SUM(Tabela44[NOVEMBRO]) -> 0 | N22: =SUM(Tabela44[DEZEMBRO]) -> 0
B24: Realizado
B26: Valor disponivel | C26: =Tabela44[[#Totals],[JANEIRO]] -> 8250 | D26: =Tabela44[[#Totals],[FEVEREIRO]] -> 11310 | E26: =Tabela44[[#Totals],[MARÇO]] -> 12000 | F26: =Tabela44[[#Totals],[ABRIL]] -> 9600 | G26: =Tabela44[[#Totals],[MAIO]] -> 9000 | H26: =Tabela44[[#Totals],[JUNHO]] -> 8840 | I26: =Tabela44[[#Totals],[JULHO]] -> 9600 | J26: =Tabela44[[#Totals],[AGOSTO]] -> 9600 | K26: =Tabela44[[#Totals],[SETEMBRO]] -> 8840 | L26: =Tabela44[[#Totals],[OUTUBRO]] -> 0 | M26: =Tabela44[[#Totals],[NOVEMBRO]] -> 0
B27: Nome | C27: JANEIRO | D27: FEVEREIRO | E27: MARÇO | F27: ABRIL | G27: MAIO | H27: JUNHO | I27: JULHO | J27: AGOSTO | K27: SETEMBRO | L27: OUTUBRO | M27: NOVEMBRO | N27: DEZEMBRO
B28: CAMILA CRISTINE ALTHOFF | C28: =SUMIFS('Consolidado gerencial'!$H:$H,'Consolidado gerencial'!$B:$B,$B28,'Consolidado gerencial'!$A:$A,C$27) -> 2753.25 | D28: =SUMIFS('Consolidado gerencial'!$H:$H,'Consolidado gerencial'!$B:$B,$B28,'Consolidado gerencial'!$A:$A,D$27) -> 3226.2 | E28: =SUMIFS('Consolidado gerencial'!$H:$H,'Consolidado gerencial'!$B:$B,$B28,'Consolidado gerencial'!$A:$A,E$27) -> 1957.27 | F28: =SUMIFS('Consolidado gerencial'!$H:$H,'Consolidado gerencial'!$B:$B,$B28,'Consolidado gerencial'!$A:$A,F$27) -> 1954.31 | G28: =SUMIFS('Consolidado gerencial'!$H:$H,'Consolidado gerencial'!$B:$B,$B28,'Consolidado gerencial'!$A:$A,G$27) -> 732.49 | H28: =SUMIFS('Consolidado gerencial'!$H:$H,'Consolidado gerencial'!$B:$B,$B28,'Consolidado gerencial'!$A:$A,H$27) -> 1997.45 | I28: =SUMIFS('Consolidado gerencial'!$H:$H,'Consolidado gerencial'!$B:$B,$B28,'Consolidado gerencial'!$A:$A,I$27) -> 2076.02 | J28: =SUMIFS('Consolidado gerencial'!$H:$H,'Consolidado gerencial'!$B:$B,$B28,'Consolidado gerencial'!$A:$A,J$27) -> 2397.52 | ... N28: =SUMIFS('Consolidado gerencial'!$H:$H,'Consolidado gerencial'!$B:$B,$B28,'Consolidado gerencial'!$A:$A,N$27) -> 0
B29: GUSTAVO MATHEUS DE OLIVEIRA | C29: =SUMIFS('Consolidado gerencial'!$H:$H,'Consolidado gerencial'!$B:$B,$B29,'Consolidado gerencial'!$A:$A,C$27) -> 1855.64 | D29: =SUMIFS('Consolidado gerencial'!$H:$H,'Consolidado gerencial'!$B:$B,$B29,'Consolidado gerencial'!$A:$A,D$27) -> 1774.3 | E29: =SUMIFS('Consolidado gerencial'!$H:$H,'Consolidado gerencial'!$B:$B,$B29,'Consolidado gerencial'!$A:$A,E$27) -> 1407.13 | F29: =SUMIFS('Consolidado gerencial'!$H:$H,'Consolidado gerencial'!$B:$B,$B29,'Consolidado gerencial'!$A:$A,F$27) -> 1324.71 | G29: =SUMIFS('Consolidado gerencial'!$H:$H,'Consolidado gerencial'!$B:$B,$B29,'Consolidado gerencial'!$A:$A,G$27) -> 1356.69 | H29: =SUMIFS('Consolidado gerencial'!$H:$H,'Consolidado gerencial'!$B:$B,$B29,'Consolidado gerencial'!$A:$A,H$27) -> 1515.36 | I29: =SUMIFS('Consolidado gerencial'!$H:$H,'Consolidado gerencial'!$B:$B,$B29,'Consolidado gerencial'!$A:$A,I$27) -> 1115.61 | J29: =SUMIFS('Consolidado gerencial'!$H:$H,'Consolidado gerencial'!$B:$B,$B29,'Consolidado gerencial'!$A:$A,J$27) -> 2129.13 | ... N29: =SUMIFS('Consolidado gerencial'!$H:$H,'Consolidado gerencial'!$B:$B,$B29,'Consolidado gerencial'!$A:$A,N$27) -> 0
B30: MATHEUS DA SILVA MORAES | C30: =SUMIFS('Consolidado gerencial'!$H:$H,'Consolidado gerencial'!$B:$B,$B30,'Consolidado gerencial'!$A:$A,C$27) -> 1089.2 | D30: =SUMIFS('Consolidado gerencial'!$H:$H,'Consolidado gerencial'!$B:$B,$B30,'Consolidado gerencial'!$A:$A,D$27) -> 1467.3 | E30: =SUMIFS('Consolidado gerencial'!$H:$H,'Consolidado gerencial'!$B:$B,$B30,'Consolidado gerencial'!$A:$A,E$27) -> 1709.72 | F30: =SUMIFS('Consolidado gerencial'!$H:$H,'Consolidado gerencial'!$B:$B,$B30,'Consolidado gerencial'!$A:$A,F$27) -> 1222.46 | G30: =SUMIFS('Consolidado gerencial'!$H:$H,'Consolidado gerencial'!$B:$B,$B30,'Consolidado gerencial'!$A:$A,G$27) -> 1428.82 | H30: =SUMIFS('Consolidado gerencial'!$H:$H,'Consolidado gerencial'!$B:$B,$B30,'Consolidado gerencial'!$A:$A,H$27) -> 1186.23 | I30: =SUMIFS('Consolidado gerencial'!$H:$H,'Consolidado gerencial'!$B:$B,$B30,'Consolidado gerencial'!$A:$A,I$27) -> 1185.5 | J30: =SUMIFS('Consolidado gerencial'!$H:$H,'Consolidado gerencial'!$B:$B,$B30,'Consolidado gerencial'!$A:$A,J$27) -> 305.04 | ... N30: =SUMIFS('Consolidado gerencial'!$H:$H,'Consolidado gerencial'!$B:$B,$B30,'Consolidado gerencial'!$A:$A,N$27) -> 0
B31: RICARDO ALEXANDRE LOMBARDI | C31: =SUMIFS('Consolidado gerencial'!$H:$H,'Consolidado gerencial'!$B:$B,$B31,'Consolidado gerencial'!$A:$A,C$27) -> 1423.4 | D31: =SUMIFS('Consolidado gerencial'!$H:$H,'Consolidado gerencial'!$B:$B,$B31,'Consolidado gerencial'!$A:$A,D$27) -> 834.9 | E31: =SUMIFS('Consolidado gerencial'!$H:$H,'Consolidado gerencial'!$B:$B,$B31,'Consolidado gerencial'!$A:$A,E$27) -> 1549.24 | F31: =SUMIFS('Consolidado gerencial'!$H:$H,'Consolidado gerencial'!$B:$B,$B31,'Consolidado gerencial'!$A:$A,F$27) -> 1332.09 | G31: =SUMIFS('Consolidado gerencial'!$H:$H,'Consolidado gerencial'!$B:$B,$B31,'Consolidado gerencial'!$A:$A,G$27) -> 1350.54 | H31: =SUMIFS('Consolidado gerencial'!$H:$H,'Consolidado gerencial'!$B:$B,$B31,'Consolidado gerencial'!$A:$A,H$27) -> 1483.38 | I31: =SUMIFS('Consolidado gerencial'!$H:$H,'Consolidado gerencial'!$B:$B,$B31,'Consolidado gerencial'!$A:$A,I$27) -> 1536.27 | J31: =SUMIFS('Consolidado gerencial'!$H:$H,'Consolidado gerencial'!$B:$B,$B31,'Consolidado gerencial'!$A:$A,J$27) -> 1346.85 | ... N31: =SUMIFS('Consolidado gerencial'!$H:$H,'Consolidado gerencial'!$B:$B,$B31,'Consolidado gerencial'!$A:$A,N$27) -> 0
B32: SABRINA DOS SANTOS PIRES | C32: =SUMIFS('Consolidado gerencial'!$H:$H,'Consolidado gerencial'!$B:$B,$B32,'Consolidado gerencial'!$A:$A,C$27) -> 1108.8 | D32: =SUMIFS('Consolidado gerencial'!$H:$H,'Consolidado gerencial'!$B:$B,$B32,'Consolidado gerencial'!$A:$A,D$27) -> 2047.1 | E32: =SUMIFS('Consolidado gerencial'!$H:$H,'Consolidado gerencial'!$B:$B,$B32,'Consolidado gerencial'!$A:$A,E$27) -> 1535.92 | F32: =SUMIFS('Consolidado gerencial'!$H:$H,'Consolidado gerencial'!$B:$B,$B32,'Consolidado gerencial'!$A:$A,F$27) -> 568.26 | G32: =SUMIFS('Consolidado gerencial'!$H:$H,'Consolidado gerencial'!$B:$B,$B32,'Consolidado gerencial'!$A:$A,G$27) -> 808.89 | H32: =SUMIFS('Consolidado gerencial'!$H:$H,'Consolidado gerencial'!$B:$B,$B32,'Consolidado gerencial'!$A:$A,H$27) -> 805.65 | I32: =SUMIFS('Consolidado gerencial'!$H:$H,'Consolidado gerencial'!$B:$B,$B32,'Consolidado gerencial'!$A:$A,I$27) -> 0 | J32: =SUMIFS('Consolidado gerencial'!$H:$H,'Consolidado gerencial'!$B:$B,$B32,'Consolidado gerencial'!$A:$A,J$27) -> 0 | ... N32: =SUMIFS('Consolidado gerencial'!$H:$H,'Consolidado gerencial'!$B:$B,$B32,'Consolidado gerencial'!$A:$A,N$27) -> 0
B33: Aline Isac Moreira | C33: =SUMIFS('Consolidado gerencial'!$H:$H,'Consolidado gerencial'!$B:$B,$B33,'Consolidado gerencial'!$A:$A,C$27) -> 0 | D33: =SUMIFS('Consolidado gerencial'!$H:$H,'Consolidado gerencial'!$B:$B,$B33,'Consolidado gerencial'!$A:$A,D$27) -> 1111 | E33: =SUMIFS('Consolidado gerencial'!$H:$H,'Consolidado gerencial'!$B:$B,$B33,'Consolidado gerencial'!$A:$A,E$27) -> 1127.7 | F33: =SUMIFS('Consolidado gerencial'!$H:$H,'Consolidado gerencial'!$B:$B,$B33,'Consolidado gerencial'!$A:$A,F$27) -> 630.99 | G33: =SUMIFS('Consolidado gerencial'!$H:$H,'Consolidado gerencial'!$B:$B,$B33,'Consolidado gerencial'!$A:$A,G$27) -> 1241.07 | H33: =SUMIFS('Consolidado gerencial'!$H:$H,'Consolidado gerencial'!$B:$B,$B33,'Consolidado gerencial'!$A:$A,H$27) -> 498.15 | I33: =SUMIFS('Consolidado gerencial'!$H:$H,'Consolidado gerencial'!$B:$B,$B33,'Consolidado gerencial'!$A:$A,I$27) -> 0 | J33: =SUMIFS('Consolidado gerencial'!$H:$H,'Consolidado gerencial'!$B:$B,$B33,'Consolidado gerencial'!$A:$A,J$27) -> 0 | ... N33: =SUMIFS('Consolidado gerencial'!$H:$H,'Consolidado gerencial'!$B:$B,$B33,'Consolidado gerencial'!$A:$A,N$27) -> 0
B34: CARLOS PROENÇA | C34: =SUMIFS('Consolidado gerencial'!$H:$H,'Consolidado gerencial'!$B:$B,$B34,'Consolidado gerencial'!$A:$A,C$27) -> 0 | D34: =SUMIFS('Consolidado gerencial'!$H:$H,'Consolidado gerencial'!$B:$B,$B34,'Consolidado gerencial'!$A:$A,D$27) -> 222.4 | E34: =SUMIFS('Consolidado gerencial'!$H:$H,'Consolidado gerencial'!$B:$B,$B34,'Consolidado gerencial'!$A:$A,E$27) -> 1516.44 | F34: =SUMIFS('Consolidado gerencial'!$H:$H,'Consolidado gerencial'!$B:$B,$B34,'Consolidado gerencial'!$A:$A,F$27) -> 1185.72 | G34: =SUMIFS('Consolidado gerencial'!$H:$H,'Consolidado gerencial'!$B:$B,$B34,'Consolidado gerencial'!$A:$A,G$27) -> 755.25 | H34: =SUMIFS('Consolidado gerencial'!$H:$H,'Consolidado gerencial'!$B:$B,$B34,'Consolidado gerencial'!$A:$A,H$27) -> 532.48 | I34: =SUMIFS('Consolidado gerencial'!$H:$H,'Consolidado gerencial'!$B:$B,$B34,'Consolidado gerencial'!$A:$A,I$27) -> 1031.19 | J34: =SUMIFS('Consolidado gerencial'!$H:$H,'Consolidado gerencial'!$B:$B,$B34,'Consolidado gerencial'!$A:$A,J$27) -> 972.15 | ... N34: =SUMIFS('Consolidado gerencial'!$H:$H,'Consolidado gerencial'!$B:$B,$B34,'Consolidado gerencial'!$A:$A,N$27) -> 0
B35: JOÃO MARTINS NETO | C35: =SUMIFS('Consolidado gerencial'!$H:$H,'Consolidado gerencial'!$B:$B,$B35,'Consolidado gerencial'!$A:$A,C$27) -> 0 | D35: =SUMIFS('Consolidado gerencial'!$H:$H,'Consolidado gerencial'!$B:$B,$B35,'Consolidado gerencial'!$A:$A,D$27) -> 799.7 | E35: =SUMIFS('Consolidado gerencial'!$H:$H,'Consolidado gerencial'!$B:$B,$B35,'Consolidado gerencial'!$A:$A,E$27) -> 1599.29 | F35: =SUMIFS('Consolidado gerencial'!$H:$H,'Consolidado gerencial'!$B:$B,$B35,'Consolidado gerencial'!$A:$A,F$27) -> 1348.72 | G35: =SUMIFS('Consolidado gerencial'!$H:$H,'Consolidado gerencial'!$B:$B,$B35,'Consolidado gerencial'!$A:$A,G$27) -> 1227.54 | H35: =SUMIFS('Consolidado gerencial'!$H:$H,'Consolidado gerencial'!$B:$B,$B35,'Consolidado gerencial'!$A:$A,H$27) -> 1164.81 | I35: =SUMIFS('Consolidado gerencial'!$H:$H,'Consolidado gerencial'!$B:$B,$B35,'Consolidado gerencial'!$A:$A,I$27) -> 1541.07 | J35: =SUMIFS('Consolidado gerencial'!$H:$H,'Consolidado gerencial'!$B:$B,$B35,'Consolidado gerencial'!$A:$A,J$27) -> 1243.29 | ... N35: =SUMIFS('Consolidado gerencial'!$H:$H,'Consolidado gerencial'!$B:$B,$B35,'Consolidado gerencial'!$A:$A,N$27) -> 0
B36: GEOVANA DUARTE FARIAS | C36: =SUMIFS('Consolidado gerencial'!$H:$H,'Consolidado gerencial'!$B:$B,$B36,'Consolidado gerencial'!$A:$A,C$27) -> 0 | D36: =SUMIFS('Consolidado gerencial'!$H:$H,'Consolidado gerencial'!$B:$B,$B36,'Consolidado gerencial'!$A:$A,D$27) -> 0 | E36: =SUMIFS('Consolidado gerencial'!$H:$H,'Consolidado gerencial'!$B:$B,$B36,'Consolidado gerencial'!$A:$A,E$27) -> 0 | F36: =SUMIFS('Consolidado gerencial'!$H:$H,'Consolidado gerencial'!$B:$B,$B36,'Consolidado gerencial'!$A:$A,F$27) -> 0 | G36: =SUMIFS('Consolidado gerencial'!$H:$H,'Consolidado gerencial'!$B:$B,$B36,'Consolidado gerencial'!$A:$A,G$27) -> 0 | H36: =SUMIFS('Consolidado gerencial'!$H:$H,'Consolidado gerencial'!$B:$B,$B36,'Consolidado gerencial'!$A:$A,H$27) -> 0 | I36: =SUMIFS('Consolidado gerencial'!$H:$H,'Consolidado gerencial'!$B:$B,$B36,'Consolidado gerencial'!$A:$A,I$27) -> 1049.26 | J36: =SUMIFS('Consolidado gerencial'!$H:$H,'Consolidado gerencial'!$B:$B,$B36,'Consolidado gerencial'!$A:$A,J$27) -> 1040.58 | ... N36: =SUMIFS('Consolidado gerencial'!$H:$H,'Consolidado gerencial'!$B:$B,$B36,'Consolidado gerencial'!$A:$A,N$27) -> 0
B37: THAYS APARECIDA CARVALHO | C37: =SUMIFS('Consolidado gerencial'!$H:$H,'Consolidado gerencial'!$B:$B,$B37,'Consolidado gerencial'!$A:$A,C$27) -> 0 | D37: =SUMIFS('Consolidado gerencial'!$H:$H,'Consolidado gerencial'!$B:$B,$B37,'Consolidado gerencial'!$A:$A,D$27) -> 0 | E37: =SUMIFS('Consolidado gerencial'!$H:$H,'Consolidado gerencial'!$B:$B,$B37,'Consolidado gerencial'!$A:$A,E$27) -> 0 | F37: =SUMIFS('Consolidado gerencial'!$H:$H,'Consolidado gerencial'!$B:$B,$B37,'Consolidado gerencial'!$A:$A,F$27) -> 0 | G37: =SUMIFS('Consolidado gerencial'!$H:$H,'Consolidado gerencial'!$B:$B,$B37,'Consolidado gerencial'!$A:$A,G$27) -> 0 | H37: =SUMIFS('Consolidado gerencial'!$H:$H,'Consolidado gerencial'!$B:$B,$B37,'Consolidado gerencial'!$A:$A,H$27) -> 0 | I37: =SUMIFS('Consolidado gerencial'!$H:$H,'Consolidado gerencial'!$B:$B,$B37,'Consolidado gerencial'!$A:$A,I$27) -> 1170.96 | J37: =SUMIFS('Consolidado gerencial'!$H:$H,'Consolidado gerencial'!$B:$B,$B37,'Consolidado gerencial'!$A:$A,J$27) -> 1190.64 | ... N37: =SUMIFS('Consolidado gerencial'!$H:$H,'Consolidado gerencial'!$B:$B,$B37,'Consolidado gerencial'!$A:$A,N$27) -> 0
B38: SAIDDA KAULE ABDALA | C38: =SUMIFS('Consolidado gerencial'!$H:$H,'Consolidado gerencial'!$B:$B,$B38,'Consolidado gerencial'!$A:$A,C$27) -> 0 | D38: =SUMIFS('Consolidado gerencial'!$H:$H,'Consolidado gerencial'!$B:$B,$B38,'Consolidado gerencial'!$A:$A,D$27) -> 0 | E38: =SUMIFS('Consolidado gerencial'!$H:$H,'Consolidado gerencial'!$B:$B,$B38,'Consolidado gerencial'!$A:$A,E$27) -> 0 | F38: =SUMIFS('Consolidado gerencial'!$H:$H,'Consolidado gerencial'!$B:$B,$B38,'Consolidado gerencial'!$A:$A,F$27) -> 0 | G38: =SUMIFS('Consolidado gerencial'!$H:$H,'Consolidado gerencial'!$B:$B,$B38,'Consolidado gerencial'!$A:$A,G$27) -> 0 | H38: =SUMIFS('Consolidado gerencial'!$H:$H,'Consolidado gerencial'!$B:$B,$B38,'Consolidado gerencial'!$A:$A,H$27) -> 0 | I38: =SUMIFS('Consolidado gerencial'!$H:$H,'Consolidado gerencial'!$B:$B,$B38,'Consolidado gerencial'!$A:$A,I$27) -> 0 | J38: =SUMIFS('Consolidado gerencial'!$H:$H,'Consolidado gerencial'!$B:$B,$B38,'Consolidado gerencial'!$A:$A,J$27) -> 0 | ... N38: =SUMIFS('Consolidado gerencial'!$H:$H,'Consolidado gerencial'!$B:$B,$B38,'Consolidado gerencial'!$A:$A,N$27) -> 0
B39: SUELEN DOS SANTOS AZEVEDO | C39: =SUMIFS('Consolidado gerencial'!$H:$H,'Consolidado gerencial'!$B:$B,$B39,'Consolidado gerencial'!$A:$A,C$27) -> 471.9 | D39: =SUMIFS('Consolidado gerencial'!$H:$H,'Consolidado gerencial'!$B:$B,$B39,'Consolidado gerencial'!$A:$A,D$27) -> 0 | E39: =SUMIFS('Consolidado gerencial'!$H:$H,'Consolidado gerencial'!$B:$B,$B39,'Consolidado gerencial'!$A:$A,E$27) -> 0 | F39: =SUMIFS('Consolidado gerencial'!$H:$H,'Consolidado gerencial'!$B:$B,$B39,'Consolidado gerencial'!$A:$A,F$27) -> 0 | G39: =SUMIFS('Consolidado gerencial'!$H:$H,'Consolidado gerencial'!$B:$B,$B39,'Consolidado gerencial'!$A:$A,G$27) -> 0 | H39: =SUMIFS('Consolidado gerencial'!$H:$H,'Consolidado gerencial'!$B:$B,$B39,'Consolidado gerencial'!$A:$A,H$27) -> 0 | I39: =SUMIFS('Consolidado gerencial'!$H:$H,'Consolidado gerencial'!$B:$B,$B39,'Consolidado gerencial'!$A:$A,I$27) -> 0 | J39: =SUMIFS('Consolidado gerencial'!$H:$H,'Consolidado gerencial'!$B:$B,$B39,'Consolidado gerencial'!$A:$A,J$27) -> 0 | ... N39: =SUMIFS('Consolidado gerencial'!$H:$H,'Consolidado gerencial'!$B:$B,$B39,'Consolidado gerencial'!$A:$A,N$27) -> 0
... B43: BRENON LUCAS ALVES DE SOUZA | C43: =SUMIFS('Consolidado gerencial'!$H:$H,'Consolidado gerencial'!$B:$B,$B43,'Consolidado gerencial'!$A:$A,C$27) -> 0 | D43: =SUMIFS('Consolidado gerencial'!$H:$H,'Consolidado gerencial'!$B:$B,$B43,'Consolidado gerencial'!$A:$A,D$27) -> 264 | E43: =SUMIFS('Consolidado gerencial'!$H:$H,'Consolidado gerencial'!$B:$B,$B43,'Consolidado gerencial'!$A:$A,E$27) -> 0 | F43: =SUMIFS('Consolidado gerencial'!$H:$H,'Consolidado gerencial'!$B:$B,$B43,'Consolidado gerencial'!$A:$A,F$27) -> 0 | G43: =SUMIFS('Consolidado gerencial'!$H:$H,'Consolidado gerencial'!$B:$B,$B43,'Consolidado gerencial'!$A:$A,G$27) -> 0 | H43: =SUMIFS('Consolidado gerencial'!$H:$H,'Consolidado gerencial'!$B:$B,$B43,'Consolidado gerencial'!$A:$A,H$27) -> 448.95 | I43: =SUMIFS('Consolidado gerencial'!$H:$H,'Consolidado gerencial'!$B:$B,$B43,'Consolidado gerencial'!$A:$A,I$27) -> 226.32 | J43: =SUMIFS('Consolidado gerencial'!$H:$H,'Consolidado gerencial'!$B:$B,$B43,'Consolidado gerencial'!$A:$A,J$27) -> 0 | ... N43: =SUMIFS('Consolidado gerencial'!$H:$H,'Consolidado gerencial'!$B:$B,$B43,'Consolidado gerencial'!$A:$A,N$27) -> 0
C44: =SUMIFS('Consolidado gerencial'!$H:$H,'Consolidado gerencial'!$B:$B,$B44,'Consolidado gerencial'!$A:$A,C$27) -> 0 | D44: =SUMIFS('Consolidado gerencial'!$H:$H,'Consolidado gerencial'!$B:$B,$B44,'Consolidado gerencial'!$A:$A,D$27) -> 0 | E44: =SUMIFS('Consolidado gerencial'!$H:$H,'Consolidado gerencial'!$B:$B,$B44,'Consolidado gerencial'!$A:$A,E$27) -> 0 | F44: =SUMIFS('Consolidado gerencial'!$H:$H,'Consolidado gerencial'!$B:$B,$B44,'Consolidado gerencial'!$A:$A,F$27) -> 0 | G44: =SUMIFS('Consolidado gerencial'!$H:$H,'Consolidado gerencial'!$B:$B,$B44,'Consolidado gerencial'!$A:$A,G$27) -> 0 | H44: =SUMIFS('Consolidado gerencial'!$H:$H,'Consolidado gerencial'!$B:$B,$B44,'Consolidado gerencial'!$A:$A,H$27) -> 0 | I44: =SUMIFS('Consolidado gerencial'!$H:$H,'Consolidado gerencial'!$B:$B,$B44,'Consolidado gerencial'!$A:$A,I$27) -> 0 | J44: =SUMIFS('Consolidado gerencial'!$H:$H,'Consolidado gerencial'!$B:$B,$B44,'Consolidado gerencial'!$A:$A,J$27) -> 0 | ... N44: =SUMIFS('Consolidado gerencial'!$H:$H,'Consolidado gerencial'!$B:$B,$B44,'Consolidado gerencial'!$A:$A,N$27) -> 0
C45: =SUMIFS('Consolidado gerencial'!$H:$H,'Consolidado gerencial'!$B:$B,$B45,'Consolidado gerencial'!$A:$A,C$27) -> 0 | D45: =SUMIFS('Consolidado gerencial'!$H:$H,'Consolidado gerencial'!$B:$B,$B45,'Consolidado gerencial'!$A:$A,D$27) -> 0 | E45: =SUMIFS('Consolidado gerencial'!$H:$H,'Consolidado gerencial'!$B:$B,$B45,'Consolidado gerencial'!$A:$A,E$27) -> 0 | F45: =SUMIFS('Consolidado gerencial'!$H:$H,'Consolidado gerencial'!$B:$B,$B45,'Consolidado gerencial'!$A:$A,F$27) -> 0 | G45: =SUMIFS('Consolidado gerencial'!$H:$H,'Consolidado gerencial'!$B:$B,$B45,'Consolidado gerencial'!$A:$A,G$27) -> 0 | H45: =SUMIFS('Consolidado gerencial'!$H:$H,'Consolidado gerencial'!$B:$B,$B45,'Consolidado gerencial'!$A:$A,H$27) -> 0 | I45: =SUMIFS('Consolidado gerencial'!$H:$H,'Consolidado gerencial'!$B:$B,$B45,'Consolidado gerencial'!$A:$A,I$27) -> 0 | J45: =SUMIFS('Consolidado gerencial'!$H:$H,'Consolidado gerencial'!$B:$B,$B45,'Consolidado gerencial'!$A:$A,J$27) -> 0 | ... N45: =SUMIFS('Consolidado gerencial'!$H:$H,'Consolidado gerencial'!$B:$B,$B45,'Consolidado gerencial'!$A:$A,N$27) -> 0
B46: TOTAL GASTO | C46: =SUBTOTAL(109,Tabela46[JANEIRO]) -> 9613.98 | D46: =SUBTOTAL(109,Tabela46[FEVEREIRO]) -> 11746.9 | E46: =SUBTOTAL(109,Tabela46[MARÇO]) -> 12402.71 | F46: =SUBTOTAL(109,Tabela46[ABRIL]) -> 9567.26 | G46: =SUBTOTAL(109,Tabela46[MAIO]) -> 8901.29 | H46: =SUBTOTAL(109,Tabela46[JUNHO]) -> 9632.46 | I46: =SUBTOTAL(109,Tabela46[JULHO]) -> 10932.2 | J46: =SUBTOTAL(109,Tabela46[AGOSTO]) -> 10625.2 | K46: =SUBTOTAL(109,Tabela46[SETEMBRO]) -> 5567.61 | L46: =SUBTOTAL(109,Tabela46[OUTUBRO]) -> 0 | M46: =SUBTOTAL(109,Tabela46[NOVEMBRO]) -> 0 | N46: =SUBTOTAL(109,Tabela46[DEZEMBRO]) -> 0
B47: SALDO | C47: =C26-Tabela46[[#Totals],[JANEIRO]] -> -1363.98 | D47: =D26-Tabela46[[#Totals],[FEVEREIRO]] -> -436.9 | E47: =E26-Tabela46[[#Totals],[MARÇO]] -> -402.71 | F47: =F26-Tabela46[[#Totals],[ABRIL]] -> 32.74 | G47: =G26-Tabela46[[#Totals],[MAIO]] -> 98.71 | H47: =H26-Tabela46[[#Totals],[JUNHO]] -> -792.46 | I47: =I26-Tabela46[[#Totals],[JULHO]] -> -1332.2 | J47: =J26-Tabela46[[#Totals],[AGOSTO]] -> -1025.2 | K47: =K26-Tabela46[[#Totals],[SETEMBRO]] -> 3272.39 | L47: =L26-Tabela46[[#Totals],[OUTUBRO]] -> 0 | M47: =M26-Tabela46[[#Totals],[NOVEMBRO]] -> 0 | N47: =N26-Tabela46[[#Totals],[DEZEMBRO]] -> 0

Sheet HISTORICO
A1: 1ª Quinzena FEVEREIRO
A2: Matricula | B2: Nome | C2: Função | D2: C.Custo | E2: Valor KM | F2: Pedagio | G2: Estacionamento | H2: Diversas | I2: TT Reembolsavel | J2: Hotel | K2: Adiantamento | L2: Valor a depositar
B3: Vaga aberta Cascavel | D3: 2900 | E3: 0 | F3: 0 | G3: 0 | H3: 0 | I3: 0 | J3: 0 | L3: 0
A4: MZ-327676 | B4: LUCAS FELIPE FARIAS DE LIMA | D4: 2900 | E4: 544.5 | F4: 0 | G4: 0 | H4: 0 | I4: 544.5 | J4: 0 | L4: 544.5
A5: MZ-326274 | B5: NIVIA DE MELO PIORNEDO | D5: 2900 | E5: 543.4 | F5: 0 | G5: 0 | H5: 0 | I5: 543.4 | J5: 0 | L5: 543.4
A6: MZ-329693 | B6: FABRICIO DAMM ROSA | D6: 2902 | E6: 1031.8 | F6: 40 | G6: 4 | H6: 35 | I6: 1110.8 | J6: 195 | L6: 1110.8
A7: MZ-328805 | B7: CAROLINA SANTOS SCHWAMBACH | D7: 2902 | E7: 0 | F7: 0 | G7: 0 | H7: 0 | I7: 0 | J7: 0 | L7: 0
A8: MZ-327723 | B8: ANDERSON MICHALSKI FERREIRA | D8: 2902 | E8: 0 | F8: 0 | G8: 0 | H8: 0 | I8: 0 | J8: 0 | L8: 0
A9: MZ-326794 | B9: BRUNO REGGIORI ESCOBAR | D9: 2902 | E9: 555.5 | F9: 0 | G9: 36 | H9: 0 | I9: 591.5 | J9: 0 | L9: 591.5
A10: MZ-326305 | B10: TATIANA RIGHI DA FONSECA | D10: 2902 | E10: 258.5 | F10: 0 | G10: 0 | H10: 0 | I10: 258.5 | J10: 0 | L10: 258.5
A11: MZ-329003 | B11: LEANDRO ROBERTO SILVEIRA | D11: 2901 | E11: 1003.2 | F11: 0 | G11: 0 | H11: 0 | I11: 1003.2 | J11: 0 | L11: 1003.2
A12: MZ-325697 | B12: GEOVANA DUARTE FARIAS | D12: 2901 | E12: 694.1 | F12: 0 | G12: 0 | H12: 0 | I12: 694.1 | J12: 0 | L12: 694.1
A13: MZ-324928 | B13: DESYREE YASMIN GAULKE KLEBBER | D13: 2901 | E13: 568.7 | F13: 0 | G13: 0 | H13: 0 | I13: 568.7 | J13: 0 | L13: 568.7
I14: =SUM(I3:I13) -> 5314.7 | J14: =SUM(J3:J13) -> 195 | L14: =SUM(L3:L13) -> 5314.7
A17: 2ª Quinzena FEVEREIRO
A18: Matricula | B18: Nome | C18: Função | E18: Valor KM | F18: Pedagio | G18: Estacionamento | H18: Diversas | I18: TT Reembolsavel | J18: Hotel | K18: Adiantamento | L18: Valor a depositar
B19: Vaga aberta PR SUL | D19: 2900 | E19: 0 | F19: 0 | G19: 0 | H19: 0 | I19: 0 | J19: 0 | L19: 0
A20: MZ-327676 | B20: LUCAS FELIPE FARIAS DE LIMA | D20: 2900 | E20: 546.7 | F20: 0 | G20: 0 | H20: 0 | I20: 546.7 | J20: 0 | K20: 500 | L20: 46.7
A21: MZ-326274 | B21: NIVIA DE MELO PIORNEDO | D21: 2900 | E21: 761.2 | F21: 0 | G21: 0 | H21: 0 | I21: 761.2 | J21: 0 | K21: 500 | L21: 261.2
A22: MZ-329693 | B22: FABRICIO DAMM ROSA | D22: 2902 | E22: 378.4 | F22: 10 | G22: 8 | H22: 19.9 | I22: 416.3 | J22: 0 | K22: 500 | L22: -83.7
A23: MZ-328805 | B23: CAROLINA SANTOS SCHWAMBACH | D23: 2902 | E23: 0 | F23: 0 | G23: 0 | H23: 0 | I23: 0 | J23: 0 | L23: 0
A24: MZ-327723 | B24: ANDERSON MICHALSKI FERREIRA | D24: 2902 | E24: 0 | F24: 0 | G24: 0 | H24: 0 | I24: 0 | J24: 0 | L24: 0
A25: MZ-326794 | B25: BRUNO REGGIORI ESCOBAR | D25: 2902 | E25: 138.6 | F25: 0 | G25: 10 | H25: 0 | I25: 148.6 | J25: 0 | K25: 500 | L25: -351.4
A26: MZ-326305 | B26: TATIANA RIGHI DA FONSECA | D26: 2902 | E26: 698.5 | F26: 0 | G26: 0 | H26: 0 | I26: 698.5 | J26: 0 | K26: 500 | L26: 198.5
A27: MZ-329003 | B27: LEANDRO ROBERTO SILVEIRA | D27: 2901 | E27: 840.4 | F27: 10.4 | G27: 0 | H27: 0 | I27: 850.8 | J27: 0 | K27: 500 | L27: 350.8
A28: MZ-325697 | B28: GEOVANA DUARTE FARIAS | D28: 2901 | E28: 594 | F28: 0 | G28: 50.5 | H28: 0 | I28: 644.5 | J28: 0 | K28: 500 | L28: 144.5
A29: MZ-324928 | B29: DESYREE YASMIN GAULKE KLEBBER | D29: 2901 | E29: 330 | F29: 0 | G29: 0 | H29: 0 | I29: 330 | J29: 0 | K29: 500 | L29: -170
A30: MZ-328852 | B30: ELAINE CRISTINA CALBAL | D30: 2900 | E30: 0 | F30: 0 | G30: 0 | H30: 0 | I30: 0 | J30: 0 | L30: 0
A31: MZ-328353 | B31: CARLOS EDUARDO FONTOURA PROENCA | D31: 2901 | E31: 0 | F31: 0 | G31: 0 | H31: 0 | I31: 0 | J31: 0 | L31: 0
I32: =SUM(I19:I31) -> 4396.6 | J32: =SUM(J19:J31) -> 0 | L32: =SUM(L19:L31) -> 396.6
A35: 1ª Quinzena MARÇO | J35: Não precisa reembolso
A36: Matricula | B36: Nome | C36: Função | D36: C.Custo | E36: Valor KM | F36: Pedagio | G36: Estacionamento | H36: Diversas | I36: TT Reembolsavel | J36: Hotel | K36: Adiantamento / Saldo | L36: Valor a depositar
A37: MZ-331244 | B37: LUCAS AZEREDO DA SILVA | D37: 2900 | E37: 0 | F37: 0 | G37: 0 | H37: 0 | I37: 0 | J37: 0 | K37: 500 | L37: 500
A38: MZ-327676 | B38: LUCAS FELIPE FARIAS DE LIMA | D38: 2900 | E38: 708.4 | F38: 0 | G38: 0 | H38: 0 | I38: 708.4 | J38: 0 | L38: 708.4
A39: MZ-326274 | B39: NIVIA DE MELO PIORNEDO | D39: 2900 | E39: 0 | F39: 0 | G39: 0 | H39: 0 | I39: 0 | J39: 0 | L39: 0
A40: MZ-324928 | B40: DESYREE YASMIN GAULKE KLEBBER | D40: 2901 | E40: 368.5 | F40: 0 | G40: 0 | H40: 0 | I40: 368.5 | J40: 0 | K40: -170 | L40: 198.5
A41: MZ-325697 | B41: GEOVANA DUARTE FARIAS | D41: 2901 | E41: 438.9 | F41: 0 | G41: 0 | H41: 0 | I41: 438.9 | J41: 0 | L41: 438.9
A42: MZ-329003 | B42: LEANDRO ROBERTO SILVEIRA | D42: 2901 | E42: 695.2 | F42: 0 | G42: 0 | H42: 0 | I42: 695.2 | J42: 0 | L42: 695.2
A43: MZ-327723 | B43: ANDERSON MICHALSKI FERREIRA | D43: 2902 | E43: 0 | F43: 0 | G43: 0 | H43: 0 | I43: 0 | J43: 0 | L43: 0
A44: MZ-326794 | B44: BRUNO REGGIORI ESCOBAR | D44: 2902 | E44: 776.6 | F44: 0 | G44: 12 | H44: 20 | I44: 808.6 | J44: 0 | K44: -351.4 | L44: 457.2
A45: MZ-328805 | B45: CAROLINA SANTOS SCHWAMBACH | D45: 2902 | E45: 0 | F45: 0 | G45: 0 | H45: 0 | I45: 0 | J45: 0 | L45: 0
A46: MZ-329693 | B46: FABRICIO DAMM ROSA | D46: 2902 | E46: 838.2 | F46: 40 | G46: 0 | H46: 4 | I46: 882.2 | J46: 0 | K46: -83.7 | L46: 798.5
A47: MZ-326305 | B47: TATIANA RIGHI DA FONSECA | D47: 2902 | E47: 595.1 | F47: 12.6 | G47: 0 | H47: 0 | I47: 607.7 | J47: 0 | L47: 607.7
A48: MZ-328852 | B48: ELAINE CRISTINA CALBAL | D48: 2900 | E48: 0 | F48: 0 | G48: 0 | H48: 0 | I48: 0 | J48: 0 | L48: 0
A49: MZ-328353 | B49: CARLOS EDUARDO FONTOURA PROENCA | D49: 2902 | E49: 16.5 | F49: 0 | G49: 0 | H49: 0 | I49: 16.5 | J49: 0 | L49: 16.5
I50: =SUM(I37:I49) -> 4526 | J50: =SUM(J37:J49) -> 0 | L50: =SUM(L37:L49) -> 4420.9
A53: 2ª Quinzena MARÇO | J53: Não precisa reembolso
A54: Matricula | B54: Nome | C54: Função | D54: C.Custo | E54: Valor KM | F54: Pedagio | G54: Estacionamento | H54: Diversas | I54: TT Reembolsavel | J54: Hotel | K54: Adiantamento / Saldo | L54: Valor a depositar
A55: MZ-331244 | B55: LUCAS AZEREDO DA SILVA | D55: 2900 | E55: 113.3 | F55: 0 | G55: 0 | H55: 30 | I55: 143.3 | J55: 0 | K55: 1000 | L55: 1143.3
A56: MZ-327676 | B56: LUCAS FELIPE FARIAS DE LIMA | D56: 2900 | E56: 374 | F56: 0 | G56: 0 | H56: 0 | I56: 374 | J56: 0 | L56: 374
A57: MZ-326274 | B57: NIVIA DE MELO PIORNEDO | D57: 2900 | E57: 693 | F57: 0 | G57: 0 | H57: 0 | I57: 693 | J57: 0 | L57: 693
A58: MZ-324928 | B58: DESYREE YASMIN GAULKE KLEBBER | D58: 2901 | E58: 104.5 | F58: 0 | G58: 0 | H58: 0 | I58: 104.5 | J58: 0 | L58: 104.5
A59: MZ-325697 | B59: GEOVANA DUARTE FARIAS | D59: 2901 | E59: 0 | F59: 0 | G59: 0 | H59: 0 | I59: 0 | J59: 0 | L59: 0
A60: MZ-329003 | B60: LEANDRO ROBERTO SILVEIRA | D60: 2901 | E60: 730.4 | F60: 0 | G60: 0 | H60: 0 | I60: 730.4 | J60: 0 | L60: 730.4
A61: MZ-327723 | B61: ANDERSON MICHALSKI FERREIRA | D61: 2902 | E61: 0 | F61: 0 | G61: 0 | H61: 0 | I61: 0 | J61: 0 | L61: 0
A62: MZ-326794 | B62: BRUNO REGGIORI ESCOBAR | D62: 2902 | E62: 0 | F62: 0 | G62: 0 | H62: 0 | I62: 0 | J62: 0 | L62: 0
A63: MZ-328805 | B63: CAROLINA SANTOS SCHWAMBACH | D63: 2902 | E63: 0 | F63: 0 | G63: 0 | H63: 0 | I63: 0 | J63: 0 | L63: 0
A64: MZ-329693 | B64: FABRICIO DAMM ROSA | D64: 2902 | E64: 1905.2 | F64: 108.4 | G64: 25 | H64: 105 | I64: 2143.6 | J64: 629 | K64: -1000 | L64: 1143.6
A65: MZ-326305 | B65: TATIANA RIGHI DA FONSECA | D65: 2902 | E65: 627 | F65: 0 | G65: 0 | H65: 0 | I65: 627 | J65: 0 | L65: 627
A66: MZ-328852 | B66: ELAINE CRISTINA CALBAL | D66: 2900 | E66: 0 | F66: 0 | G66: 0 | H66: 0 | I66: 0 | J66: 0 | L66: 0
A67: MZ-328353 | B67: CARLOS EDUARDO FONTOURA PROENCA | D67: 2902 | E67: 0 | F67: 0 | G67: 0 | H67: 0 | I67: 0 | J67: 0 | L67: 0
L68: 4815.8
A70: 1ª Quinzena ABRIL | J70: Não precisa reembolso
A71: Matricula | B71: Nome | C71: Função | D71: C.Custo | E71: Valor KM | F71: Pedagio | G71: Estacionamento | H71: Diversas | I71: TT Reembolsavel | J71: Hotel | K71: Adiantamento / Saldo | L71: Valor a depositar
A72: MZ-328852 | B72: ELAINE CRISTINA CALBAL | D72: 2900 | E72: 0 | F72: 0 | G72: 0 | H72: 0 | I72: 0 | J72: 0 | L72: 0
A73: MZ-331244 | B73: LUCAS AZEREDO DA SILVA | D73: 2900 | E73: 1576.3 | F73: 0 | G73: 0 | H73: 36 | I73: 1612.3 | J73: 180 | K73: -1000 | L73: 612.3
A74: MZ-327676 | B74: LUCAS FELIPE FARIAS DE LIMA | D74: 2900 | E74: 816.2 | F74: 0 | G74: 0 | H74: 0 | I74: 816.2 | J74: 0 | L74: 816.2
A75: MZ-326274 | B75: NIVIA DE MELO PIORNEDO | D75: 2900 | E75: 295.9 | F75: 0 | G75: 0 | H75: 0 | I75: 295.9 | J75: 0 | L75: 295.9 | N75: MZ-326274 | O75: NIVIA DE MELO PIORNEDO | P75: 2900 | Q75: 625.9 | R75: 0 | S75: 0 | T75: 0 | U75: 625.9
